Workbook
Name INVEST_TOTAL: 'Investimento (CAPEX)'!$E$85

Sheet Leia-me
A1: DiscoverON — Projeção e acompanhamento financeiro (v6 · 08/09/2026)
A3: AS ABAS, NA ORDEM DE USO
A4: 1. PREMISSAS — preços, equipe (com mês de entrada), professores, sazonalidade, CAC, tabela do Simples e custos padrão. Edite só as células amarelas.
A5: 2. CUSTOS MÊS A MÊS — cada custo por período. Digite por cima para variar um mês (ex.: pró-labore só de fev, marketing maior na abertura).
A6: 3. CENÁRIOS (Pessimista / Moderado / Otimista) e SIMULADOR — projeção mês a mês.
A7: 4. CUSTOS DE IMPLANTAÇÃO (aba vermelha) — livro de lançamentos da obra/abertura, cada gasto com categoria, tipo, fornecedor e status.
A8: 5. ANÁLISE DE CUSTOS (aba roxa) — para onde o dinheiro foi: totais por categoria e tipo, matriz cruzada, pago × previsto e gráficos.
A9: 6. REALIZADO (verde) e PLANO × REAL (laranja) — o dia a dia da operação depois de aberta.
A10: 7. PAINEL DO MÊS (azul) — escolha o período e veja plano × real com alertas.
A11: 8. INVESTIMENTO (CAPEX) e RESUMO.
A13: NOVIDADES DESTA VERSÃO
A14: • MARKETING → CAC → MATRÍCULAS: nas Premissas, escolha a origem das matrículas. No modo 2, cada cenário calcula as matrículas do mês dividindo o marketing daquele período (aba 'Custos mês a mês') pelo CAC. Ex.: R$ 6.000 com CAC de R$ 200 = 30 matrículas — e todos os totais se ajustam sozinhos.
... A28: ⚠ As fórmulas estão protegidas: só as células amarelas aceitam edição. Para liberar: Revisão > Desproteger Planilha (sem senha).

Sheet Premissas
A1: PREMISSAS — edite as células amarelas
A2: Mensalidade — curso (por aluno) | B2: 280
A3: Matrícula (por aluno novo) | B3: 200
A4: Material — preço de venda (12x no cartão) | B4: 900
A5: Material — recebido à vista com antecipação | B5: 810 | E5: ~10% de taxa de antecipação do cartão.
A6: Material — custo por aluno (pago em 12x) | B6: 375
A7: Taxas do modelo
A8: Desistência mensal (% da base) | B8: 0.1
A9: Inadimplência (% da mensalidade) | B9: 0.1
A10: Comissão do vendedor por matrícula | B10: 40 | E10: Só o vendedor recebe comissão; conta a partir do mês em que ele entra.
A11: Encargos mensais sobre CLT (FGTS e provisões) | B11: 0.1 | E11: No Simples o INSS patronal já está no DAS. 13º e férias saem como desembolso próprio.
A12: Vale-transporte / benefícios por CLT (R$/mês) | B12: 200
A13: Equipe — salário, vínculo e mês de entrada | B13: Salário | C13: CLT? 1/0 | D13: Entra no período
A14: Vendedor (recebe a comissão) | B14: 2100 | C14: 1 | D14: 2 | E14: Período: 0 = Out (obras) · 1 = Nov (obras) · 2 = Dez (M1, abertura) · 3 = Jan (M2) … 17 = Mar (M16).
A15: Recepção | B15: 2000 | C15: 1 | D15: 2
A16: Estagiário | B16: 1200 | C16: 0 | D16: 2
A17: Administrador | B17: 6000 | C17: 0 | D17: 2
A18: Auxiliar de limpeza | B18: 1500 | C18: 1 | D18: 2
A19: (livre — adicione aqui) | B19: 0 | C19: 1 | D19: 2
A20: (livre) | B20: 0 | C20: 1 | D20: 2
A21: Folha com todos ativos (referência) | B21: =SUMPRODUCT($B$14:$B$20,1+$C$14:$C$20*$B$11)
A22: Professores — dimensionados pela capacidade das salas
A23: Professor CLT (salário base, cada) | B23: 1200
A24: Carga contratada (h-aula/semana) | B24: 20
A25: Coeficiente de aproveitamento da grade | B25: 0.7 | E25: A demanda concentra nos horários de pico.
A26: Salas de inglês | B26: 4
A27: Capacidade da sala de inglês | B27: 8
A28: Aulas de inglês por aluno (h/semana) | B28: 2
A29: Salas de informática | B29: 1
A30: Capacidade da sala de informática | B30: 10
A31: Aulas de informática por aluno (h/semana) | B31: 1
A32: Horas de aula por dia (9h–20h, exceto 12h–13h) | B32: 10
A33: Dias de aula por semana | B33: 5
A34: Horas-aula efetivas por professor/semana | B34: =B24*B25
A35: Custo por professor/mês (salário + encargos) | B35: =B23*(1+B11)
A36: Teto físico de alunos pelas salas | B36: =MIN(B26*B32*B33*B25/B28*B27,B29*B32*B33*B25/B31*B30)
A37: % dos alunos que fazem inglês | B37: 1
A38: % dos alunos que fazem informática | B38: 1
A40: 13º e férias — saem do caixa concentrados
A41: Pagar 13º em dezembro? (1 = sim) | B41: 1 | E41: Proporcional aos meses trabalhados no ano civil.
A42: Pagar férias + 1/3 ao completar 12 meses? (1 = sim) | B42: 1
A44: Sazonalidade — multiplicador do churn por mês
A45: Janeiro | B45: 1.5 | E45: 1,00× = churn normal. Jan e jul são férias: mais desistências.
A46: Fevereiro | B46: 1
A47: Março | B47: 1
A48: Abril | B48: 1
A49: Maio | B49: 1
A50: Junho | B50: 1.1
A51: Julho | B51: 1.4
A52: Agosto | B52: 1
A53: Setembro | B53: 1
A54: Outubro | B54: 1
A55: Novembro | B55: 1
A56: Dezembro | B56: 1.2
A58: Marketing e CAC — quanto investimento vira matrícula
A59: Origem das matrículas (1 = digito eu · 2 = marketing ÷ CAC · 3 = soma dos canais) | B59: 1 | E59: Modo 2: matrículas = marketing do período ÷ CAC. Modo 3: matrículas = soma da aba 'Canais de aquisição'.
A60: CAC — custo de aquisição por aluno (R$) | B60: 200 | E60: Ex.: R$ 6.000 de marketing com CAC de R$ 200 = 30 matrículas no mês.
E61: No modo 2, lance marketing também em out/nov na aba 'Custos mês a mês' — sem verba nesses meses a pré-venda fica zerada.
A62: Reserva para imprevistos da obra (% sobre reforma + abertura) | B62: 0.15
A64: Simples Nacional — tabela progressiva (Anexo III)
A65: Faixa | B65: RBT12 até | C65: Alíquota | D65: Dedução
A66: Faixa 1 | B66: 180000 | C66: 0.06 | D66: 0 | E66: Alíquota EFETIVA = (RBT12 × alíquota − dedução) ÷ RBT12. Empresa nova: RBT12 proporcionalizado. CONFIRME o anexo com o contador.
A67: Faixa 2 | B67: 360000 | C67: 0.112 | D67: 9360
A68: Faixa 3 | B68: 720000 | C68: 0.135 | D68: 17640
A69: Faixa 4 | B69: 1800000 | C69: 0.16 | D69: 35640
A70: Faixa 5 | B70: 3600000 | C70: 0.21 | D70: 125640
A71: Faixa 6 | B71: 4800000 | C71: 0.33 | D71: 648000
A73: Custos — valor padrão (a aba 'Custos mês a mês' varia por período)
A74: Aluguel do espaço | B74: 12000
A75: Água | B75: 300
A76: Luz | B76: 1000
A77: Telefone | B77: 0
A78: Internet | B78: 200
A79: Sistema de gestão DiscoverON | B79: 127
A80: Itens para aula | B80: 500
A81: Materiais de limpeza + higiene | B81: 250
A82: Brindes | B82: 300
A83: Marketing | B83: 750
A84: Aluguel dos computadores | B84: 2720
A85: Seguro empresarial | B85: 200
... A88: Pró-labore | B88: 0
A90: Break-even de alunos (mensalidade − professores) | B90: =ROUNDUP((SUM(B74:B88)+B21+SUMPRODUCT(($C$14:$C$20)*($B$14:$B$20>0))*B12)/((B2*(1-B9)-B2*'Cenário Moderado'!$S$20)-(B28/B27+B31/B30)*B35/B34),0) | E90: Usa a alíquota efetiva já madura (último mês do Moderado), não os 6% da 1ª faixa.

Sheet Custos mês a mês
A1: Custos por período — sobrescreva qualquer célula | B1: Out (obras) | C1: Nov (obras) | D1: Dez (M1) | E1: Jan (M2) | F1: Fev (M3) | G1: Mar (M4) | H1: Abr (M5) | I1: Mai (M6) | J1: Jun (M7) | K1: Jul (M8) | L1: Ago (M9) | M1: Set (M10) | N1: Out (M11) | O1: Nov (M12) | P1: Dez (M13) | Q1: Jan (M14) | R1: Fev (M15) | S1: Mar (M16)
A2: Aluguel do espaço | B2: 0 | C2: 0 | D2: =Premissas!$B$74 | E2: =Premissas!$B$74 | F2: =Premissas!$B$74 | G2: =Premissas!$B$74 | H2: =Premissas!$B$74 | I2: =Premissas!$B$74 | J2: =Premissas!$B$74 | K2: =Premissas!$B$74 | ... S2: =Premissas!$B$74
A3: Água | B3: 0 | C3: 0 | D3: =Premissas!$B$75 | E3: =Premissas!$B$75 | F3: =Premissas!$B$75 | G3: =Premissas!$B$75 | H3: =Premissas!$B$75 | I3: =Premissas!$B$75 | J3: =Premissas!$B$75 | K3: =Premissas!$B$75 | ... S3: =Premissas!$B$75
A4: Luz | B4: 0 | C4: 0 | D4: =Premissas!$B$76 | E4: =Premissas!$B$76 | F4: =Premissas!$B$76 | G4: =Premissas!$B$76 | H4: =Premissas!$B$76 | I4: =Premissas!$B$76 | J4: =Premissas!$B$76 | K4: =Premissas!$B$76 | ... S4: =Premissas!$B$76
A5: Telefone | B5: 0 | C5: 0 | D5: =Premissas!$B$77 | E5: =Premissas!$B$77 | F5: =Premissas!$B$77 | G5: =Premissas!$B$77 | H5: =Premissas!$B$77 | I5: =Premissas!$B$77 | J5: =Premissas!$B$77 | K5: =Premissas!$B$77 | ... S5: =Premissas!$B$77
A6: Internet | B6: 0 | C6: 0 | D6: =Premissas!$B$78 | E6: =Premissas!$B$78 | F6: =Premissas!$B$78 | G6: =Premissas!$B$78 | H6: =Premissas!$B$78 | I6: =Premissas!$B$78 | J6: =Premissas!$B$78 | K6: =Premissas!$B$78 | ... S6: =Premissas!$B$78
A7: Sistema de gestão DiscoverON | B7: 0 | C7: 0 | D7: =Premissas!$B$79 | E7: =Premissas!$B$79 | F7: =Premissas!$B$79 | G7: =Premissas!$B$79 | H7: =Premissas!$B$79 | I7: =Premissas!$B$79 | J7: =Premissas!$B$79 | K7: =Premissas!$B$79 | ... S7: =Premissas!$B$79
A8: Itens para aula | B8: 0 | C8: 0 | D8: =Premissas!$B$80 | E8: =Premissas!$B$80 | F8: =Premissas!$B$80 | G8: =Premissas!$B$80 | H8: =Premissas!$B$80 | I8: =Premissas!$B$80 | J8: =Premissas!$B$80 | K8: =Premissas!$B$80 | ... S8: =Premissas!$B$80
A9: Materiais de limpeza + higiene | B9: 0 | C9: 0 | D9: =Premissas!$B$81 | E9: =Premissas!$B$81 | F9: =Premissas!$B$81 | G9: =Premissas!$B$81 | H9: =Premissas!$B$81 | I9: =Premissas!$B$81 | J9: =Premissas!$B$81 | K9: =Premissas!$B$81 | ... S9: =Premissas!$B$81
A10: Brindes | B10: 0 | C10: 0 | D10: =Premissas!$B$82 | E10: =Premissas!$B$82 | F10: =Premissas!$B$82 | G10: =Premissas!$B$82 | H10: =Premissas!$B$82 | I10: =Premissas!$B$82 | J10: =Premissas!$B$82 | K10: =Premissas!$B$82 | ... S10: =Premissas!$B$82
A11: Marketing | B11: 0 | C11: 0 | D11: =Premissas!$B$83 | E11: =Premissas!$B$83 | F11: =Premissas!$B$83 | G11: =Premissas!$B$83 | H11: =Premissas!$B$83 | I11: =Premissas!$B$83 | J11: =Premissas!$B$83 | K11: =Premissas!$B$83 | ... S11: =Premissas!$B$83
A12: Aluguel dos computadores | B12: 0 | C12: 0 | D12: =Premissas!$B$84 | E12: =Premissas!$B$84 | F12: =Premissas!$B$84 | G12: =Premissas!$B$84 | H12: =Premissas!$B$84 | I12: =Premissas!$B$84 | J12: =Premissas!$B$84 | K12: =Premissas!$B$84 | ... S12: =Premissas!$B$84
A13: Seguro empresarial | B13: 0 | C13: 0 | D13: =Premissas!$B$85 | E13: =Premissas!$B$85 | F13: =Premissas!$B$85 | G13: =Premissas!$B$85 | H13: =Premissas!$B$85 | I13: =Premissas!$B$85 | J13: =Premissas!$B$85 | K13: =Premissas!$B$85 | ... S13: =Premissas!$B$85
A14: Taxas bancárias + gasolina | B14: 0 | C14: 0 | D14: =Premissas!$B$86 | E14: =Premissas!$B$86 | F14: =Premissas!$B$86 | G14: =Premissas!$B$86 | H14: =Premissas!$B$86 | I14: =Premissas!$B$86 | J14: =Premissas!$B$86 | K14: =Premissas!$B$86 | ... S14: =Premissas!$B$86
A15: Custos operacionais (contab., manut., licenças…) | B15: 0 | C15: 0 | D15: =Premissas!$B$87 | E15: =Premissas!$B$87 | F15: =Premissas!$B$87 | G15: =Premissas!$B$87 | H15: =Premissas!$B$87 | I15: =Premissas!$B$87 | J15: =Premissas!$B$87 | K15: =Premissas!$B$87 | ... S15: =Premissas!$B$87
A16: Pró-labore | B16: 0 | C16: 0 | D16: =Premissas!$B$88 | E16: =Premissas!$B$88 | F16: =Premissas!$B$88 | G16: =Premissas!$B$88 | H16: =Premissas!$B$88 | I16: =Premissas!$B$88 | J16: =Premissas!$B$88 | K16: =Premissas!$B$88 | ... S16: =Premissas!$B$88
A17: Total de custos do período | B17: =SUM(B2:B16) | C17: =SUM(C2:C16) | D17: =SUM(D2:D16) | E17: =SUM(E2:E16) | F17: =SUM(F2:F16) | G17: =SUM(G2:G16) | H17: =SUM(H2:H16) | I17: =SUM(I2:I16) | ... S17: =SUM(S2:S16)
A19: Out e Nov vêm zerados (obras). Do M1 em diante puxam o padrão das Premissas — digite por cima para variar o mês.
A20: A linha 11 (Marketing) alimenta o cálculo de matrículas quando o modo CAC está ligado nas Premissas.

Sheet Canais de aquisição
A1: CANAIS DE AQUISIÇÃO — de onde vem cada aluno | B1: CAC (R$) | C1: Out (obras) | D1: Nov (obras) | E1: Dez (M1) | F1: Jan (M2) | G1: Fev (M3) | H1: Mar (M4) | I1: Abr (M5) | J1: Mai (M6) | K1: Jun (M7) | L1: Jul (M8) | M1: Ago (M9) | N1: Set (M10) | O1: Out (M11) | P1: Nov (M12) | Q1: Dez (M13) | R1: Jan (M14) | S1: Fev (M15) | T1: Mar (M16)
A2: Passantes / fachada | B2: 0 | C2: 2 | D2: 11 | E2: 4 | F2: 10 | G2: 10 | H2: 6 | I2: 6 | J2: 6 | K2: 6 | L2: 10 | M2: 10 | N2: 6 | O2: 6 | P2: 10 | Q2: 10 | R2: 6 | S2: 10 | T2: 6
A3: Indicação de aluno | B3: 50 | C3: 1 | D3: 8 | E3: 3 | F3: 7 | G3: 7 | H3: 4 | I3: 4 | J3: 4 | K3: 4 | L3: 7 | M3: 7 | N3: 4 | O3: 4 | P3: 7 | Q3: 7 | R3: 4 | S3: 7 | T3: 4
A4: Tráfego pago | B4: 250 | C4: 1 | D4: 13 | E4: 5 | F4: 10 | G4: 10 | H4: 7 | I4: 7 | J4: 7 | K4: 7 | L4: 10 | M4: 10 | N4: 7 | O4: 7 | P4: 10 | Q4: 10 | R4: 7 | S4: 10 | T4: 7
A5: Redes sociais (orgânico) | B5: 0 | C5: 0 | D5: 1 | E5: 1 | F5: 1 | G5: 1 | H5: 1 | I5: 1 | J5: 1 | K5: 1 | L5: 1 | M5: 1 | N5: 1 | O5: 1 | P5: 1 | Q5: 1 | R5: 1 | S5: 1 | T5: 1
A6: Parcerias / escolas | B6: 80 | C6: 0 | D6: 1 | E6: 0 | F6: 1 | G6: 1 | H6: 1 | I6: 1 | J6: 1 | K6: 1 | L6: 1 | M6: 1 | N6: 1 | O6: 1 | P6: 1 | Q6: 1 | R6: 1 | S6: 1 | T6: 1
A7: Eventos / panfletagem | B7: 120 | C7: 0 | D7: 1 | E7: 0 | F7: 1 | G7: 1 | H7: 1 | I7: 1 | J7: 1 | K7: 1 | L7: 1 | M7: 1 | N7: 1 | O7: 1 | P7: 1 | Q7: 1 | R7: 1 | S7: 1 | T7: 1
A8: Outros | B8: 0 | C8: 0 | D8: 0 | E8: 0 | F8: 0 | G8: 0 | H8: 0 | I8: 0 | J8: 0 | K8: 0 | L8: 0 | M8: 0 | N8: 0 | O8: 0 | P8: 0 | Q8: 0 | R8: 0 | S8: 0 | T8: 0
A9: Total de matrículas do mês | C9: =SUM(C2:C8) | D9: =SUM(D2:D8) | E9: =SUM(E2:E8) | F9: =SUM(F2:F8) | G9: =SUM(G2:G8) | H9: =SUM(H2:H8) | I9: =SUM(I2:I8) | J9: =SUM(J2:J8) | ... T9: =SUM(T2:T8)
A10: Custo de aquisição do mês | C10: =SUMPRODUCT(C$2:C$8,$B$2:$B$8) | D10: =SUMPRODUCT(D$2:D$8,$B$2:$B$8) | E10: =SUMPRODUCT(E$2:E$8,$B$2:$B$8) | F10: =SUMPRODUCT(F$2:F$8,$B$2:$B$8) | G10: =SUMPRODUCT(G$2:G$8,$B$2:$B$8) | H10: =SUMPRODUCT(H$2:H$8,$B$2:$B$8) | I10: =SUMPRODUCT(I$2:I$8,$B$2:$B$8) | J10: =SUMPRODUCT(J$2:J$8,$B$2:$B$8) | ... T10: =SUMPRODUCT(T$2:T$8,$B$2:$B$8)
A11: CAC médio do mês | C11: =IF(C9=0,0,C10/C9) | D11: =IF(D9=0,0,D10/D9) | E11: =IF(E9=0,0,E10/E9) | F11: =IF(F9=0,0,F10/F9) | G11: =IF(G9=0,0,G10/G9) | H11: =IF(H9=0,0,H10/H9) | I11: =IF(I9=0,0,I10/I9) | J11: =IF(J9=0,0,J10/J9) | ... T11: =IF(T9=0,0,T10/T9)
A13: RETORNO POR CANAL (todo o horizonte)
A14: Canal | B14: Alunos | C14: % das matrículas | D14: Investido | E14: CAC realizado | F14: Alunos por R$ 1.000
A15: =A2 | B15: =SUM(C2:T2) | C15: =IF(SUM($B$15:$B$21)=0,0,B15/SUM($B$15:$B$21)) | D15: =B15*$B$2 | E15: =IF(B15=0,0,D15/B15) | F15: =IF(D15=0,"— (orgânico)",B15/(D15/1000))
A16: =A3 | B16: =SUM(C3:T3) | C16: =IF(SUM($B$15:$B$21)=0,0,B16/SUM($B$15:$B$21)) | D16: =B16*$B$3 | E16: =IF(B16=0,0,D16/B16) | F16: =IF(D16=0,"— (orgânico)",B16/(D16/1000))
A17: =A4 | B17: =SUM(C4:T4) | C17: =IF(SUM($B$15:$B$21)=0,0,B17/SUM($B$15:$B$21)) | D17: =B17*$B$4 | E17: =IF(B17=0,0,D17/B17) | F17: =IF(D17=0,"— (orgânico)",B17/(D17/1000))
A18: =A5 | B18: =SUM(C5:T5) | C18: =IF(SUM($B$15:$B$21)=0,0,B18/SUM($B$15:$B$21)) | D18: =B18*$B$5 | E18: =IF(B18=0,0,D18/B18) | F18: =IF(D18=0,"— (orgânico)",B18/(D18/1000))
A19: =A6 | B19: =SUM(C6:T6) | C19: =IF(SUM($B$15:$B$21)=0,0,B19/SUM($B$15:$B$21)) | D19: =B19*$B$6 | E19: =IF(B19=0,0,D19/B19) | F19: =IF(D19=0,"— (orgânico)",B19/(D19/1000))
A20: =A7 | B20: =SUM(C7:T7) | C20: =IF(SUM($B$15:$B$21)=0,0,B20/SUM($B$15:$B$21)) | D20: =B20*$B$7 | E20: =IF(B20=0,0,D20/B20) | F20: =IF(D20=0,"— (orgânico)",B20/(D20/1000))
A21: =A8 | B21: =SUM(C8:T8) | C21: =IF(SUM($B$15:$B$21)=0,0,B21/SUM($B$15:$B$21)) | D21: =B21*$B$8 | E21: =IF(B21=0,0,D21/B21) | F21: =IF(D21=0,"— (orgânico)",B21/(D21/1000))
A22: Só canais pagos (CAC > 0) | B22: =SUMIF($B$2:$B$8,">0",$B$15:$B$21) | D22: =SUMIF($B$2:$B$8,">0",$D$15:$D$21) | E22: =IF(B22=0,0,D22/B22) | F22: =IF(D22=0,0,B22/(D22/1000))
A24: Quantos alunos cada R$ 1.000 traz: compare o tráfego pago com indicação e parcerias antes de decidir onde botar a verba.
A26: Lance quantos alunos vieram de cada canal em cada mês. O CAC de cada canal (coluna B) multiplica a quantidade e vira a linha 'Aquisição de alunos' nos cenários.
A27: Canais orgânicos (passantes, indicação, redes) podem ter CAC 0 ou só o bônus de indicação. Tráfego pago é onde o dinheiro sai de fato.
A28: Para as matrículas virem daqui, coloque 3 em 'Origem das matrículas' nas Premissas. Esta aba vale para os 3 cenários.

Sheet Cenário Pessimista
A1: Cenário Pessimista | B1: Out (obras) | C1: Nov (obras) | D1: Dez (M1) | E1: Jan (M2) | F1: Fev (M3) | G1: Mar (M4) | H1: Abr (M5) | I1: Mai (M6) | J1: Jun (M7) | K1: Jul (M8) | L1: Ago (M9) | M1: Set (M10) | N1: Out (M11) | O1: Nov (M12) | P1: Dez (M13) | Q1: Jan (M14) | R1: Fev (M15) | S1: Mar (M16)
A2: Período (0 = out) | B2: 0 | C2: 1 | D2: 2 | E2: 3 | F2: 4 | G2: 5 | H2: 6 | I2: 7 | J2: 8 | K2: 9 | L2: 10 | M2: 11 | N2: 12 | O2: 13 | P2: 14 | Q2: 15 | R2: 16 | S2: 17
A3: Matrículas — entrada manual ✏️ editável | B3: 2 | C3: 20 | D3: 10 | E3: 20 | F3: 25 | G3: 15 | H3: 15 | I3: 15 | J3: 15 | K3: 20 | L3: 20 | M3: 15 | N3: 15 | O3: 20 | P3: 20 | Q3: 15 | R3: 20 | S3: 15 | U3: Break-even (alunos):
A4: Matrículas no período (vale para o cálculo) | B4: =IF(Premissas!$B$59=3,'Canais de aquisição'!C$9,IF(Premissas!$B$59=2,ROUND('Custos mês a mês'!B$11/MAX(Premissas!$B$60,1),0),B3)) | C4: =IF(Premissas!$B$59=3,'Canais de aquisição'!D$9,IF(Premissas!$B$59=2,ROUND('Custos mês a mês'!C$11/MAX(Premissas!$B$60,1),0),C3)) | D4: =IF(Premissas!$B$59=3,'Canais de aquisição'!E$9,IF(Premissas!$B$59=2,ROUND('Custos mês a mês'!D$11/MAX(Premissas!$B$60,1),0),D3)) | E4: =IF(Premissas!$B$59=3,'Canais de aquisição'!F$9,IF(Premissas!$B$59=2,ROUND('Custos mês a mês'!E$11/MAX(Premissas!$B$60,1),0),E3)) | F4: =IF(Premissas!$B$59=3,'Canais de aquisição'!G$9,IF(Premissas!$B$59=2,ROUND('Custos mês a mês'!F$11/MAX(Premissas!$B$60,1),0),F3)) | G4: =IF(Premissas!$B$59=3,'Canais de aquisição'!H$9,IF(Premissas!$B$59=2,ROUND('Custos mês a mês'!G$11/MAX(Premissas!$B$60,1),0),G3)) | H4: =IF(Premissas!$B$59=3,'Canais de aquisição'!I$9,IF(Premissas!$B$59=2,ROUND('Custos mês a mês'!H$11/MAX(Premissas!$B$60,1),0),H3)) | I4: =IF(Premissas!$B$59=3,'Canais de aquisição'!J$9,IF(Premissas!$B$59=2,ROUND('Custos mês a mês'!I$11/MAX(Premissas!$B$60,1),0),I3)) | ... S4: =IF(Premissas!$B$59=3,'Canais de aquisição'!T$9,IF(Premissas!$B$59=2,ROUND('Custos mês a mês'!S$11/MAX(Premissas!$B$60,1),0),S3)) | U4: =Premissas!$B$90
A5: CAC realizado (marketing + canais ÷ matrículas) | B5: =IF(B4=0,0,('Custos mês a mês'!B$11+'Canais de aquisição'!C$10)/B4) | C5: =IF(C4=0,0,('Custos mês a mês'!C$11+'Canais de aquisição'!D$10)/C4) | D5: =IF(D4=0,0,('Custos mês a mês'!D$11+'Canais de aquisição'!E$10)/D4) | E5: =IF(E4=0,0,('Custos mês a mês'!E$11+'Canais de aquisição'!F$10)/E4) | F5: =IF(F4=0,0,('Custos mês a mês'!F$11+'Canais de aquisição'!G$10)/F4) | G5: =IF(G4=0,0,('Custos mês a mês'!G$11+'Canais de aquisição'!H$10)/G4) | H5: =IF(H4=0,0,('Custos mês a mês'!H$11+'Canais de aquisição'!I$10)/H4) | I5: =IF(I4=0,0,('Custos mês a mês'!I$11+'Canais de aquisição'!J$10)/I4) | ... S5: =IF(S4=0,0,('Custos mês a mês'!S$11+'Canais de aquisição'!T$10)/S4)
A6: Desistências no mês | B6: 0 | C6: =B7*Premissas!$B$8*Premissas!$B$55 | D6: =C7*Premissas!$B$8*Premissas!$B$56 | E6: =D7*Premissas!$B$8*Premissas!$B$45 | F6: =E7*Premissas!$B$8*Premissas!$B$46 | G6: =F7*Premissas!$B$8*Premissas!$B$47 | H6: =G7*Premissas!$B$8*Premissas!$B$48 | I6: =H7*Premissas!$B$8*Premissas!$B$49 | J6: =I7*Premissas!$B$8*Premissas!$B$50 | K6: =J7*Premissas!$B$8*Premissas!$B$51 | L6: =K7*Premissas!$B$8*Premissas!$B$52 | M6: =L7*Premissas!$B$8*Premissas!$B$53 | N6: =M7*Premissas!$B$8*Premissas!$B$54 | O6: =N7*Premissas!$B$8*Premissas!$B$55 | P6: =O7*Premissas!$B$8*Premissas!$B$56 | Q6: =P7*Premissas!$B$8*Premissas!$B$45 | R6: =Q7*Premissas!$B$8*Premissas!$B$46 | S6: =R7*Premissas!$B$8*Premissas!$B$47 | U6: 🟢 VERDE FORTE = mês do BREAK-EVEN
A7: Total de alunos | B7: =B4 | C7: =B7-C6+C4 | D7: =C7-D6+D4 | E7: =D7-E6+E4 | F7: =E7-F6+F4 | G7: =F7-G6+G4 | H7: =G7-H6+H4 | I7: =H7-I6+I4 | J7: =I7-J6+J4 | ... S7: =R7-S6+S4 | U7: 🟦 AZUL = mês do PAYBACK
A8: Professores necessários | B8: 0 | C8: 0 | D8: =CEILING(CEILING(D7*Premissas!$B$37/Premissas!$B$27,1)*Premissas!$B$28/Premissas!$B$34,1)+CEILING(CEILING(D7*Premissas!$B$38/Premissas!$B$30,1)*Premissas!$B$31/Premissas!$B$34,1) | E8: =CEILING(CEILING(E7*Premissas!$B$37/Premissas!$B$27,1)*Premissas!$B$28/Premissas!$B$34,1)+CEILING(CEILING(E7*Premissas!$B$38/Premissas!$B$30,1)*Premissas!$B$31/Premissas!$B$34,1) | F8: =CEILING(CEILING(F7*Premissas!$B$37/Premissas!$B$27,1)*Premissas!$B$28/Premissas!$B$34,1)+CEILING(CEILING(F7*Premissas!$B$38/Premissas!$B$30,1)*Premissas!$B$31/Premissas!$B$34,1) | G8: =CEILING(CEILING(G7*Premissas!$B$37/Premissas!$B$27,1)*Premissas!$B$28/Premissas!$B$34,1)+CEILING(CEILING(G7*Premissas!$B$38/Premissas!$B$30,1)*Premissas!$B$31/Premissas!$B$34,1) | H8: =CEILING(CEILING(H7*Premissas!$B$37/Premissas!$B$27,1)*Premissas!$B$28/Premissas!$B$34,1)+CEILING(CEILING(H7*Premissas!$B$38/Premissas!$B$30,1)*Premissas!$B$31/Premissas!$B$34,1) | I8: =CEILING(CEILING(I7*Premissas!$B$37/Premissas!$B$27,1)*Premissas!$B$28/Premissas!$B$34,1)+CEILING(CEILING(I7*Premissas!$B$38/Premissas!$B$30,1)*Premissas!$B$31/Premissas!$B$34,1) | J8: =CEILING(CEILING(J7*Premissas!$B$37/Premissas!$B$27,1)*Premissas!$B$28/Premissas!$B$34,1)+CEILING(CEILING(J7*Premissas!$B$38/Premissas!$B$30,1)*Premissas!$B$31/Premissas!$B$34,1) | K8: =CEILING(CEILING(K7*Premissas!$B$37/Premissas!$B$27,1)*Premissas!$B$28/Premissas!$B$34,1)+CEILING(CEILING(K7*Premissas!$B$38/Premissas!$B$30,1)*Premissas!$B$31/Premissas!$B$34,1) | ... S8: =CEILING(CEILING(S7*Premissas!$B$37/Premissas!$B$27,1)*Premissas!$B$28/Premissas!$B$34,1)+CEILING(CEILING(S7*Premissas!$B$38/Premissas!$B$30,1)*Premissas!$B$31/Premissas!$B$34,1) | U8: 🟩 verde claro = meses já positivos
A9: Ocupação das salas (100% = grade cheia) | B9: 0 | C9: 0 | D9: =MAX(CEILING(D7*Premissas!$B$37/Premissas!$B$27,1)*Premissas!$B$28/(Premissas!$B$26*Premissas!$B$32*Premissas!$B$33*Premissas!$B$25),CEILING(D7*Premissas!$B$38/Premissas!$B$30,1)*Premissas!$B$31/(Premissas!$B$29*Premissas!$B$32*Premissas!$B$33*Premissas!$B$25)) | E9: =MAX(CEILING(E7*Premissas!$B$37/Premissas!$B$27,1)*Premissas!$B$28/(Premissas!$B$26*Premissas!$B$32*Premissas!$B$33*Premissas!$B$25),CEILING(E7*Premissas!$B$38/Premissas!$B$30,1)*Premissas!$B$31/(Premissas!$B$29*Premissas!$B$32*Premissas!$B$33*Premissas!$B$25)) | F9: =MAX(CEILING(F7*Premissas!$B$37/Premissas!$B$27,1)*Premissas!$B$28/(Premissas!$B$26*Premissas!$B$32*Premissas!$B$33*Premissas!$B$25),CEILING(F7*Premissas!$B$38/Premissas!$B$30,1)*Premissas!$B$31/(Premissas!$B$29*Premissas!$B$32*Premissas!$B$33*Premissas!$B$25)) | G9: =MAX(CEILING(G7*Premissas!$B$37/Premissas!$B$27,1)*Premissas!$B$28/(Premissas!$B$26*Premissas!$B$32*Premissas!$B$33*Premissas!$B$25),CEILING(G7*Premissas!$B$38/Premissas!$B$30,1)*Premissas!$B$31/(Premissas!$B$29*Premissas!$B$32*Premissas!$B$33*Premissas!$B$25)) | H9: =MAX(CEILING(H7*Premissas!$B$37/Premissas!$B$27,1)*Premissas!$B$28/(Premissas!$B$26*Premissas!$B$32*Premissas!$B$33*Premissas!$B$25),CEILING(H7*Premissas!$B$38/Premissas!$B$30,1)*Premissas!$B$31/(Premissas!$B$29*Premissas!$B$32*Premissas!$B$33*Premissas!$B$25)) | I9: =MAX(CEILING(I7*Premissas!$B$37/Premissas!$B$27,1)*Premissas!$B$28/(Premissas!$B$26*Premissas!$B$32*Premissas!$B$33*Premissas!$B$25),CEILING(I7*Premissas!$B$38/Premissas!$B$30,1)*Premissas!$B$31/(Premissas!$B$29*Premissas!$B$32*Premissas!$B$33*Premissas!$B$25)) | J9: =MAX(CEILING(J7*Premissas!$B$37/Premissas!$B$27,1)*Premissas!$B$28/(Premissas!$B$26*Premissas!$B$32*Premissas!$B$33*Premissas!$B$25),CEILING(J7*Premissas!$B$38/Premissas!$B$30,1)*Premissas!$B$31/(Premissas!$B$29*Premissas!$B$32*Premissas!$B$33*Premissas!$B$25)) | K9: =MAX(CEILING(K7*Premissas!$B$37/Premissas!$B$27,1)*Premissas!$B$28/(Premissas!$B$26*Premissas!$B$32*Premissas!$B$33*Premissas!$B$25),CEILING(K7*Premissas!$B$38/Premissas!$B$30,1)*Premissas!$B$31/(Premissas!$B$29*Premissas!$B$32*Premissas!$B$33*Premissas!$B$25)) | ... S9: =MAX(CEILING(S7*Premissas!$B$37/Premissas!$B$27,1)*Premissas!$B$28/(Premissas!$B$26*Premissas!$B$32*Premissas!$B$33*Premissas!$B$25),CEILING(S7*Premissas!$B$38/Premissas!$B$30,1)*Premissas!$B$31/(Premissas!$B$29*Premissas!$B$32*Premissas!$B$33*Premissas!$B$25))
A11: RECEITA RECEBIDA (caixa)
A12: Matrícula | B12: =B4*Premissas!$B$3 | C12: =C4*Premissas!$B$3 | D12: =D4*Premissas!$B$3 | E12: =E4*Premissas!$B$3 | F12: =F4*Premissas!$B$3 | G12: =G4*Premissas!$B$3 | H12: =H4*Premissas!$B$3 | I12: =I4*Premissas!$B$3 | ... S12: =S4*Premissas!$B$3
A13: Mensalidade recebida (líq. de inadimplência) | B13: 0 | C13: 0 | D13: =C7*Premissas!$B$2*(1-Premissas!$B$9) | E13: =D7*Premissas!$B$2*(1-Premissas!$B$9) | F13: =E7*Premissas!$B$2*(1-Premissas!$B$9) | G13: =F7*Premissas!$B$2*(1-Premissas!$B$9) | H13: =G7*Premissas!$B$2*(1-Premissas!$B$9) | I13: =H7*Premissas!$B$2*(1-Premissas!$B$9) | J13: =I7*Premissas!$B$2*(1-Premissas!$B$9) | K13: =J7*Premissas!$B$2*(1-Premissas!$B$9) | ... S13: =R7*Premissas!$B$2*(1-Premissas!$B$9)
A14: Material antecipado no cartão | B14: =B4*Premissas!$B$5 | C14: =C4*Premissas!$B$5 | D14: =D4*Premissas!$B$5 | E14: =E4*Premissas!$B$5 | F14: =F4*Premissas!$B$5 | G14: =G4*Premissas!$B$5 | H14: =H4*Premissas!$B$5 | I14: =I4*Premissas!$B$5 | ... S14: =S4*Premissas!$B$5
A15: Receita recebida | B15: =SUM(B12:B14) | C15: =SUM(C12:C14) | D15: =SUM(D12:D14) | E15: =SUM(E12:E14) | F15: =SUM(F12:F14) | G15: =SUM(G12:G14) | H15: =SUM(H12:H14) | I15: =SUM(I12:I14) | ... S15: =SUM(S12:S14)
A17: BASE DO SIMPLES NACIONAL
A18: Faturamento do mês (nota emitida) | B18: =B4*Premissas!$B$3+B4*Premissas!$B$4 | C18: =C4*Premissas!$B$3+C4*Premissas!$B$4 | D18: =D4*Premissas!$B$3+C7*Premissas!$B$2+D4*Premissas!$B$4 | E18: =E4*Premissas!$B$3+D7*Premissas!$B$2+E4*Premissas!$B$4 | F18: =F4*Premissas!$B$3+E7*Premissas!$B$2+F4*Premissas!$B$4 | G18: =G4*Premissas!$B$3+F7*Premissas!$B$2+G4*Premissas!$B$4 | H18: =H4*Premissas!$B$3+G7*Premissas!$B$2+H4*Premissas!$B$4 | I18: =I4*Premissas!$B$3+H7*Premissas!$B$2+I4*Premissas!$B$4 | J18: =J4*Premissas!$B$3+I7*Premissas!$B$2+J4*Premissas!$B$4 | K18: =K4*Premissas!$B$3+J7*Premissas!$B$2+K4*Premissas!$B$4 | ... S18: =S4*Premissas!$B$3+R7*Premissas!$B$2+S4*Premissas!$B$4
A19: RBT12 proporcionalizado | B19: =SUM($B$18:B18)/1*12 | C19: =SUM($B$18:C18)/2*12 | D19: =SUM($B$18:D18)/3*12 | E19: =SUM($B$18:E18)/4*12 | F19: =SUM($B$18:F18)/5*12 | G19: =SUM($B$18:G18)/6*12 | H19: =SUM($B$18:H18)/7*12 | I19: =SUM($B$18:I18)/8*12 | J19: =SUM($B$18:J18)/9*12 | K19: =SUM($B$18:K18)/10*12 | L19: =SUM($B$18:L18)/11*12 | M19: =SUM(B18:M18) | N19: =SUM(C18:N18) | O19: =SUM(D18:O18) | P19: =SUM(E18:P18) | Q19: =SUM(F18:Q18) | R19: =SUM(G18:R18) | S19: =SUM(H18:S18)
A20: Alíquota efetiva do Simples | B20: =IF(B19=0,Premissas!$C$66,IF(B19<=Premissas!$B$66,(B19*Premissas!$C$66-Premissas!$D$66)/B19,IF(B19<=Premissas!$B$67,(B19*Premissas!$C$67-Premissas!$D$67)/B19,IF(B19<=Premissas!$B$68,(B19*Premissas!$C$68-Premissas!$D$68)/B19,IF(B19<=Premissas!$B$69,(B19*Premissas!$C$69-Premissas!$D$69)/B19,IF(B19<=Premissas!$B$70,(B19*Premissas!$C$70-Premissas!$D$70)/B19,(B19*Premissas!$C$71-Premissas!$D$71)/B19)))))) | C20: =IF(C19=0,Premissas!$C$66,IF(C19<=Premissas!$B$66,(C19*Premissas!$C$66-Premissas!$D$66)/C19,IF(C19<=Premissas!$B$67,(C19*Premissas!$C$67-Premissas!$D$67)/C19,IF(C19<=Premissas!$B$68,(C19*Premissas!$C$68-Premissas!$D$68)/C19,IF(C19<=Premissas!$B$69,(C19*Premissas!$C$69-Premissas!$D$69)/C19,IF(C19<=Premissas!$B$70,(C19*Premissas!$C$70-Premissas!$D$70)/C19,(C19*Premissas!$C$71-Premissas!$D$71)/C19)))))) | D20: =IF(D19=0,Premissas!$C$66,IF(D19<=Premissas!$B$66,(D19*Premissas!$C$66-Premissas!$D$66)/D19,IF(D19<=Premissas!$B$67,(D19*Premissas!$C$67-Premissas!$D$67)/D19,IF(D19<=Premissas!$B$68,(D19*Premissas!$C$68-Premissas!$D$68)/D19,IF(D19<=Premissas!$B$69,(D19*Premissas!$C$69-Premissas!$D$69)/D19,IF(D19<=Premissas!$B$70,(D19*Premissas!$C$70-Premissas!$D$70)/D19,(D19*Premissas!$C$71-Premissas!$D$71)/D19)))))) | E20: =IF(E19=0,Premissas!$C$66,IF(E19<=Premissas!$B$66,(E19*Premissas!$C$66-Premissas!$D$66)/E19,IF(E19<=Premissas!$B$67,(E19*Premissas!$C$67-Premissas!$D$67)/E19,IF(E19<=Premissas!$B$68,(E19*Premissas!$C$68-Premissas!$D$68)/E19,IF(E19<=Premissas!$B$69,(E19*Premissas!$C$69-Premissas!$D$69)/E19,IF(E19<=Premissas!$B$70,(E19*Premissas!$C$70-Premissas!$D$70)/E19,(E19*Premissas!$C$71-Premissas!$D$71)/E19)))))) | F20: =IF(F19=0,Premissas!$C$66,IF(F19<=Premissas!$B$66,(F19*Premissas!$C$66-Premissas!$D$66)/F19,IF(F19<=Premissas!$B$67,(F19*Premissas!$C$67-Premissas!$D$67)/F19,IF(F19<=Premissas!$B$68,(F19*Premissas!$C$68-Premissas!$D$68)/F19,IF(F19<=Premissas!$B$69,(F19*Premissas!$C$69-Premissas!$D$69)/F19,IF(F19<=Premissas!$B$70,(F19*Premissas!$C$70-Premissas!$D$70)/F19,(F19*Premissas!$C$71-Premissas!$D$71)/F19)))))) | G20: =IF(G19=0,Premissas!$C$66,IF(G19<=Premissas!$B$66,(G19*Premissas!$C$66-Premissas!$D$66)/G19,IF(G19<=Premissas!$B$67,(G19*Premissas!$C$67-Premissas!$D$67)/G19,IF(G19<=Premissas!$B$68,(G19*Premissas!$C$68-Premissas!$D$68)/G19,IF(G19<=Premissas!$B$69,(G19*Premissas!$C$69-Premissas!$D$69)/G19,IF(G19<=Premissas!$B$70,(G19*Premissas!$C$70-Premissas!$D$70)/G19,(G19*Premissas!$C$71-Premissas!$D$71)/G19)))))) | H20: =IF(H19=0,Premissas!$C$66,IF(H19<=Premissas!$B$66,(H19*Premissas!$C$66-Premissas!$D$66)/H19,IF(H19<=Premissas!$B$67,(H19*Premissas!$C$67-Premissas!$D$67)/H19,IF(H19<=Premissas!$B$68,(H19*Premissas!$C$68-Premissas!$D$68)/H19,IF(H19<=Premissas!$B$69,(H19*Premissas!$C$69-Premissas!$D$69)/H19,IF(H19<=Premissas!$B$70,(H19*Premissas!$C$70-Premissas!$D$70)/H19,(H19*Premissas!$C$71-Premissas!$D$71)/H19)))))) | I20: =IF(I19=0,Premissas!$C$66,IF(I19<=Premissas!$B$66,(I19*Premissas!$C$66-Premissas!$D$66)/I19,IF(I19<=Premissas!$B$67,(I19*Premissas!$C$67-Premissas!$D$67)/I19,IF(I19<=Premissas!$B$68,(I19*Premissas!$C$68-Premissas!$D$68)/I19,IF(I19<=Premissas!$B$69,(I19*Premissas!$C$69-Premissas!$D$69)/I19,IF(I19<=Premissas!$B$70,(I19*Premissas!$C$70-Premissas!$D$70)/I19,(I19*Premissas!$C$71-Premissas!$D$71)/I19)))))) | ... S20: =IF(S19=0,Premissas!$C$66,IF(S19<=Premissas!$B$66,(S19*Premissas!$C$66-Premissas!$D$66)/S19,IF(S19<=Premissas!$B$67,(S19*Premissas!$C$67-Premissas!$D$67)/S19,IF(S19<=Premissas!$B$68,(S19*Premissas!$C$68-Premissas!$D$68)/S19,IF(S19<=Premissas!$B$69,(S19*Premissas!$C$69-Premissas!$D$69)/S19,IF(S19<=Premissas!$B$70,(S19*Premissas!$C$70-Premissas!$D$70)/S19,(S19*Premissas!$C$71-Premissas!$D$71)/S19))))))
A22: DESPESAS
A23: Impostos (Simples progressivo) | B23: =B18*B20 | C23: =C18*C20 | D23: =D18*D20 | E23: =E18*E20 | F23: =F18*F20 | G23: =G18*G20 | H23: =H18*H20 | I23: =I18*I20 | ... S23: =S18*S20
A24: Material — parcelas 12x | B24: 0 | C24: 0 | D24: =SUM($B$4:D4)*Premissas!$B$6/12 | E24: =SUM($B$4:E4)*Premissas!$B$6/12 | F24: =SUM($B$4:F4)*Premissas!$B$6/12 | G24: =SUM($B$4:G4)*Premissas!$B$6/12 | H24: =SUM($B$4:H4)*Premissas!$B$6/12 | I24: =SUM($B$4:I4)*Premissas!$B$6/12 | J24: =SUM($B$4:J4)*Premissas!$B$6/12 | K24: =SUM($B$4:K4)*Premissas!$B$6/12 | ... O24: =SUM($B$4:O4)*Premissas!$B$6/12 | P24: =SUM(E4:P4)*Premissas!$B$6/12 | Q24: =SUM(F4:Q4)*Premissas!$B$6/12 | R24: =SUM(G4:R4)*Premissas!$B$6/12 | S24: =SUM(H4:S4)*Premissas!$B$6/12
A25: Comissão do vendedor | B25: =IF(B2>=Premissas!$D$14,B4*Premissas!$B$10*(1+Premissas!$B$11),0) | C25: =IF(C2>=Premissas!$D$14,C4*Premissas!$B$10*(1+Premissas!$B$11),0) | D25: =IF(D2>=Premissas!$D$14,D4*Premissas!$B$10*(1+Premissas!$B$11),0) | E25: =IF(E2>=Premissas!$D$14,E4*Premissas!$B$10*(1+Premissas!$B$11),0) | F25: =IF(F2>=Premissas!$D$14,F4*Premissas!$B$10*(1+Premissas!$B$11),0) | G25: =IF(G2>=Premissas!$D$14,G4*Premissas!$B$10*(1+Premissas!$B$11),0) | H25: =IF(H2>=Premissas!$D$14,H4*Premissas!$B$10*(1+Premissas!$B$11),0) | I25: =IF(I2>=Premissas!$D$14,I4*Premissas!$B$10*(1+Premissas!$B$11),0) | ... S25: =IF(S2>=Premissas!$D$14,S4*Premissas!$B$10*(1+Premissas!$B$11),0)
A26: Aquisição de alunos (custo dos canais) | B26: ='Canais de aquisição'!C$10 | C26: ='Canais de aquisição'!D$10 | D26: ='Canais de aquisição'!E$10 | E26: ='Canais de aquisição'!F$10 | F26: ='Canais de aquisição'!G$10 | G26: ='Canais de aquisição'!H$10 | H26: ='Canais de aquisição'!I$10 | I26: ='Canais de aquisição'!J$10 | ... S26: ='Canais de aquisição'!T$10
A27: Folha + encargos mensais (só quem já entrou) | B27: =SUMPRODUCT((Premissas!$D$14:$D$20<=B2)*Premissas!$B$14:$B$20*(1+Premissas!$C$14:$C$20*Premissas!$B$11)) | C27: =SUMPRODUCT((Premissas!$D$14:$D$20<=C2)*Premissas!$B$14:$B$20*(1+Premissas!$C$14:$C$20*Premissas!$B$11)) | D27: =SUMPRODUCT((Premissas!$D$14:$D$20<=D2)*Premissas!$B$14:$B$20*(1+Premissas!$C$14:$C$20*Premissas!$B$11)) | E27: =SUMPRODUCT((Premissas!$D$14:$D$20<=E2)*Premissas!$B$14:$B$20*(1+Premissas!$C$14:$C$20*Premissas!$B$11)) | F27: =SUMPRODUCT((Premissas!$D$14:$D$20<=F2)*Premissas!$B$14:$B$20*(1+Premissas!$C$14:$C$20*Premissas!$B$11)) | G27: =SUMPRODUCT((Premissas!$D$14:$D$20<=G2)*Premissas!$B$14:$B$20*(1+Premissas!$C$14:$C$20*Premissas!$B$11)) | H27: =SUMPRODUCT((Premissas!$D$14:$D$20<=H2)*Premissas!$B$14:$B$20*(1+Premissas!$C$14:$C$20*Premissas!$B$11)) | I27: =SUMPRODUCT((Premissas!$D$14:$D$20<=I2)*Premissas!$B$14:$B$20*(1+Premissas!$C$14:$C$20*Premissas!$B$11)) | ... S27: =SUMPRODUCT((Premissas!$D$14:$D$20<=S2)*Premissas!$B$14:$B$20*(1+Premissas!$C$14:$C$20*Premissas!$B$11))
A28: Vale-transporte / benefícios | B28: =SUMPRODUCT((Premissas!$D$14:$D$20<=B2)*Premissas!$C$14:$C$20*(Premissas!$B$14:$B$20>0))*Premissas!$B$12 | C28: =SUMPRODUCT((Premissas!$D$14:$D$20<=C2)*Premissas!$C$14:$C$20*(Premissas!$B$14:$B$20>0))*Premissas!$B$12 | D28: =SUMPRODUCT((Premissas!$D$14:$D$20<=D2)*Premissas!$C$14:$C$20*(Premissas!$B$14:$B$20>0))*Premissas!$B$12 | E28: =SUMPRODUCT((Premissas!$D$14:$D$20<=E2)*Premissas!$C$14:$C$20*(Premissas!$B$14:$B$20>0))*Premissas!$B$12 | F28: =SUMPRODUCT((Premissas!$D$14:$D$20<=F2)*Premissas!$C$14:$C$20*(Premissas!$B$14:$B$20>0))*Premissas!$B$12 | G28: =SUMPRODUCT((Premissas!$D$14:$D$20<=G2)*Premissas!$C$14:$C$20*(Premissas!$B$14:$B$20>0))*Premissas!$B$12 | H28: =SUMPRODUCT((Premissas!$D$14:$D$20<=H2)*Premissas!$C$14:$C$20*(Premissas!$B$14:$B$20>0))*Premissas!$B$12 | I28: =SUMPRODUCT((Premissas!$D$14:$D$20<=I2)*Premissas!$C$14:$C$20*(Premissas!$B$14:$B$20>0))*Premissas!$B$12 | ... S28: =SUMPRODUCT((Premissas!$D$14:$D$20<=S2)*Premissas!$C$14:$C$20*(Premissas!$B$14:$B$20>0))*Premissas!$B$12
A29: 13º e férias (desembolso) | B29: 0 | C29: 0 | D29: =Premissas!$B$41*SUMPRODUCT((Premissas!$D$14:$D$20<=2)*Premissas!$C$14:$C$20*Premissas!$B$14:$B$20*(2-((Premissas!$D$14:$D$20>0)*Premissas!$D$14:$D$20+(Premissas!$D$14:$D$20<=0)*0)+1)/12)+0 | E29: 0 | F29: 0 | G29: 0 | H29: 0 | I29: 0 | J29: 0 | K29: 0 | L29: 0 | M29: 0 | N29: =0+Premissas!$B$42*SUMPRODUCT((Premissas!$D$14:$D$20=0)*Premissas!$C$14:$C$20*Premissas!$B$14:$B$20)*4/3 | O29: =0+Premissas!$B$42*SUMPRODUCT((Premissas!$D$14:$D$20=1)*Premissas!$C$14:$C$20*Premissas!$B$14:$B$20)*4/3 | P29: =Premissas!$B$41*SUMPRODUCT((Premissas!$D$14:$D$20<=14)*Premissas!$C$14:$C$20*Premissas!$B$14:$B$20*(14-((Premissas!$D$14:$D$20>3)*Premissas!$D$14:$D$20+(Premissas!$D$14:$D$20<=3)*3)+1)/12)+Premissas!$B$42*SUMPRODUCT((Premissas!$D$14:$D$20=2)*Premissas!$C$14:$C$20*Premissas!$B$14:$B$20)*4/3 | Q29: =0+Premissas!$B$42*SUMPRODUCT((Premissas!$D$14:$D$20=3)*Premissas!$C$14:$C$20*Premissas!$B$14:$B$20)*4/3 | R29: =0+Premissas!$B$42*SUMPRODUCT((Premissas!$D$14:$D$20=4)*Premissas!$C$14:$C$20*Premissas!$B$14:$B$20)*4/3 | S29: =0+Premissas!$B$42*SUMPRODUCT((Premissas!$D$14:$D$20=5)*Premissas!$C$14:$C$20*Premissas!$B$14:$B$20)*4/3
A30: Professores (salário + encargos) | B30: 0 | C30: 0 | D30: =D8*Premissas!$B$35 | E30: =E8*Premissas!$B$35 | F30: =F8*Premissas!$B$35 | G30: =G8*Premissas!$B$35 | H30: =H8*Premissas!$B$35 | I30: =I8*Premissas!$B$35 | J30: =J8*Premissas!$B$35 | K30: =K8*Premissas!$B$35 | ... S30: =S8*Premissas!$B$35
A31: Aluguel do espaço | B31: ='Custos mês a mês'!B2 | C31: ='Custos mês a mês'!C2 | D31: ='Custos mês a mês'!D2 | E31: ='Custos mês a mês'!E2 | F31: ='Custos mês a mês'!F2 | G31: ='Custos mês a mês'!G2 | H31: ='Custos mês a mês'!H2 | I31: ='Custos mês a mês'!I2 | ... S31: ='Custos mês a mês'!S2
A32: Água | B32: ='Custos mês a mês'!B3 | C32: ='Custos mês a mês'!C3 | D32: ='Custos mês a mês'!D3 | E32: ='Custos mês a mês'!E3 | F32: ='Custos mês a mês'!F3 | G32: ='Custos mês a mês'!G3 | H32: ='Custos mês a mês'!H3 | I32: ='Custos mês a mês'!I3 | ... S32: ='Custos mês a mês'!S3
A33: Luz | B33: ='Custos mês a mês'!B4 | C33: ='Custos mês a mês'!C4 | D33: ='Custos mês a mês'!D4 | E33: ='Custos mês a mês'!E4 | F33: ='Custos mês a mês'!F4 | G33: ='Custos mês a mês'!G4 | H33: ='Custos mês a mês'!H4 | I33: ='Custos mês a mês'!I4 | ... S33: ='Custos mês a mês'!S4
A34: Telefone | B34: ='Custos mês a mês'!B5 | C34: ='Custos mês a mês'!C5 | D34: ='Custos mês a mês'!D5 | E34: ='Custos mês a mês'!E5 | F34: ='Custos mês a mês'!F5 | G34: ='Custos mês a mês'!G5 | H34: ='Custos mês a mês'!H5 | I34: ='Custos mês a mês'!I5 | ... S34: ='Custos mês a mês'!S5
A35: Internet | B35: ='Custos mês a mês'!B6 | C35: ='Custos mês a mês'!C6 | D35: ='Custos mês a mês'!D6 | E35: ='Custos mês a mês'!E6 | F35: ='Custos mês a mês'!F6 | G35: ='Custos mês a mês'!G6 | H35: ='Custos mês a mês'!H6 | I35: ='Custos mês a mês'!I6 | ... S35: ='Custos mês a mês'!S6
A36: Sistema de gestão DiscoverON | B36: ='Custos mês a mês'!B7 | C36: ='Custos mês a mês'!C7 | D36: ='Custos mês a mês'!D7 | E36: ='Custos mês a mês'!E7 | F36: ='Custos mês a mês'!F7 | G36: ='Custos mês a mês'!G7 | H36: ='Custos mês a mês'!H7 | I36: ='Custos mês a mês'!I7 | ... S36: ='Custos mês a mês'!S7
A37: Itens para aula | B37: ='Custos mês a mês'!B8 | C37: ='Custos mês a mês'!C8 | D37: ='Custos mês a mês'!D8 | E37: ='Custos mês a mês'!E8 | F37: ='Custos mês a mês'!F8 | G37: ='Custos mês a mês'!G8 | H37: ='Custos mês a mês'!H8 | I37: ='Custos mês a mês'!I8 | ... S37: ='Custos mês a mês'!S8
A38: Materiais de limpeza + higiene | B38: ='Custos mês a mês'!B9 | C38: ='Custos mês a mês'!C9 | D38: ='Custos mês a mês'!D9 | E38: ='Custos mês a mês'!E9 | F38: ='Custos mês a mês'!F9 | G38: ='Custos mês a mês'!G9 | H38: ='Custos mês a mês'!H9 | I38: ='Custos mês a mês'!I9 | ... S38: ='Custos mês a mês'!S9
A39: Brindes | B39: ='Custos mês a mês'!B10 | C39: ='Custos mês a mês'!C10 | D39: ='Custos mês a mês'!D10 | E39: ='Custos mês a mês'!E10 | F39: ='Custos mês a mês'!F10 | G39: ='Custos mês a mês'!G10 | H39: ='Custos mês a mês'!H10 | I39: ='Custos mês a mês'!I10 | ... S39: ='Custos mês a mês'!S10
A40: Marketing | B40: ='Custos mês a mês'!B11 | C40: ='Custos mês a mês'!C11 | D40: ='Custos mês a mês'!D11 | E40: ='Custos mês a mês'!E11 | F40: ='Custos mês a mês'!F11 | G40: ='Custos mês a mês'!G11 | H40: ='Custos mês a mês'!H11 | I40: ='Custos mês a mês'!I11 | ... S40: ='Custos mês a mês'!S11
A41: Aluguel dos computadores | B41: ='Custos mês a mês'!B12 | C41: ='Custos mês a mês'!C12 | D41: ='Custos mês a mês'!D12 | E41: ='Custos mês a mês'!E12 | F41: ='Custos mês a mês'!F12 | G41: ='Custos mês a mês'!G12 | H41: ='Custos mês a mês'!H12 | I41: ='Custos mês a mês'!I12 | ... S41: ='Custos mês a mês'!S12
A42: Seguro empresarial | B42: ='Custos mês a mês'!B13 | C42: ='Custos mês a mês'!C13 | D42: ='Custos mês a mês'!D13 | E42: ='Custos mês a mês'!E13 | F42: ='Custos mês a mês'!F13 | G42: ='Custos mês a mês'!G13 | H42: ='Custos mês a mês'!H13 | I42: ='Custos mês a mês'!I13 | ... S42: ='Custos mês a mês'!S13
... A45: Pró-labore | B45: ='Custos mês a mês'!B16 | C45: ='Custos mês a mês'!C16 | D45: ='Custos mês a mês'!D16 | E45: ='Custos mês a mês'!E16 | F45: ='Custos mês a mês'!F16 | G45: ='Custos mês a mês'!G16 | H45: ='Custos mês a mês'!H16 | I45: ='Custos mês a mês'!I16 | ... S45: ='Custos mês a mês'!S16
A46: Total de despesas | B46: =SUM(B23:B45) | C46: =SUM(C23:C45) | D46: =SUM(D23:D45) | E46: =SUM(E23:E45) | F46: =SUM(F23:F45) | G46: =SUM(G23:G45) | H46: =SUM(H23:H45) | I46: =SUM(I23:I45) | ... S46: =SUM(S23:S45)
A48: Resultado do mês | B48: =B15-B46 | C48: =C15-C46 | D48: =D15-D46 | E48: =E15-E46 | F48: =F15-F46 | G48: =G15-G46 | H48: =H15-H46 | I48: =I15-I46 | ... S48: =S15-S46
A49: Caixa acumulado (operacional) | B49: =B48 | C49: =B49+C48 | D49: =C49+D48 | E49: =D49+E48 | F49: =E49+F48 | G49: =F49+G48 | H49: =G49+H48 | I49: =H49+I48 | J49: =I49+J48 | ... S49: =R49+S48
A50: Caixa acumulado incl. investimento | B50: =B49-INVEST_TOTAL | C50: =C49-INVEST_TOTAL | D50: =D49-INVEST_TOTAL | E50: =E49-INVEST_TOTAL | F50: =F49-INVEST_TOTAL | G50: =G49-INVEST_TOTAL | H50: =H49-INVEST_TOTAL | I50: =I49-INVEST_TOTAL | ... S50: =S49-INVEST_TOTAL
A51: MARCOS | D51: =IF(AND(D48>0,COUNTIF($D48:D48,">0")=1),IF(AND(D50>=0,COUNTIF($D50:D50,">=0")=1),"BE + PAYBACK","BREAK-EVEN"),IF(AND(D50>=0,COUNTIF($D50:D50,">=0")=1),"PAYBACK","")) | E51: =IF(AND(E48>0,COUNTIF($D48:E48,">0")=1),IF(AND(E50>=0,COUNTIF($D50:E50,">=0")=1),"BE + PAYBACK","BREAK-EVEN"),IF(AND(E50>=0,COUNTIF($D50:E50,">=0")=1),"PAYBACK","")) | F51: =IF(AND(F48>0,COUNTIF($D48:F48,">0")=1),IF(AND(F50>=0,COUNTIF($D50:F50,">=0")=1),"BE + PAYBACK","BREAK-EVEN"),IF(AND(F50>=0,COUNTIF($D50:F50,">=0")=1),"PAYBACK","")) | G51: =IF(AND(G48>0,COUNTIF($D48:G48,">0")=1),IF(AND(G50>=0,COUNTIF($D50:G50,">=0")=1),"BE + PAYBACK","BREAK-EVEN"),IF(AND(G50>=0,COUNTIF($D50:G50,">=0")=1),"PAYBACK","")) | H51: =IF(AND(H48>0,COUNTIF($D48:H48,">0")=1),IF(AND(H50>=0,COUNTIF($D50:H50,">=0")=1),"BE + PAYBACK","BREAK-EVEN"),IF(AND(H50>=0,COUNTIF($D50:H50,">=0")=1),"PAYBACK","")) | I51: =IF(AND(I48>0,COUNTIF($D48:I48,">0")=1),IF(AND(I50>=0,COUNTIF($D50:I50,">=0")=1),"BE + PAYBACK","BREAK-EVEN"),IF(AND(I50>=0,COUNTIF($D50:I50,">=0")=1),"PAYBACK","")) | J51: =IF(AND(J48>0,COUNTIF($D48:J48,">0")=1),IF(AND(J50>=0,COUNTIF($D50:J50,">=0")=1),"BE + PAYBACK","BREAK-EVEN"),IF(AND(J50>=0,COUNTIF($D50:J50,">=0")=1),"PAYBACK","")) | K51: =IF(AND(K48>0,COUNTIF($D48:K48,">0")=1),IF(AND(K50>=0,COUNTIF($D50:K50,">=0")=1),"BE + PAYBACK","BREAK-EVEN"),IF(AND(K50>=0,COUNTIF($D50:K50,">=0")=1),"PAYBACK","")) | ... S51: =IF(AND(S48>0,COUNTIF($D48:S48,">0")=1),IF(AND(S50>=0,COUNTIF($D50:S50,">=0")=1),"BE + PAYBACK","BREAK-EVEN"),IF(AND(S50>=0,COUNTIF($D50:S50,">=0")=1),"PAYBACK",""))

Sheet Cenário Moderado
A1: Cenário Moderado | B1: Out (obras) | C1: Nov (obras) | D1: Dez (M1) | E1: Jan (M2) | F1: Fev (M3) | G1: Mar (M4) | H1: Abr (M5) | I1: Mai (M6) | J1: Jun (M7) | K1: Jul (M8) | L1: Ago (M9) | M1: Set (M10) | N1: Out (M11) | O1: Nov (M12) | P1: Dez (M13) | Q1: Jan (M14) | R1: Fev (M15) | S1: Mar (M16)
A2: Período (0 = out) | B2: 0 | C2: 1 | D2: 2 | E2: 3 | F2: 4 | G2: 5 | H2: 6 | I2: 7 | J2: 8 | K2: 9 | L2: 10 | M2: 11 | N2: 12 | O2: 13 | P2: 14 | Q2: 15 | R2: 16 | S2: 17
A3: Matrículas — entrada manual ✏️ editável | B3: 4 | C3: 35 | D3: 13 | E3: 30 | F3: 30 | G3: 20 | H3: 20 | I3: 20 | J3: 20 | K3: 30 | L3: 30 | M3: 20 | N3: 20 | O3: 30 | P3: 30 | Q3: 20 | R3: 30 | S3: 20 | U3: Break-even (alunos):
A4: Matrículas no período (vale para o cálculo) | B4: =IF(Premissas!$B$59=3,'Canais de aquisição'!C$9,IF(Premissas!$B$59=2,ROUND('Custos mês a mês'!B$11/MAX(Premissas!$B$60,1),0),B3)) | C4: =IF(Premissas!$B$59=3,'Canais de aquisição'!D$9,IF(Premissas!$B$59=2,ROUND('Custos mês a mês'!C$11/MAX(Premissas!$B$60,1),0),C3)) | D4: =IF(Premissas!$B$59=3,'Canais de aquisição'!E$9,IF(Premissas!$B$59=2,ROUND('Custos mês a mês'!D$11/MAX(Premissas!$B$60,1),0),D3)) | E4: =IF(Premissas!$B$59=3,'Canais de aquisição'!F$9,IF(Premissas!$B$59=2,ROUND('Custos mês a mês'!E$11/MAX(Premissas!$B$60,1),0),E3)) | F4: =IF(Premissas!$B$59=3,'Canais de aquisição'!G$9,IF(Premissas!$B$59=2,ROUND('Custos mês a mês'!F$11/MAX(Premissas!$B$60,1),0),F3)) | G4: =IF(Premissas!$B$59=3,'Canais de aquisição'!H$9,IF(Premissas!$B$59=2,ROUND('Custos mês a mês'!G$11/MAX(Premissas!$B$60,1),0),G3)) | H4: =IF(Premissas!$B$59=3,'Canais de aquisição'!I$9,IF(Premissas!$B$59=2,ROUND('Custos mês a mês'!H$11/MAX(Premissas!$B$60,1),0),H3)) | I4: =IF(Premissas!$B$59=3,'Canais de aquisição'!J$9,IF(Premissas!$B$59=2,ROUND('Custos mês a mês'!I$11/MAX(Premissas!$B$60,1),0),I3)) | ... S4: =IF(Premissas!$B$59=3,'Canais de aquisição'!T$9,IF(Premissas!$B$59=2,ROUND('Custos mês a mês'!S$11/MAX(Premissas!$B$60,1),0),S3)) | U4: =Premissas!$B$90
A5: CAC realizado (marketing + canais ÷ matrículas) | B5: =IF(B4=0,0,('Custos mês a mês'!B$11+'Canais de aquisição'!C$10)/B4) | C5: =IF(C4=0,0,('Custos mês a mês'!C$11+'Canais de aquisição'!D$10)/C4) | D5: =IF(D4=0,0,('Custos mês a mês'!D$11+'Canais de aquisição'!E$10)/D4) | E5: =IF(E4=0,0,('Custos mês a mês'!E$11+'Canais de aquisição'!F$10)/E4) | F5: =IF(F4=0,0,('Custos mês a mês'!F$11+'Canais de aquisição'!G$10)/F4) | G5: =IF(G4=0,0,('Custos mês a mês'!G$11+'Canais de aquisição'!H$10)/G4) | H5: =IF(H4=0,0,('Custos mês a mês'!H$11+'Canais de aquisição'!I$10)/H4) | I5: =IF(I4=0,0,('Custos mês a mês'!I$11+'Canais de aquisição'!J$10)/I4) | ... S5: =IF(S4=0,0,('Custos mês a mês'!S$11+'Canais de aquisição'!T$10)/S4)
A6: Desistências no mês | B6: 0 | C6: =B7*Premissas!$B$8*Premissas!$B$55 | D6: =C7*Premissas!$B$8*Premissas!$B$56 | E6: =D7*Premissas!$B$8*Premissas!$B$45 | F6: =E7*Premissas!$B$8*Premissas!$B$46 | G6: =F7*Premissas!$B$8*Premissas!$B$47 | H6: =G7*Premissas!$B$8*Premissas!$B$48 | I6: =H7*Premissas!$B$8*Premissas!$B$49 | J6: =I7*Premissas!$B$8*Premissas!$B$50 | K6: =J7*Premissas!$B$8*Premissas!$B$51 | L6: =K7*Premissas!$B$8*Premissas!$B$52 | M6: =L7*Premissas!$B$8*Premissas!$B$53 | N6: =M7*Premissas!$B$8*Premissas!$B$54 | O6: =N7*Premissas!$B$8*Premissas!$B$55 | P6: =O7*Premissas!$B$8*Premissas!$B$56 | Q6: =P7*Premissas!$B$8*Premissas!$B$45 | R6: =Q7*Premissas!$B$8*Premissas!$B$46 | S6: =R7*Premissas!$B$8*Premissas!$B$47 | U6: 🟢 VERDE FORTE = mês do BREAK-EVEN
A7: Total de alunos | B7: =B4 | C7: =B7-C6+C4 | D7: =C7-D6+D4 | E7: =D7-E6+E4 | F7: =E7-F6+F4 | G7: =F7-G6+G4 | H7: =G7-H6+H4 | I7: =H7-I6+I4 | J7: =I7-J6+J4 | ... S7: =R7-S6+S4 | U7: 🟦 AZUL = mês do PAYBACK
A8: Professores necessários | B8: 0 | C8: 0 | D8: =CEILING(CEILING(D7*Premissas!$B$37/Premissas!$B$27,1)*Premissas!$B$28/Premissas!$B$34,1)+CEILING(CEILING(D7*Premissas!$B$38/Premissas!$B$30,1)*Premissas!$B$31/Premissas!$B$34,1) | E8: =CEILING(CEILING(E7*Premissas!$B$37/Premissas!$B$27,1)*Premissas!$B$28/Premissas!$B$34,1)+CEILING(CEILING(E7*Premissas!$B$38/Premissas!$B$30,1)*Premissas!$B$31/Premissas!$B$34,1) | F8: =CEILING(CEILING(F7*Premissas!$B$37/Premissas!$B$27,1)*Premissas!$B$28/Premissas!$B$34,1)+CEILING(CEILING(F7*Premissas!$B$38/Premissas!$B$30,1)*Premissas!$B$31/Premissas!$B$34,1) | G8: =CEILING(CEILING(G7*Premissas!$B$37/Premissas!$B$27,1)*Premissas!$B$28/Premissas!$B$34,1)+CEILING(CEILING(G7*Premissas!$B$38/Premissas!$B$30,1)*Premissas!$B$31/Premissas!$B$34,1) | H8: =CEILING(CEILING(H7*Premissas!$B$37/Premissas!$B$27,1)*Premissas!$B$28/Premissas!$B$34,1)+CEILING(CEILING(H7*Premissas!$B$38/Premissas!$B$30,1)*Premissas!$B$31/Premissas!$B$34,1) | I8: =CEILING(CEILING(I7*Premissas!$B$37/Premissas!$B$27,1)*Premissas!$B$28/Premissas!$B$34,1)+CEILING(CEILING(I7*Premissas!$B$38/Premissas!$B$30,1)*Premissas!$B$31/Premissas!$B$34,1) | J8: =CEILING(CEILING(J7*Premissas!$B$37/Premissas!$B$27,1)*Premissas!$B$28/Premissas!$B$34,1)+CEILING(CEILING(J7*Premissas!$B$38/Premissas!$B$30,1)*Premissas!$B$31/Premissas!$B$34,1) | K8: =CEILING(CEILING(K7*Premissas!$B$37/Premissas!$B$27,1)*Premissas!$B$28/Premissas!$B$34,1)+CEILING(CEILING(K7*Premissas!$B$38/Premissas!$B$30,1)*Premissas!$B$31/Premissas!$B$34,1) | ... S8: =CEILING(CEILING(S7*Premissas!$B$37/Premissas!$B$27,1)*Premissas!$B$28/Premissas!$B$34,1)+CEILING(CEILING(S7*Premissas!$B$38/Premissas!$B$30,1)*Premissas!$B$31/Premissas!$B$34,1) | U8: 🟩 verde claro = meses já positivos
A9: Ocupação das salas (100% = grade cheia) | B9: 0 | C9: 0 | D9: =MAX(CEILING(D7*Premissas!$B$37/Premissas!$B$27,1)*Premissas!$B$28/(Premissas!$B$26*Premissas!$B$32*Premissas!$B$33*Premissas!$B$25),CEILING(D7*Premissas!$B$38/Premissas!$B$30,1)*Premissas!$B$31/(Premissas!$B$29*Premissas!$B$32*Premissas!$B$33*Premissas!$B$25)) | E9: =MAX(CEILING(E7*Premissas!$B$37/Premissas!$B$27,1)*Premissas!$B$28/(Premissas!$B$26*Premissas!$B$32*Premissas!$B$33*Premissas!$B$25),CEILING(E7*Premissas!$B$38/Premissas!$B$30,1)*Premissas!$B$31/(Premissas!$B$29*Premissas!$B$32*Premissas!$B$33*Premissas!$B$25)) | F9: =MAX(CEILING(F7*Premissas!$B$37/Premissas!$B$27,1)*Premissas!$B$28/(Premissas!$B$26*Premissas!$B$32*Premissas!$B$33*Premissas!$B$25),CEILING(F7*Premissas!$B$38/Premissas!$B$30,1)*Premissas!$B$31/(Premissas!$B$29*Premissas!$B$32*Premissas!$B$33*Premissas!$B$25)) | G9: =MAX(CEILING(G7*Premissas!$B$37/Premissas!$B$27,1)*Premissas!$B$28/(Premissas!$B$26*Premissas!$B$32*Premissas!$B$33*Premissas!$B$25),CEILING(G7*Premissas!$B$38/Premissas!$B$30,1)*Premissas!$B$31/(Premissas!$B$29*Premissas!$B$32*Premissas!$B$33*Premissas!$B$25)) | H9: =MAX(CEILING(H7*Premissas!$B$37/Premissas!$B$27,1)*Premissas!$B$28/(Premissas!$B$26*Premissas!$B$32*Premissas!$B$33*Premissas!$B$25),CEILING(H7*Premissas!$B$38/Premissas!$B$30,1)*Premissas!$B$31/(Premissas!$B$29*Premissas!$B$32*Premissas!$B$33*Premissas!$B$25)) | I9: =MAX(CEILING(I7*Premissas!$B$37/Premissas!$B$27,1)*Premissas!$B$28/(Premissas!$B$26*Premissas!$B$32*Premissas!$B$33*Premissas!$B$25),CEILING(I7*Premissas!$B$38/Premissas!$B$30,1)*Premissas!$B$31/(Premissas!$B$29*Premissas!$B$32*Premissas!$B$33*Premissas!$B$25)) | J9: =MAX(CEILING(J7*Premissas!$B$37/Premissas!$B$27,1)*Premissas!$B$28/(Premissas!$B$26*Premissas!$B$32*Premissas!$B$33*Premissas!$B$25),CEILING(J7*Premissas!$B$38/Premissas!$B$30,1)*Premissas!$B$31/(Premissas!$B$29*Premissas!$B$32*Premissas!$B$33*Premissas!$B$25)) | K9: =MAX(CEILING(K7*Premissas!$B$37/Premissas!$B$27,1)*Premissas!$B$28/(Premissas!$B$26*Premissas!$B$32*Premissas!$B$33*Premissas!$B$25),CEILING(K7*Premissas!$B$38/Premissas!$B$30,1)*Premissas!$B$31/(Premissas!$B$29*Premissas!$B$32*Premissas!$B$33*Premissas!$B$25)) | ... S9: =MAX(CEILING(S7*Premissas!$B$37/Premissas!$B$27,1)*Premissas!$B$28/(Premissas!$B$26*Premissas!$B$32*Premissas!$B$33*Premissas!$B$25),CEILING(S7*Premissas!$B$38/Premissas!$B$30,1)*Premissas!$B$31/(Premissas!$B$29*Premissas!$B$32*Premissas!$B$33*Premissas!$B$25))
A11: RECEITA RECEBIDA (caixa)
A12: Matrícula | B12: =B4*Premissas!$B$3 | C12: =C4*Premissas!$B$3 | D12: =D4*Premissas!$B$3 | E12: =E4*Premissas!$B$3 | F12: =F4*Premissas!$B$3 | G12: =G4*Premissas!$B$3 | H12: =H4*Premissas!$B$3 | I12: =I4*Premissas!$B$3 | ... S12: =S4*Premissas!$B$3
A13: Mensalidade recebida (líq. de inadimplência) | B13: 0 | C13: 0 | D13: =C7*Premissas!$B$2*(1-Premissas!$B$9) | E13: =D7*Premissas!$B$2*(1-Premissas!$B$9) | F13: =E7*Premissas!$B$2*(1-Premissas!$B$9) | G13: =F7*Premissas!$B$2*(1-Premissas!$B$9) | H13: =G7*Premissas!$B$2*(1-Premissas!$B$9) | I13: =H7*Premissas!$B$2*(1-Premissas!$B$9) | J13: =I7*Premissas!$B$2*(1-Premissas!$B$9) | K13: =J7*Premissas!$B$2*(1-Premissas!$B$9) | ... S13: =R7*Premissas!$B$2*(1-Premissas!$B$9)
A14: Material antecipado no cartão | B14: =B4*Premissas!$B$5 | C14: =C4*Premissas!$B$5 | D14: =D4*Premissas!$B$5 | E14: =E4*Premissas!$B$5 | F14: =F4*Premissas!$B$5 | G14: =G4*Premissas!$B$5 | H14: =H4*Premissas!$B$5 | I14: =I4*Premissas!$B$5 | ... S14: =S4*Premissas!$B$5
A15: Receita recebida | B15: =SUM(B12:B14) | C15: =SUM(C12:C14) | D15: =SUM(D12:D14) | E15: =SUM(E12:E14) | F15: =SUM(F12:F14) | G15: =SUM(G12:G14) | H15: =SUM(H12:H14) | I15: =SUM(I12:I14) | ... S15: =SUM(S12:S14)
A17: BASE DO SIMPLES NACIONAL
A18: Faturamento do mês (nota emitida) | B18: =B4*Premissas!$B$3+B4*Premissas!$B$4 | C18: =C4*Premissas!$B$3+C4*Premissas!$B$4 | D18: =D4*Premissas!$B$3+C7*Premissas!$B$2+D4*Premissas!$B$4 | E18: =E4*Premissas!$B$3+D7*Premissas!$B$2+E4*Premissas!$B$4 | F18: =F4*Premissas!$B$3+E7*Premissas!$B$2+F4*Premissas!$B$4 | G18: =G4*Premissas!$B$3+F7*Premissas!$B$2+G4*Premissas!$B$4 | H18: =H4*Premissas!$B$3+G7*Premissas!$B$2+H4*Premissas!$B$4 | I18: =I4*Premissas!$B$3+H7*Premissas!$B$2+I4*Premissas!$B$4 | J18: =J4*Premissas!$B$3+I7*Premissas!$B$2+J4*Premissas!$B$4 | K18: =K4*Premissas!$B$3+J7*Premissas!$B$2+K4*Premissas!$B$4 | ... S18: =S4*Premissas!$B$3+R7*Premissas!$B$2+S4*Premissas!$B$4
A19: RBT12 proporcionalizado | B19: =SUM($B$18:B18)/1*12 | C19: =SUM($B$18:C18)/2*12 | D19: =SUM($B$18:D18)/3*12 | E19: =SUM($B$18:E18)/4*12 | F19: =SUM($B$18:F18)/5*12 | G19: =SUM($B$18:G18)/6*12 | H19: =SUM($B$18:H18)/7*12 | I19: =SUM($B$18:I18)/8*12 | J19: =SUM($B$18:J18)/9*12 | K19: =SUM($B$18:K18)/10*12 | L19: =SUM($B$18:L18)/11*12 | M19: =SUM(B18:M18) | N19: =SUM(C18:N18) | O19: =SUM(D18:O18) | P19: =SUM(E18:P18) | Q19: =SUM(F18:Q18) | R19: =SUM(G18:R18) | S19: =SUM(H18:S18)
A20: Alíquota efetiva do Simples | B20: =IF(B19=0,Premissas!$C$66,IF(B19<=Premissas!$B$66,(B19*Premissas!$C$66-Premissas!$D$66)/B19,IF(B19<=Premissas!$B$67,(B19*Premissas!$C$67-Premissas!$D$67)/B19,IF(B19<=Premissas!$B$68,(B19*Premissas!$C$68-Premissas!$D$68)/B19,IF(B19<=Premissas!$B$69,(B19*Premissas!$C$69-Premissas!$D$69)/B19,IF(B19<=Premissas!$B$70,(B19*Premissas!$C$70-Premissas!$D$70)/B19,(B19*Premissas!$C$71-Premissas!$D$71)/B19)))))) | C20: =IF(C19=0,Premissas!$C$66,IF(C19<=Premissas!$B$66,(C19*Premissas!$C$66-Premissas!$D$66)/C19,IF(C19<=Premissas!$B$67,(C19*Premissas!$C$67-Premissas!$D$67)/C19,IF(C19<=Premissas!$B$68,(C19*Premissas!$C$68-Premissas!$D$68)/C19,IF(C19<=Premissas!$B$69,(C19*Premissas!$C$69-Premissas!$D$69)/C19,IF(C19<=Premissas!$B$70,(C19*Premissas!$C$70-Premissas!$D$70)/C19,(C19*Premissas!$C$71-Premissas!$D$71)/C19)))))) | D20: =IF(D19=0,Premissas!$C$66,IF(D19<=Premissas!$B$66,(D19*Premissas!$C$66-Premissas!$D$66)/D19,IF(D19<=Premissas!$B$67,(D19*Premissas!$C$67-Premissas!$D$67)/D19,IF(D19<=Premissas!$B$68,(D19*Premissas!$C$68-Premissas!$D$68)/D19,IF(D19<=Premissas!$B$69,(D19*Premissas!$C$69-Premissas!$D$69)/D19,IF(D19<=Premissas!$B$70,(D19*Premissas!$C$70-Premissas!$D$70)/D19,(D19*Premissas!$C$71-Premissas!$D$71)/D19)))))) | E20: =IF(E19=0,Premissas!$C$66,IF(E19<=Premissas!$B$66,(E19*Premissas!$C$66-Premissas!$D$66)/E19,IF(E19<=Premissas!$B$67,(E19*Premissas!$C$67-Premissas!$D$67)/E19,IF(E19<=Premissas!$B$68,(E19*Premissas!$C$68-Premissas!$D$68)/E19,IF(E19<=Premissas!$B$69,(E19*Premissas!$C$69-Premissas!$D$69)/E19,IF(E19<=Premissas!$B$70,(E19*Premissas!$C$70-Premissas!$D$70)/E19,(E19*Premissas!$C$71-Premissas!$D$71)/E19)))))) | F20: =IF(F19=0,Premissas!$C$66,IF(F19<=Premissas!$B$66,(F19*Premissas!$C$66-Premissas!$D$66)/F19,IF(F19<=Premissas!$B$67,(F19*Premissas!$C$67-Premissas!$D$67)/F19,IF(F19<=Premissas!$B$68,(F19*Premissas!$C$68-Premissas!$D$68)/F19,IF(F19<=Premissas!$B$69,(F19*Premissas!$C$69-Premissas!$D$69)/F19,IF(F19<=Premissas!$B$70,(F19*Premissas!$C$70-Premissas!$D$70)/F19,(F19*Premissas!$C$71-Premissas!$D$71)/F19)))))) | G20: =IF(G19=0,Premissas!$C$66,IF(G19<=Premissas!$B$66,(G19*Premissas!$C$66-Premissas!$D$66)/G19,IF(G19<=Premissas!$B$67,(G19*Premissas!$C$67-Premissas!$D$67)/G19,IF(G19<=Premissas!$B$68,(G19*Premissas!$C$68-Premissas!$D$68)/G19,IF(G19<=Premissas!$B$69,(G19*Premissas!$C$69-Premissas!$D$69)/G19,IF(G19<=Premissas!$B$70,(G19*Premissas!$C$70-Premissas!$D$70)/G19,(G19*Premissas!$C$71-Premissas!$D$71)/G19)))))) | H20: =IF(H19=0,Premissas!$C$66,IF(H19<=Premissas!$B$66,(H19*Premissas!$C$66-Premissas!$D$66)/H19,IF(H19<=Premissas!$B$67,(H19*Premissas!$C$67-Premissas!$D$67)/H19,IF(H19<=Premissas!$B$68,(H19*Premissas!$C$68-Premissas!$D$68)/H19,IF(H19<=Premissas!$B$69,(H19*Premissas!$C$69-Premissas!$D$69)/H19,IF(H19<=Premissas!$B$70,(H19*Premissas!$C$70-Premissas!$D$70)/H19,(H19*Premissas!$C$71-Premissas!$D$71)/H19)))))) | I20: =IF(I19=0,Premissas!$C$66,IF(I19<=Premissas!$B$66,(I19*Premissas!$C$66-Premissas!$D$66)/I19,IF(I19<=Premissas!$B$67,(I19*Premissas!$C$67-Premissas!$D$67)/I19,IF(I19<=Premissas!$B$68,(I19*Premissas!$C$68-Premissas!$D$68)/I19,IF(I19<=Premissas!$B$69,(I19*Premissas!$C$69-Premissas!$D$69)/I19,IF(I19<=Premissas!$B$70,(I19*Premissas!$C$70-Premissas!$D$70)/I19,(I19*Premissas!$C$71-Premissas!$D$71)/I19)))))) | ... S20: =IF(S19=0,Premissas!$C$66,IF(S19<=Premissas!$B$66,(S19*Premissas!$C$66-Premissas!$D$66)/S19,IF(S19<=Premissas!$B$67,(S19*Premissas!$C$67-Premissas!$D$67)/S19,IF(S19<=Premissas!$B$68,(S19*Premissas!$C$68-Premissas!$D$68)/S19,IF(S19<=Premissas!$B$69,(S19*Premissas!$C$69-Premissas!$D$69)/S19,IF(S19<=Premissas!$B$70,(S19*Premissas!$C$70-Premissas!$D$70)/S19,(S19*Premissas!$C$71-Premissas!$D$71)/S19))))))
A22: DESPESAS
A23: Impostos (Simples progressivo) | B23: =B18*B20 | C23: =C18*C20 | D23: =D18*D20 | E23: =E18*E20 | F23: =F18*F20 | G23: =G18*G20 | H23: =H18*H20 | I23: =I18*I20 | ... S23: =S18*S20
A24: Material — parcelas 12x | B24: 0 | C24: 0 | D24: =SUM($B$4:D4)*Premissas!$B$6/12 | E24: =SUM($B$4:E4)*Premissas!$B$6/12 | F24: =SUM($B$4:F4)*Premissas!$B$6/12 | G24: =SUM($B$4:G4)*Premissas!$B$6/12 | H24: =SUM($B$4:H4)*Premissas!$B$6/12 | I24: =SUM($B$4:I4)*Premissas!$B$6/12 | J24: =SUM($B$4:J4)*Premissas!$B$6/12 | K24: =SUM($B$4:K4)*Premissas!$B$6/12 | ... O24: =SUM($B$4:O4)*Premissas!$B$6/12 | P24: =SUM(E4:P4)*Premissas!$B$6/12 | Q24: =SUM(F4:Q4)*Premissas!$B$6/12 | R24: =SUM(G4:R4)*Premissas!$B$6/12 | S24: =SUM(H4:S4)*Premissas!$B$6/12
A25: Comissão do vendedor | B25: =IF(B2>=Premissas!$D$14,B4*Premissas!$B$10*(1+Premissas!$B$11),0) | C25: =IF(C2>=Premissas!$D$14,C4*Premissas!$B$10*(1+Premissas!$B$11),0) | D25: =IF(D2>=Premissas!$D$14,D4*Premissas!$B$10*(1+Premissas!$B$11),0) | E25: =IF(E2>=Premissas!$D$14,E4*Premissas!$B$10*(1+Premissas!$B$11),0) | F25: =IF(F2>=Premissas!$D$14,F4*Premissas!$B$10*(1+Premissas!$B$11),0) | G25: =IF(G2>=Premissas!$D$14,G4*Premissas!$B$10*(1+Premissas!$B$11),0) | H25: =IF(H2>=Premissas!$D$14,H4*Premissas!$B$10*(1+Premissas!$B$11),0) | I25: =IF(I2>=Premissas!$D$14,I4*Premissas!$B$10*(1+Premissas!$B$11),0) | ... S25: =IF(S2>=Premissas!$D$14,S4*Premissas!$B$10*(1+Premissas!$B$11),0)
A26: Aquisição de alunos (custo dos canais) | B26: ='Canais de aquisição'!C$10 | C26: ='Canais de aquisição'!D$10 | D26: ='Canais de aquisição'!E$10 | E26: ='Canais de aquisição'!F$10 | F26: ='Canais de aquisição'!G$10 | G26: ='Canais de aquisição'!H$10 | H26: ='Canais de aquisição'!I$10 | I26: ='Canais de aquisição'!J$10 | ... S26: ='Canais de aquisição'!T$10
A27: Folha + encargos mensais (só quem já entrou) | B27: =SUMPRODUCT((Premissas!$D$14:$D$20<=B2)*Premissas!$B$14:$B$20*(1+Premissas!$C$14:$C$20*Premissas!$B$11)) | C27: =SUMPRODUCT((Premissas!$D$14:$D$20<=C2)*Premissas!$B$14:$B$20*(1+Premissas!$C$14:$C$20*Premissas!$B$11)) | D27: =SUMPRODUCT((Premissas!$D$14:$D$20<=D2)*Premissas!$B$14:$B$20*(1+Premissas!$C$14:$C$20*Premissas!$B$11)) | E27: =SUMPRODUCT((Premissas!$D$14:$D$20<=E2)*Premissas!$B$14:$B$20*(1+Premissas!$C$14:$C$20*Premissas!$B$11)) | F27: =SUMPRODUCT((Premissas!$D$14:$D$20<=F2)*Premissas!$B$14:$B$20*(1+Premissas!$C$14:$C$20*Premissas!$B$11)) | G27: =SUMPRODUCT((Premissas!$D$14:$D$20<=G2)*Premissas!$B$14:$B$20*(1+Premissas!$C$14:$C$20*Premissas!$B$11)) | H27: =SUMPRODUCT((Premissas!$D$14:$D$20<=H2)*Premissas!$B$14:$B$20*(1+Premissas!$C$14:$C$20*Premissas!$B$11)) | I27: =SUMPRODUCT((Premissas!$D$14:$D$20<=I2)*Premissas!$B$14:$B$20*(1+Premissas!$C$14:$C$20*Premissas!$B$11)) | ... S27: =SUMPRODUCT((Premissas!$D$14:$D$20<=S2)*Premissas!$B$14:$B$20*(1+Premissas!$C$14:$C$20*Premissas!$B$11))
A28: Vale-transporte / benefícios | B28: =SUMPRODUCT((Premissas!$D$14:$D$20<=B2)*Premissas!$C$14:$C$20*(Premissas!$B$14:$B$20>0))*Premissas!$B$12 | C28: =SUMPRODUCT((Premissas!$D$14:$D$20<=C2)*Premissas!$C$14:$C$20*(Premissas!$B$14:$B$20>0))*Premissas!$B$12 | D28: =SUMPRODUCT((Premissas!$D$14:$D$20<=D2)*Premissas!$C$14:$C$20*(Premissas!$B$14:$B$20>0))*Premissas!$B$12 | E28: =SUMPRODUCT((Premissas!$D$14:$D$20<=E2)*Premissas!$C$14:$C$20*(Premissas!$B$14:$B$20>0))*Premissas!$B$12 | F28: =SUMPRODUCT((Premissas!$D$14:$D$20<=F2)*Premissas!$C$14:$C$20*(Premissas!$B$14:$B$20>0))*Premissas!$B$12 | G28: =SUMPRODUCT((Premissas!$D$14:$D$20<=G2)*Premissas!$C$14:$C$20*(Premissas!$B$14:$B$20>0))*Premissas!$B$12 | H28: =SUMPRODUCT((Premissas!$D$14:$D$20<=H2)*Premissas!$C$14:$C$20*(Premissas!$B$14:$B$20>0))*Premissas!$B$12 | I28: =SUMPRODUCT((Premissas!$D$14:$D$20<=I2)*Premissas!$C$14:$C$20*(Premissas!$B$14:$B$20>0))*Premissas!$B$12 | ... S28: =SUMPRODUCT((Premissas!$D$14:$D$20<=S2)*Premissas!$C$14:$C$20*(Premissas!$B$14:$B$20>0))*Premissas!$B$12
A29: 13º e férias (desembolso) | B29: 0 | C29: 0 | D29: =Premissas!$B$41*SUMPRODUCT((Premissas!$D$14:$D$20<=2)*Premissas!$C$14:$C$20*Premissas!$B$14:$B$20*(2-((Premissas!$D$14:$D$20>0)*Premissas!$D$14:$D$20+(Premissas!$D$14:$D$20<=0)*0)+1)/12)+0 | E29: 0 | F29: 0 | G29: 0 | H29: 0 | I29: 0 | J29: 0 | K29: 0 | L29: 0 | M29: 0 | N29: =0+Premissas!$B$42*SUMPRODUCT((Premissas!$D$14:$D$20=0)*Premissas!$C$14:$C$20*Premissas!$B$14:$B$20)*4/3 | O29: =0+Premissas!$B$42*SUMPRODUCT((Premissas!$D$14:$D$20=1)*Premissas!$C$14:$C$20*Premissas!$B$14:$B$20)*4/3 | P29: =Premissas!$B$41*SUMPRODUCT((Premissas!$D$14:$D$20<=14)*Premissas!$C$14:$C$20*Premissas!$B$14:$B$20*(14-((Premissas!$D$14:$D$20>3)*Premissas!$D$14:$D$20+(Premissas!$D$14:$D$20<=3)*3)+1)/12)+Premissas!$B$42*SUMPRODUCT((Premissas!$D$14:$D$20=2)*Premissas!$C$14:$C$20*Premissas!$B$14:$B$20)*4/3 | Q29: =0+Premissas!$B$42*SUMPRODUCT((Premissas!$D$14:$D$20=3)*Premissas!$C$14:$C$20*Premissas!$B$14:$B$20)*4/3 | R29: =0+Premissas!$B$42*SUMPRODUCT((Premissas!$D$14:$D$20=4)*Premissas!$C$14:$C$20*Premissas!$B$14:$B$20)*4/3 | S29: =0+Premissas!$B$42*SUMPRODUCT((Premissas!$D$14:$D$20=5)*Premissas!$C$14:$C$20*Premissas!$B$14:$B$20)*4/3
A30: Professores (salário + encargos) | B30: 0 | C30: 0 | D30: =D8*Premissas!$B$35 | E30: =E8*Premissas!$B$35 | F30: =F8*Premissas!$B$35 | G30: =G8*Premissas!$B$35 | H30: =H8*Premissas!$B$35 | I30: =I8*Premissas!$B$35 | J30: =J8*Premissas!$B$35 | K30: =K8*Premissas!$B$35 | ... S30: =S8*Premissas!$B$35
A31: Aluguel do espaço | B31: ='Custos mês a mês'!B2 | C31: ='Custos mês a mês'!C2 | D31: ='Custos mês a mês'!D2 | E31: ='Custos mês a mês'!E2 | F31: ='Custos mês a mês'!F2 | G31: ='Custos mês a mês'!G2 | H31: ='Custos mês a mês'!H2 | I31: ='Custos mês a mês'!I2 | ... S31: ='Custos mês a mês'!S2
A32: Água | B32: ='Custos mês a mês'!B3 | C32: ='Custos mês a mês'!C3 | D32: ='Custos mês a mês'!D3 | E32: ='Custos mês a mês'!E3 | F32: ='Custos mês a mês'!F3 | G32: ='Custos mês a mês'!G3 | H32: ='Custos mês a mês'!H3 | I32: ='Custos mês a mês'!I3 | ... S32: ='Custos mês a mês'!S3
A33: Luz | B33: ='Custos mês a mês'!B4 | C33: ='Custos mês a mês'!C4 | D33: ='Custos mês a mês'!D4 | E33: ='Custos mês a mês'!E4 | F33: ='Custos mês a mês'!F4 | G33: ='Custos mês a mês'!G4 | H33: ='Custos mês a mês'!H4 | I33: ='Custos mês a mês'!I4 | ... S33: ='Custos mês a mês'!S4
A34: Telefone | B34: ='Custos mês a mês'!B5 | C34: ='Custos mês a mês'!C5 | D34: ='Custos mês a mês'!D5 | E34: ='Custos mês a mês'!E5 | F34: ='Custos mês a mês'!F5 | G34: ='Custos mês a mês'!G5 | H34: ='Custos mês a mês'!H5 | I34: ='Custos mês a mês'!I5 | ... S34: ='Custos mês a mês'!S5
A35: Internet | B35: ='Custos mês a mês'!B6 | C35: ='Custos mês a mês'!C6 | D35: ='Custos mês a mês'!D6 | E35: ='Custos mês a mês'!E6 | F35: ='Custos mês a mês'!F6 | G35: ='Custos mês a mês'!G6 | H35: ='Custos mês a mês'!H6 | I35: ='Custos mês a mês'!I6 | ... S35: ='Custos mês a mês'!S6
A36: Sistema de gestão DiscoverON | B36: ='Custos mês a mês'!B7 | C36: ='Custos mês a mês'!C7 | D36: ='Custos mês a mês'!D7 | E36: ='Custos mês a mês'!E7 | F36: ='Custos mês a mês'!F7 | G36: ='Custos mês a mês'!G7 | H36: ='Custos mês a mês'!H7 | I36: ='Custos mês a mês'!I7 | ... S36: ='Custos mês a mês'!S7
A37: Itens para aula | B37: ='Custos mês a mês'!B8 | C37: ='Custos mês a mês'!C8 | D37: ='Custos mês a mês'!D8 | E37: ='Custos mês a mês'!E8 | F37: ='Custos mês a mês'!F8 | G37: ='Custos mês a mês'!G8 | H37: ='Custos mês a mês'!H8 | I37: ='Custos mês a mês'!I8 | ... S37: ='Custos mês a mês'!S8
A38: Materiais de limpeza + higiene | B38: ='Custos mês a mês'!B9 | C38: ='Custos mês a mês'!C9 | D38: ='Custos mês a mês'!D9 | E38: ='Custos mês a mês'!E9 | F38: ='Custos mês a mês'!F9 | G38: ='Custos mês a mês'!G9 | H38: ='Custos mês a mês'!H9 | I38: ='Custos mês a mês'!I9 | ... S38: ='Custos mês a mês'!S9
A39: Brindes | B39: ='Custos mês a mês'!B10 | C39: ='Custos mês a mês'!C10 | D39: ='Custos mês a mês'!D10 | E39: ='Custos mês a mês'!E10 | F39: ='Custos mês a mês'!F10 | G39: ='Custos mês a mês'!G10 | H39: ='Custos mês a mês'!H10 | I39: ='Custos mês a mês'!I10 | ... S39: ='Custos mês a mês'!S10
A40: Marketing | B40: ='Custos mês a mês'!B11 | C40: ='Custos mês a mês'!C11 | D40: ='Custos mês a mês'!D11 | E40: ='Custos mês a mês'!E11 | F40: ='Custos mês a mês'!F11 | G40: ='Custos mês a mês'!G11 | H40: ='Custos mês a mês'!H11 | I40: ='Custos mês a mês'!I11 | ... S40: ='Custos mês a mês'!S11
A41: Aluguel dos computadores | B41: ='Custos mês a mês'!B12 | C41: ='Custos mês a mês'!C12 | D41: ='Custos mês a mês'!D12 | E41: ='Custos mês a mês'!E12 | F41: ='Custos mês a mês'!F12 | G41: ='Custos mês a mês'!G12 | H41: ='Custos mês a mês'!H12 | I41: ='Custos mês a mês'!I12 | ... S41: ='Custos mês a mês'!S12
A42: Seguro empresarial | B42: ='Custos mês a mês'!B13 | C42: ='Custos mês a mês'!C13 | D42: ='Custos mês a mês'!D13 | E42: ='Custos mês a mês'!E13 | F42: ='Custos mês a mês'!F13 | G42: ='Custos mês a mês'!G13 | H42: ='Custos mês a mês'!H13 | I42: ='Custos mês a mês'!I13 | ... S42: ='Custos mês a mês'!S13
... A45: Pró-labore | B45: ='Custos mês a mês'!B16 | C45: ='Custos mês a mês'!C16 | D45: ='Custos mês a mês'!D16 | E45: ='Custos mês a mês'!E16 | F45: ='Custos mês a mês'!F16 | G45: ='Custos mês a mês'!G16 | H45: ='Custos mês a mês'!H16 | I45: ='Custos mês a mês'!I16 | ... S45: ='Custos mês a mês'!S16
A46: Total de despesas | B46: =SUM(B23:B45) | C46: =SUM(C23:C45) | D46: =SUM(D23:D45) | E46: =SUM(E23:E45) | F46: =SUM(F23:F45) | G46: =SUM(G23:G45) | H46: =SUM(H23:H45) | I46: =SUM(I23:I45) | ... S46: =SUM(S23:S45)
A48: Resultado do mês | B48: =B15-B46 | C48: =C15-C46 | D48: =D15-D46 | E48: =E15-E46 | F48: =F15-F46 | G48: =G15-G46 | H48: =H15-H46 | I48: =I15-I46 | ... S48: =S15-S46
A49: Caixa acumulado (operacional) | B49: =B48 | C49: =B49+C48 | D49: =C49+D48 | E49: =D49+E48 | F49: =E49+F48 | G49: =F49+G48 | H49: =G49+H48 | I49: =H49+I48 | J49: =I49+J48 | ... S49: =R49+S48
A50: Caixa acumulado incl. investimento | B50: =B49-INVEST_TOTAL | C50: =C49-INVEST_TOTAL | D50: =D49-INVEST_TOTAL | E50: =E49-INVEST_TOTAL | F50: =F49-INVEST_TOTAL | G50: =G49-INVEST_TOTAL | H50: =H49-INVEST_TOTAL | I50: =I49-INVEST_TOTAL | ... S50: =S49-INVEST_TOTAL
A51: MARCOS | D51: =IF(AND(D48>0,COUNTIF($D48:D48,">0")=1),IF(AND(D50>=0,COUNTIF($D50:D50,">=0")=1),"BE + PAYBACK","BREAK-EVEN"),IF(AND(D50>=0,COUNTIF($D50:D50,">=0")=1),"PAYBACK","")) | E51: =IF(AND(E48>0,COUNTIF($D48:E48,">0")=1),IF(AND(E50>=0,COUNTIF($D50:E50,">=0")=1),"BE + PAYBACK","BREAK-EVEN"),IF(AND(E50>=0,COUNTIF($D50:E50,">=0")=1),"PAYBACK","")) | F51: =IF(AND(F48>0,COUNTIF($D48:F48,">0")=1),IF(AND(F50>=0,COUNTIF($D50:F50,">=0")=1),"BE + PAYBACK","BREAK-EVEN"),IF(AND(F50>=0,COUNTIF($D50:F50,">=0")=1),"PAYBACK","")) | G51: =IF(AND(G48>0,COUNTIF($D48:G48,">0")=1),IF(AND(G50>=0,COUNTIF($D50:G50,">=0")=1),"BE + PAYBACK","BREAK-EVEN"),IF(AND(G50>=0,COUNTIF($D50:G50,">=0")=1),"PAYBACK","")) | H51: =IF(AND(H48>0,COUNTIF($D48:H48,">0")=1),IF(AND(H50>=0,COUNTIF($D50:H50,">=0")=1),"BE + PAYBACK","BREAK-EVEN"),IF(AND(H50>=0,COUNTIF($D50:H50,">=0")=1),"PAYBACK","")) | I51: =IF(AND(I48>0,COUNTIF($D48:I48,">0")=1),IF(AND(I50>=0,COUNTIF($D50:I50,">=0")=1),"BE + PAYBACK","BREAK-EVEN"),IF(AND(I50>=0,COUNTIF($D50:I50,">=0")=1),"PAYBACK","")) | J51: =IF(AND(J48>0,COUNTIF($D48:J48,">0")=1),IF(AND(J50>=0,COUNTIF($D50:J50,">=0")=1),"BE + PAYBACK","BREAK-EVEN"),IF(AND(J50>=0,COUNTIF($D50:J50,">=0")=1),"PAYBACK","")) | K51: =IF(AND(K48>0,COUNTIF($D48:K48,">0")=1),IF(AND(K50>=0,COUNTIF($D50:K50,">=0")=1),"BE + PAYBACK","BREAK-EVEN"),IF(AND(K50>=0,COUNTIF($D50:K50,">=0")=1),"PAYBACK","")) | ... S51: =IF(AND(S48>0,COUNTIF($D48:S48,">0")=1),IF(AND(S50>=0,COUNTIF($D50:S50,">=0")=1),"BE + PAYBACK","BREAK-EVEN"),IF(AND(S50>=0,COUNTIF($D50:S50,">=0")=1),"PAYBACK",""))

Sheet Cenário Otimista
A1: Cenário Otimista | B1: Out (obras) | C1: Nov (obras) | D1: Dez (M1) | E1: Jan (M2) | F1: Fev (M3) | G1: Mar (M4) | H1: Abr (M5) | I1: Mai (M6) | J1: Jun (M7) | K1: Jul (M8) | L1: Ago (M9) | M1: Set (M10) | N1: Out (M11) | O1: Nov (M12) | P1: Dez (M13) | Q1: Jan (M14) | R1: Fev (M15) | S1: Mar (M16)
A2: Período (0 = out) | B2: 0 | C2: 1 | D2: 2 | E2: 3 | F2: 4 | G2: 5 | H2: 6 | I2: 7 | J2: 8 | K2: 9 | L2: 10 | M2: 11 | N2: 12 | O2: 13 | P2: 14 | Q2: 15 | R2: 16 | S2: 17
A3: Matrículas — entrada manual ✏️ editável | B3: 5 | C3: 40 | D3: 15 | E3: 35 | F3: 30 | G3: 20 | H3: 20 | I3: 20 | J3: 20 | K3: 40 | L3: 40 | M3: 20 | N3: 20 | O3: 40 | P3: 30 | Q3: 40 | R3: 40 | S3: 20 | U3: Break-even (alunos):
A4: Matrículas no período (vale para o cálculo) | B4: =IF(Premissas!$B$59=3,'Canais de aquisição'!C$9,IF(Premissas!$B$59=2,ROUND('Custos mês a mês'!B$11/MAX(Premissas!$B$60,1),0),B3)) | C4: =IF(Premissas!$B$59=3,'Canais de aquisição'!D$9,IF(Premissas!$B$59=2,ROUND('Custos mês a mês'!C$11/MAX(Premissas!$B$60,1),0),C3)) | D4: =IF(Premissas!$B$59=3,'Canais de aquisição'!E$9,IF(Premissas!$B$59=2,ROUND('Custos mês a mês'!D$11/MAX(Premissas!$B$60,1),0),D3)) | E4: =IF(Premissas!$B$59=3,'Canais de aquisição'!F$9,IF(Premissas!$B$59=2,ROUND('Custos mês a mês'!E$11/MAX(Premissas!$B$60,1),0),E3)) | F4: =IF(Premissas!$B$59=3,'Canais de aquisição'!G$9,IF(Premissas!$B$59=2,ROUND('Custos mês a mês'!F$11/MAX(Premissas!$B$60,1),0),F3)) | G4: =IF(Premissas!$B$59=3,'Canais de aquisição'!H$9,IF(Premissas!$B$59=2,ROUND('Custos mês a mês'!G$11/MAX(Premissas!$B$60,1),0),G3)) | H4: =IF(Premissas!$B$59=3,'Canais de aquisição'!I$9,IF(Premissas!$B$59=2,ROUND('Custos mês a mês'!H$11/MAX(Premissas!$B$60,1),0),H3)) | I4: =IF(Premissas!$B$59=3,'Canais de aquisição'!J$9,IF(Premissas!$B$59=2,ROUND('Custos mês a mês'!I$11/MAX(Premissas!$B$60,1),0),I3)) | ... S4: =IF(Premissas!$B$59=3,'Canais de aquisição'!T$9,IF(Premissas!$B$59=2,ROUND('Custos mês a mês'!S$11/MAX(Premissas!$B$60,1),0),S3)) | U4: =Premissas!$B$90
A5: CAC realizado (marketing + canais ÷ matrículas) | B5: =IF(B4=0,0,('Custos mês a mês'!B$11+'Canais de aquisição'!C$10)/B4) | C5: =IF(C4=0,0,('Custos mês a mês'!C$11+'Canais de aquisição'!D$10)/C4) | D5: =IF(D4=0,0,('Custos mês a mês'!D$11+'Canais de aquisição'!E$10)/D4) | E5: =IF(E4=0,0,('Custos mês a mês'!E$11+'Canais de aquisição'!F$10)/E4) | F5: =IF(F4=0,0,('Custos mês a mês'!F$11+'Canais de aquisição'!G$10)/F4) | G5: =IF(G4=0,0,('Custos mês a mês'!G$11+'Canais de aquisição'!H$10)/G4) | H5: =IF(H4=0,0,('Custos mês a mês'!H$11+'Canais de aquisição'!I$10)/H4) | I5: =IF(I4=0,0,('Custos mês a mês'!I$11+'Canais de aquisição'!J$10)/I4) | ... S5: =IF(S4=0,0,('Custos mês a mês'!S$11+'Canais de aquisição'!T$10)/S4)
A6: Desistências no mês | B6: 0 | C6: =B7*Premissas!$B$8*Premissas!$B$55 | D6: =C7*Premissas!$B$8*Premissas!$B$56 | E6: =D7*Premissas!$B$8*Premissas!$B$45 | F6: =E7*Premissas!$B$8*Premissas!$B$46 | G6: =F7*Premissas!$B$8*Premissas!$B$47 | H6: =G7*Premissas!$B$8*Premissas!$B$48 | I6: =H7*Premissas!$B$8*Premissas!$B$49 | J6: =I7*Premissas!$B$8*Premissas!$B$50 | K6: =J7*Premissas!$B$8*Premissas!$B$51 | L6: =K7*Premissas!$B$8*Premissas!$B$52 | M6: =L7*Premissas!$B$8*Premissas!$B$53 | N6: =M7*Premissas!$B$8*Premissas!$B$54 | O6: =N7*Premissas!$B$8*Premissas!$B$55 | P6: =O7*Premissas!$B$8*Premissas!$B$56 | Q6: =P7*Premissas!$B$8*Premissas!$B$45 | R6: =Q7*Premissas!$B$8*Premissas!$B$46 | S6: =R7*Premissas!$B$8*Premissas!$B$47 | U6: 🟢 VERDE FORTE = mês do BREAK-EVEN
A7: Total de alunos | B7: =B4 | C7: =B7-C6+C4 | D7: =C7-D6+D4 | E7: =D7-E6+E4 | F7: =E7-F6+F4 | G7: =F7-G6+G4 | H7: =G7-H6+H4 | I7: =H7-I6+I4 | J7: =I7-J6+J4 | ... S7: =R7-S6+S4 | U7: 🟦 AZUL = mês do PAYBACK
A8: Professores necessários | B8: 0 | C8: 0 | D8: =CEILING(CEILING(D7*Premissas!$B$37/Premissas!$B$27,1)*Premissas!$B$28/Premissas!$B$34,1)+CEILING(CEILING(D7*Premissas!$B$38/Premissas!$B$30,1)*Premissas!$B$31/Premissas!$B$34,1) | E8: =CEILING(CEILING(E7*Premissas!$B$37/Premissas!$B$27,1)*Premissas!$B$28/Premissas!$B$34,1)+CEILING(CEILING(E7*Premissas!$B$38/Premissas!$B$30,1)*Premissas!$B$31/Premissas!$B$34,1) | F8: =CEILING(CEILING(F7*Premissas!$B$37/Premissas!$B$27,1)*Premissas!$B$28/Premissas!$B$34,1)+CEILING(CEILING(F7*Premissas!$B$38/Premissas!$B$30,1)*Premissas!$B$31/Premissas!$B$34,1) | G8: =CEILING(CEILING(G7*Premissas!$B$37/Premissas!$B$27,1)*Premissas!$B$28/Premissas!$B$34,1)+CEILING(CEILING(G7*Premissas!$B$38/Premissas!$B$30,1)*Premissas!$B$31/Premissas!$B$34,1) | H8: =CEILING(CEILING(H7*Premissas!$B$37/Premissas!$B$27,1)*Premissas!$B$28/Premissas!$B$34,1)+CEILING(CEILING(H7*Premissas!$B$38/Premissas!$B$30,1)*Premissas!$B$31/Premissas!$B$34,1) | I8: =CEILING(CEILING(I7*Premissas!$B$37/Premissas!$B$27,1)*Premissas!$B$28/Premissas!$B$34,1)+CEILING(CEILING(I7*Premissas!$B$38/Premissas!$B$30,1)*Premissas!$B$31/Premissas!$B$34,1) | J8: =CEILING(CEILING(J7*Premissas!$B$37/Premissas!$B$27,1)*Premissas!$B$28/Premissas!$B$34,1)+CEILING(CEILING(J7*Premissas!$B$38/Premissas!$B$30,1)*Premissas!$B$31/Premissas!$B$34,1) | K8: =CEILING(CEILING(K7*Premissas!$B$37/Premissas!$B$27,1)*Premissas!$B$28/Premissas!$B$34,1)+CEILING(CEILING(K7*Premissas!$B$38/Premissas!$B$30,1)*Premissas!$B$31/Premissas!$B$34,1) | ... S8: =CEILING(CEILING(S7*Premissas!$B$37/Premissas!$B$27,1)*Premissas!$B$28/Premissas!$B$34,1)+CEILING(CEILING(S7*Premissas!$B$38/Premissas!$B$30,1)*Premissas!$B$31/Premissas!$B$34,1) | U8: 🟩 verde claro = meses já positivos
A9: Ocupação das salas (100% = grade cheia) | B9: 0 | C9: 0 | D9: =MAX(CEILING(D7*Premissas!$B$37/Premissas!$B$27,1)*Premissas!$B$28/(Premissas!$B$26*Premissas!$B$32*Premissas!$B$33*Premissas!$B$25),CEILING(D7*Premissas!$B$38/Premissas!$B$30,1)*Premissas!$B$31/(Premissas!$B$29*Premissas!$B$32*Premissas!$B$33*Premissas!$B$25)) | E9: =MAX(CEILING(E7*Premissas!$B$37/Premissas!$B$27,1)*Premissas!$B$28/(Premissas!$B$26*Premissas!$B$32*Premissas!$B$33*Premissas!$B$25),CEILING(E7*Premissas!$B$38/Premissas!$B$30,1)*Premissas!$B$31/(Premissas!$B$29*Premissas!$B$32*Premissas!$B$33*Premissas!$B$25)) | F9: =MAX(CEILING(F7*Premissas!$B$37/Premissas!$B$27,1)*Premissas!$B$28/(Premissas!$B$26*Premissas!$B$32*Premissas!$B$33*Premissas!$B$25),CEILING(F7*Premissas!$B$38/Premissas!$B$30,1)*Premissas!$B$31/(Premissas!$B$29*Premissas!$B$32*Premissas!$B$33*Premissas!$B$25)) | G9: =MAX(CEILING(G7*Premissas!$B$37/Premissas!$B$27,1)*Premissas!$B$28/(Premissas!$B$26*Premissas!$B$32*Premissas!$B$33*Premissas!$B$25),CEILING(G7*Premissas!$B$38/Premissas!$B$30,1)*Premissas!$B$31/(Premissas!$B$29*Premissas!$B$32*Premissas!$B$33*Premissas!$B$25)) | H9: =MAX(CEILING(H7*Premissas!$B$37/Premissas!$B$27,1)*Premissas!$B$28/(Premissas!$B$26*Premissas!$B$32*Premissas!$B$33*Premissas!$B$25),CEILING(H7*Premissas!$B$38/Premissas!$B$30,1)*Premissas!$B$31/(Premissas!$B$29*Premissas!$B$32*Premissas!$B$33*Premissas!$B$25)) | I9: =MAX(CEILING(I7*Premissas!$B$37/Premissas!$B$27,1)*Premissas!$B$28/(Premissas!$B$26*Premissas!$B$32*Premissas!$B$33*Premissas!$B$25),CEILING(I7*Premissas!$B$38/Premissas!$B$30,1)*Premissas!$B$31/(Premissas!$B$29*Premissas!$B$32*Premissas!$B$33*Premissas!$B$25)) | J9: =MAX(CEILING(J7*Premissas!$B$37/Premissas!$B$27,1)*Premissas!$B$28/(Premissas!$B$26*Premissas!$B$32*Premissas!$B$33*Premissas!$B$25),CEILING(J7*Premissas!$B$38/Premissas!$B$30,1)*Premissas!$B$31/(Premissas!$B$29*Premissas!$B$32*Premissas!$B$33*Premissas!$B$25)) | K9: =MAX(CEILING(K7*Premissas!$B$37/Premissas!$B$27,1)*Premissas!$B$28/(Premissas!$B$26*Premissas!$B$32*Premissas!$B$33*Premissas!$B$25),CEILING(K7*Premissas!$B$38/Premissas!$B$30,1)*Premissas!$B$31/(Premissas!$B$29*Premissas!$B$32*Premissas!$B$33*Premissas!$B$25)) | ... S9: =MAX(CEILING(S7*Premissas!$B$37/Premissas!$B$27,1)*Premissas!$B$28/(Premissas!$B$26*Premissas!$B$32*Premissas!$B$33*Premissas!$B$25),CEILING(S7*Premissas!$B$38/Premissas!$B$30,1)*Premissas!$B$31/(Premissas!$B$29*Premissas!$B$32*Premissas!$B$33*Premissas!$B$25))
A11: RECEITA RECEBIDA (caixa)
A12: Matrícula | B12: =B4*Premissas!$B$3 | C12: =C4*Premissas!$B$3 | D12: =D4*Premissas!$B$3 | E12: =E4*Premissas!$B$3 | F12: =F4*Premissas!$B$3 | G12: =G4*Premissas!$B$3 | H12: =H4*Premissas!$B$3 | I12: =I4*Premissas!$B$3 | ... S12: =S4*Premissas!$B$3
A13: Mensalidade recebida (líq. de inadimplência) | B13: 0 | C13: 0 | D13: =C7*Premissas!$B$2*(1-Premissas!$B$9) | E13: =D7*Premissas!$B$2*(1-Premissas!$B$9) | F13: =E7*Premissas!$B$2*(1-Premissas!$B$9) | G13: =F7*Premissas!$B$2*(1-Premissas!$B$9) | H13: =G7*Premissas!$B$2*(1-Premissas!$B$9) | I13: =H7*Premissas!$B$2*(1-Premissas!$B$9) | J13: =I7*Premissas!$B$2*(1-Premissas!$B$9) | K13: =J7*Premissas!$B$2*(1-Premissas!$B$9) | ... S13: =R7*Premissas!$B$2*(1-Premissas!$B$9)
A14: Material antecipado no cartão | B14: =B4*Premissas!$B$5 | C14: =C4*Premissas!$B$5 | D14: =D4*Premissas!$B$5 | E14: =E4*Premissas!$B$5 | F14: =F4*Premissas!$B$5 | G14: =G4*Premissas!$B$5 | H14: =H4*Premissas!$B$5 | I14: =I4*Premissas!$B$5 | ... S14: =S4*Premissas!$B$5
A15: Receita recebida | B15: =SUM(B12:B14) | C15: =SUM(C12:C14) | D15: =SUM(D12:D14) | E15: =SUM(E12:E14) | F15: =SUM(F12:F14) | G15: =SUM(G12:G14) | H15: =SUM(H12:H14) | I15: =SUM(I12:I14) | ... S15: =SUM(S12:S14)
A17: BASE DO SIMPLES NACIONAL
A18: Faturamento do mês (nota emitida) | B18: =B4*Premissas!$B$3+B4*Premissas!$B$4 | C18: =C4*Premissas!$B$3+C4*Premissas!$B$4 | D18: =D4*Premissas!$B$3+C7*Premissas!$B$2+D4*Premissas!$B$4 | E18: =E4*Premissas!$B$3+D7*Premissas!$B$2+E4*Premissas!$B$4 | F18: =F4*Premissas!$B$3+E7*Premissas!$B$2+F4*Premissas!$B$4 | G18: =G4*Premissas!$B$3+F7*Premissas!$B$2+G4*Premissas!$B$4 | H18: =H4*Premissas!$B$3+G7*Premissas!$B$2+H4*Premissas!$B$4 | I18: =I4*Premissas!$B$3+H7*Premissas!$B$2+I4*Premissas!$B$4 | J18: =J4*Premissas!$B$3+I7*Premissas!$B$2+J4*Premissas!$B$4 | K18: =K4*Premissas!$B$3+J7*Premissas!$B$2+K4*Premissas!$B$4 | ... S18: =S4*Premissas!$B$3+R7*Premissas!$B$2+S4*Premissas!$B$4
A19: RBT12 proporcionalizado | B19: =SUM($B$18:B18)/1*12 | C19: =SUM($B$18:C18)/2*12 | D19: =SUM($B$18:D18)/3*12 | E19: =SUM($B$18:E18)/4*12 | F19: =SUM($B$18:F18)/5*12 | G19: =SUM($B$18:G18)/6*12 | H19: =SUM($B$18:H18)/7*12 | I19: =SUM($B$18:I18)/8*12 | J19: =SUM($B$18:J18)/9*12 | K19: =SUM($B$18:K18)/10*12 | L19: =SUM($B$18:L18)/11*12 | M19: =SUM(B18:M18) | N19: =SUM(C18:N18) | O19: =SUM(D18:O18) | P19: =SUM(E18:P18) | Q19: =SUM(F18:Q18) | R19: =SUM(G18:R18) | S19: =SUM(H18:S18)
A20: Alíquota efetiva do Simples | B20: =IF(B19=0,Premissas!$C$66,IF(B19<=Premissas!$B$66,(B19*Premissas!$C$66-Premissas!$D$66)/B19,IF(B19<=Premissas!$B$67,(B19*Premissas!$C$67-Premissas!$D$67)/B19,IF(B19<=Premissas!$B$68,(B19*Premissas!$C$68-Premissas!$D$68)/B19,IF(B19<=Premissas!$B$69,(B19*Premissas!$C$69-Premissas!$D$69)/B19,IF(B19<=Premissas!$B$70,(B19*Premissas!$C$70-Premissas!$D$70)/B19,(B19*Premissas!$C$71-Premissas!$D$71)/B19)))))) | C20: =IF(C19=0,Premissas!$C$66,IF(C19<=Premissas!$B$66,(C19*Premissas!$C$66-Premissas!$D$66)/C19,IF(C19<=Premissas!$B$67,(C19*Premissas!$C$67-Premissas!$D$67)/C19,IF(C19<=Premissas!$B$68,(C19*Premissas!$C$68-Premissas!$D$68)/C19,IF(C19<=Premissas!$B$69,(C19*Premissas!$C$69-Premissas!$D$69)/C19,IF(C19<=Premissas!$B$70,(C19*Premissas!$C$70-Premissas!$D$70)/C19,(C19*Premissas!$C$71-Premissas!$D$71)/C19)))))) | D20: =IF(D19=0,Premissas!$C$66,IF(D19<=Premissas!$B$66,(D19*Premissas!$C$66-Premissas!$D$66)/D19,IF(D19<=Premissas!$B$67,(D19*Premissas!$C$67-Premissas!$D$67)/D19,IF(D19<=Premissas!$B$68,(D19*Premissas!$C$68-Premissas!$D$68)/D19,IF(D19<=Premissas!$B$69,(D19*Premissas!$C$69-Premissas!$D$69)/D19,IF(D19<=Premissas!$B$70,(D19*Premissas!$C$70-Premissas!$D$70)/D19,(D19*Premissas!$C$71-Premissas!$D$71)/D19)))))) | E20: =IF(E19=0,Premissas!$C$66,IF(E19<=Premissas!$B$66,(E19*Premissas!$C$66-Premissas!$D$66)/E19,IF(E19<=Premissas!$B$67,(E19*Premissas!$C$67-Premissas!$D$67)/E19,IF(E19<=Premissas!$B$68,(E19*Premissas!$C$68-Premissas!$D$68)/E19,IF(E19<=Premissas!$B$69,(E19*Premissas!$C$69-Premissas!$D$69)/E19,IF(E19<=Premissas!$B$70,(E19*Premissas!$C$70-Premissas!$D$70)/E19,(E19*Premissas!$C$71-Premissas!$D$71)/E19)))))) | F20: =IF(F19=0,Premissas!$C$66,IF(F19<=Premissas!$B$66,(F19*Premissas!$C$66-Premissas!$D$66)/F19,IF(F19<=Premissas!$B$67,(F19*Premissas!$C$67-Premissas!$D$67)/F19,IF(F19<=Premissas!$B$68,(F19*Premissas!$C$68-Premissas!$D$68)/F19,IF(F19<=Premissas!$B$69,(F19*Premissas!$C$69-Premissas!$D$69)/F19,IF(F19<=Premissas!$B$70,(F19*Premissas!$C$70-Premissas!$D$70)/F19,(F19*Premissas!$C$71-Premissas!$D$71)/F19)))))) | G20: =IF(G19=0,Premissas!$C$66,IF(G19<=Premissas!$B$66,(G19*Premissas!$C$66-Premissas!$D$66)/G19,IF(G19<=Premissas!$B$67,(G19*Premissas!$C$67-Premissas!$D$67)/G19,IF(G19<=Premissas!$B$68,(G19*Premissas!$C$68-Premissas!$D$68)/G19,IF(G19<=Premissas!$B$69,(G19*Premissas!$C$69-Premissas!$D$69)/G19,IF(G19<=Premissas!$B$70,(G19*Premissas!$C$70-Premissas!$D$70)/G19,(G19*Premissas!$C$71-Premissas!$D$71)/G19)))))) | H20: =IF(H19=0,Premissas!$C$66,IF(H19<=Premissas!$B$66,(H19*Premissas!$C$66-Premissas!$D$66)/H19,IF(H19<=Premissas!$B$67,(H19*Premissas!$C$67-Premissas!$D$67)/H19,IF(H19<=Premissas!$B$68,(H19*Premissas!$C$68-Premissas!$D$68)/H19,IF(H19<=Premissas!$B$69,(H19*Premissas!$C$69-Premissas!$D$69)/H19,IF(H19<=Premissas!$B$70,(H19*Premissas!$C$70-Premissas!$D$70)/H19,(H19*Premissas!$C$71-Premissas!$D$71)/H19)))))) | I20: =IF(I19=0,Premissas!$C$66,IF(I19<=Premissas!$B$66,(I19*Premissas!$C$66-Premissas!$D$66)/I19,IF(I19<=Premissas!$B$67,(I19*Premissas!$C$67-Premissas!$D$67)/I19,IF(I19<=Premissas!$B$68,(I19*Premissas!$C$68-Premissas!$D$68)/I19,IF(I19<=Premissas!$B$69,(I19*Premissas!$C$69-Premissas!$D$69)/I19,IF(I19<=Premissas!$B$70,(I19*Premissas!$C$70-Premissas!$D$70)/I19,(I19*Premissas!$C$71-Premissas!$D$71)/I19)))))) | ... S20: =IF(S19=0,Premissas!$C$66,IF(S19<=Premissas!$B$66,(S19*Premissas!$C$66-Premissas!$D$66)/S19,IF(S19<=Premissas!$B$67,(S19*Premissas!$C$67-Premissas!$D$67)/S19,IF(S19<=Premissas!$B$68,(S19*Premissas!$C$68-Premissas!$D$68)/S19,IF(S19<=Premissas!$B$69,(S19*Premissas!$C$69-Premissas!$D$69)/S19,IF(S19<=Premissas!$B$70,(S19*Premissas!$C$70-Premissas!$D$70)/S19,(S19*Premissas!$C$71-Premissas!$D$71)/S19))))))
A22: DESPESAS
A23: Impostos (Simples progressivo) | B23: =B18*B20 | C23: =C18*C20 | D23: =D18*D20 | E23: =E18*E20 | F23: =F18*F20 | G23: =G18*G20 | H23: =H18*H20 | I23: =I18*I20 | ... S23: =S18*S20
A24: Material — parcelas 12x | B24: 0 | C24: 0 | D24: =SUM($B$4:D4)*Premissas!$B$6/12 | E24: =SUM($B$4:E4)*Premissas!$B$6/12 | F24: =SUM($B$4:F4)*Premissas!$B$6/12 | G24: =SUM($B$4:G4)*Premissas!$B$6/12 | H24: =SUM($B$4:H4)*Premissas!$B$6/12 | I24: =SUM($B$4:I4)*Premissas!$B$6/12 | J24: =SUM($B$4:J4)*Premissas!$B$6/12 | K24: =SUM($B$4:K4)*Premissas!$B$6/12 | ... O24: =SUM($B$4:O4)*Premissas!$B$6/12 | P24: =SUM(E4:P4)*Premissas!$B$6/12 | Q24: =SUM(F4:Q4)*Premissas!$B$6/12 | R24: =SUM(G4:R4)*Premissas!$B$6/12 | S24: =SUM(H4:S4)*Premissas!$B$6/12
A25: Comissão do vendedor | B25: =IF(B2>=Premissas!$D$14,B4*Premissas!$B$10*(1+Premissas!$B$11),0) | C25: =IF(C2>=Premissas!$D$14,C4*Premissas!$B$10*(1+Premissas!$B$11),0) | D25: =IF(D2>=Premissas!$D$14,D4*Premissas!$B$10*(1+Premissas!$B$11),0) | E25: =IF(E2>=Premissas!$D$14,E4*Premissas!$B$10*(1+Premissas!$B$11),0) | F25: =IF(F2>=Premissas!$D$14,F4*Premissas!$B$10*(1+Premissas!$B$11),0) | G25: =IF(G2>=Premissas!$D$14,G4*Premissas!$B$10*(1+Premissas!$B$11),0) | H25: =IF(H2>=Premissas!$D$14,H4*Premissas!$B$10*(1+Premissas!$B$11),0) | I25: =IF(I2>=Premissas!$D$14,I4*Premissas!$B$10*(1+Premissas!$B$11),0) | ... S25: =IF(S2>=Premissas!$D$14,S4*Premissas!$B$10*(1+Premissas!$B$11),0)
A26: Aquisição de alunos (custo dos canais) | B26: ='Canais de aquisição'!C$10 | C26: ='Canais de aquisição'!D$10 | D26: ='Canais de aquisição'!E$10 | E26: ='Canais de aquisição'!F$10 | F26: ='Canais de aquisição'!G$10 | G26: ='Canais de aquisição'!H$10 | H26: ='Canais de aquisição'!I$10 | I26: ='Canais de aquisição'!J$10 | ... S26: ='Canais de aquisição'!T$10
A27: Folha + encargos mensais (só quem já entrou) | B27: =SUMPRODUCT((Premissas!$D$14:$D$20<=B2)*Premissas!$B$14:$B$20*(1+Premissas!$C$14:$C$20*Premissas!$B$11)) | C27: =SUMPRODUCT((Premissas!$D$14:$D$20<=C2)*Premissas!$B$14:$B$20*(1+Premissas!$C$14:$C$20*Premissas!$B$11)) | D27: =SUMPRODUCT((Premissas!$D$14:$D$20<=D2)*Premissas!$B$14:$B$20*(1+Premissas!$C$14:$C$20*Premissas!$B$11)) | E27: =SUMPRODUCT((Premissas!$D$14:$D$20<=E2)*Premissas!$B$14:$B$20*(1+Premissas!$C$14:$C$20*Premissas!$B$11)) | F27: =SUMPRODUCT((Premissas!$D$14:$D$20<=F2)*Premissas!$B$14:$B$20*(1+Premissas!$C$14:$C$20*Premissas!$B$11)) | G27: =SUMPRODUCT((Premissas!$D$14:$D$20<=G2)*Premissas!$B$14:$B$20*(1+Premissas!$C$14:$C$20*Premissas!$B$11)) | H27: =SUMPRODUCT((Premissas!$D$14:$D$20<=H2)*Premissas!$B$14:$B$20*(1+Premissas!$C$14:$C$20*Premissas!$B$11)) | I27: =SUMPRODUCT((Premissas!$D$14:$D$20<=I2)*Premissas!$B$14:$B$20*(1+Premissas!$C$14:$C$20*Premissas!$B$11)) | ... S27: =SUMPRODUCT((Premissas!$D$14:$D$20<=S2)*Premissas!$B$14:$B$20*(1+Premissas!$C$14:$C$20*Premissas!$B$11))
A28: Vale-transporte / benefícios | B28: =SUMPRODUCT((Premissas!$D$14:$D$20<=B2)*Premissas!$C$14:$C$20*(Premissas!$B$14:$B$20>0))*Premissas!$B$12 | C28: =SUMPRODUCT((Premissas!$D$14:$D$20<=C2)*Premissas!$C$14:$C$20*(Premissas!$B$14:$B$20>0))*Premissas!$B$12 | D28: =SUMPRODUCT((Premissas!$D$14:$D$20<=D2)*Premissas!$C$14:$C$20*(Premissas!$B$14:$B$20>0))*Premissas!$B$12 | E28: =SUMPRODUCT((Premissas!$D$14:$D$20<=E2)*Premissas!$C$14:$C$20*(Premissas!$B$14:$B$20>0))*Premissas!$B$12 | F28: =SUMPRODUCT((Premissas!$D$14:$D$20<=F2)*Premissas!$C$14:$C$20*(Premissas!$B$14:$B$20>0))*Premissas!$B$12 | G28: =SUMPRODUCT((Premissas!$D$14:$D$20<=G2)*Premissas!$C$14:$C$20*(Premissas!$B$14:$B$20>0))*Premissas!$B$12 | H28: =SUMPRODUCT((Premissas!$D$14:$D$20<=H2)*Premissas!$C$14:$C$20*(Premissas!$B$14:$B$20>0))*Premissas!$B$12 | I28: =SUMPRODUCT((Premissas!$D$14:$D$20<=I2)*Premissas!$C$14:$C$20*(Premissas!$B$14:$B$20>0))*Premissas!$B$12 | ... S28: =SUMPRODUCT((Premissas!$D$14:$D$20<=S2)*Premissas!$C$14:$C$20*(Premissas!$B$14:$B$20>0))*Premissas!$B$12
A29: 13º e férias (desembolso) | B29: 0 | C29: 0 | D29: =Premissas!$B$41*SUMPRODUCT((Premissas!$D$14:$D$20<=2)*Premissas!$C$14:$C$20*Premissas!$B$14:$B$20*(2-((Premissas!$D$14:$D$20>0)*Premissas!$D$14:$D$20+(Premissas!$D$14:$D$20<=0)*0)+1)/12)+0 | E29: 0 | F29: 0 | G29: 0 | H29: 0 | I29: 0 | J29: 0 | K29: 0 | L29: 0 | M29: 0 | N29: =0+Premissas!$B$42*SUMPRODUCT((Premissas!$D$14:$D$20=0)*Premissas!$C$14:$C$20*Premissas!$B$14:$B$20)*4/3 | O29: =0+Premissas!$B$42*SUMPRODUCT((Premissas!$D$14:$D$20=1)*Premissas!$C$14:$C$20*Premissas!$B$14:$B$20)*4/3 | P29: =Premissas!$B$41*SUMPRODUCT((Premissas!$D$14:$D$20<=14)*Premissas!$C$14:$C$20*Premissas!$B$14:$B$20*(14-((Premissas!$D$14:$D$20>3)*Premissas!$D$14:$D$20+(Premissas!$D$14:$D$20<=3)*3)+1)/12)+Premissas!$B$42*SUMPRODUCT((Premissas!$D$14:$D$20=2)*Premissas!$C$14:$C$20*Premissas!$B$14:$B$20)*4/3 | Q29: =0+Premissas!$B$42*SUMPRODUCT((Premissas!$D$14:$D$20=3)*Premissas!$C$14:$C$20*Premissas!$B$14:$B$20)*4/3 | R29: =0+Premissas!$B$42*SUMPRODUCT((Premissas!$D$14:$D$20=4)*Premissas!$C$14:$C$20*Premissas!$B$14:$B$20)*4/3 | S29: =0+Premissas!$B$42*SUMPRODUCT((Premissas!$D$14:$D$20=5)*Premissas!$C$14:$C$20*Premissas!$B$14:$B$20)*4/3
A30: Professores (salário + encargos) | B30: 0 | C30: 0 | D30: =D8*Premissas!$B$35 | E30: =E8*Premissas!$B$35 | F30: =F8*Premissas!$B$35 | G30: =G8*Premissas!$B$35 | H30: =H8*Premissas!$B$35 | I30: =I8*Premissas!$B$35 | J30: =J8*Premissas!$B$35 | K30: =K8*Premissas!$B$35 | ... S30: =S8*Premissas!$B$35
A31: Aluguel do espaço | B31: ='Custos mês a mês'!B2 | C31: ='Custos mês a mês'!C2 | D31: ='Custos mês a mês'!D2 | E31: ='Custos mês a mês'!E2 | F31: ='Custos mês a mês'!F2 | G31: ='Custos mês a mês'!G2 | H31: ='Custos mês a mês'!H2 | I31: ='Custos mês a mês'!I2 | ... S31: ='Custos mês a mês'!S2
A32: Água | B32: ='Custos mês a mês'!B3 | C32: ='Custos mês a mês'!C3 | D32: ='Custos mês a mês'!D3 | E32: ='Custos mês a mês'!E3 | F32: ='Custos mês a mês'!F3 | G32: ='Custos mês a mês'!G3 | H32: ='Custos mês a mês'!H3 | I32: ='Custos mês a mês'!I3 | ... S32: ='Custos mês a mês'!S3
A33: Luz | B33: ='Custos mês a mês'!B4 | C33: ='Custos mês a mês'!C4 | D33: ='Custos mês a mês'!D4 | E33: ='Custos mês a mês'!E4 | F33: ='Custos mês a mês'!F4 | G33: ='Custos mês a mês'!G4 | H33: ='Custos mês a mês'!H4 | I33: ='Custos mês a mês'!I4 | ... S33: ='Custos mês a mês'!S4
A34: Telefone | B34: ='Custos mês a mês'!B5 | C34: ='Custos mês a mês'!C5 | D34: ='Custos mês a mês'!D5 | E34: ='Custos mês a mês'!E5 | F34: ='Custos mês a mês'!F5 | G34: ='Custos mês a mês'!G5 | H34: ='Custos mês a mês'!H5 | I34: ='Custos mês a mês'!I5 | ... S34: ='Custos mês a mês'!S5
A35: Internet | B35: ='Custos mês a mês'!B6 | C35: ='Custos mês a mês'!C6 | D35: ='Custos mês a mês'!D6 | E35: ='Custos mês a mês'!E6 | F35: ='Custos mês a mês'!F6 | G35: ='Custos mês a mês'!G6 | H35: ='Custos mês a mês'!H6 | I35: ='Custos mês a mês'!I6 | ... S35: ='Custos mês a mês'!S6
A36: Sistema de gestão DiscoverON | B36: ='Custos mês a mês'!B7 | C36: ='Custos mês a mês'!C7 | D36: ='Custos mês a mês'!D7 | E36: ='Custos mês a mês'!E7 | F36: ='Custos mês a mês'!F7 | G36: ='Custos mês a mês'!G7 | H36: ='Custos mês a mês'!H7 | I36: ='Custos mês a mês'!I7 | ... S36: ='Custos mês a mês'!S7
A37: Itens para aula | B37: ='Custos mês a mês'!B8 | C37: ='Custos mês a mês'!C8 | D37: ='Custos mês a mês'!D8 | E37: ='Custos mês a mês'!E8 | F37: ='Custos mês a mês'!F8 | G37: ='Custos mês a mês'!G8 | H37: ='Custos mês a mês'!H8 | I37: ='Custos mês a mês'!I8 | ... S37: ='Custos mês a mês'!S8
A38: Materiais de limpeza + higiene | B38: ='Custos mês a mês'!B9 | C38: ='Custos mês a mês'!C9 | D38: ='Custos mês a mês'!D9 | E38: ='Custos mês a mês'!E9 | F38: ='Custos mês a mês'!F9 | G38: ='Custos mês a mês'!G9 | H38: ='Custos mês a mês'!H9 | I38: ='Custos mês a mês'!I9 | ... S38: ='Custos mês a mês'!S9
A39: Brindes | B39: ='Custos mês a mês'!B10 | C39: ='Custos mês a mês'!C10 | D39: ='Custos mês a mês'!D10 | E39: ='Custos mês a mês'!E10 | F39: ='Custos mês a mês'!F10 | G39: ='Custos mês a mês'!G10 | H39: ='Custos mês a mês'!H10 | I39: ='Custos mês a mês'!I10 | ... S39: ='Custos mês a mês'!S10
A40: Marketing | B40: ='Custos mês a mês'!B11 | C40: ='Custos mês a mês'!C11 | D40: ='Custos mês a mês'!D11 | E40: ='Custos mês a mês'!E11 | F40: ='Custos mês a mês'!F11 | G40: ='Custos mês a mês'!G11 | H40: ='Custos mês a mês'!H11 | I40: ='Custos mês a mês'!I11 | ... S40: ='Custos mês a mês'!S11
A41: Aluguel dos computadores | B41: ='Custos mês a mês'!B12 | C41: ='Custos mês a mês'!C12 | D41: ='Custos mês a mês'!D12 | E41: ='Custos mês a mês'!E12 | F41: ='Custos mês a mês'!F12 | G41: ='Custos mês a mês'!G12 | H41: ='Custos mês a mês'!H12 | I41: ='Custos mês a mês'!I12 | ... S41: ='Custos mês a mês'!S12
A42: Seguro empresarial | B42: ='Custos mês a mês'!B13 | C42: ='Custos mês a mês'!C13 | D42: ='Custos mês a mês'!D13 | E42: ='Custos mês a mês'!E13 | F42: ='Custos mês a mês'!F13 | G42: ='Custos mês a mês'!G13 | H42: ='Custos mês a mês'!H13 | I42: ='Custos mês a mês'!I13 | ... S42: ='Custos mês a mês'!S13
... A45: Pró-labore | B45: ='Custos mês a mês'!B16 | C45: ='Custos mês a mês'!C16 | D45: ='Custos mês a mês'!D16 | E45: ='Custos mês a mês'!E16 | F45: ='Custos mês a mês'!F16 | G45: ='Custos mês a mês'!G16 | H45: ='Custos mês a mês'!H16 | I45: ='Custos mês a mês'!I16 | ... S45: ='Custos mês a mês'!S16
A46: Total de despesas | B46: =SUM(B23:B45) | C46: =SUM(C23:C45) | D46: =SUM(D23:D45) | E46: =SUM(E23:E45) | F46: =SUM(F23:F45) | G46: =SUM(G23:G45) | H46: =SUM(H23:H45) | I46: =SUM(I23:I45) | ... S46: =SUM(S23:S45)
A48: Resultado do mês | B48: =B15-B46 | C48: =C15-C46 | D48: =D15-D46 | E48: =E15-E46 | F48: =F15-F46 | G48: =G15-G46 | H48: =H15-H46 | I48: =I15-I46 | ... S48: =S15-S46
A49: Caixa acumulado (operacional) | B49: =B48 | C49: =B49+C48 | D49: =C49+D48 | E49: =D49+E48 | F49: =E49+F48 | G49: =F49+G48 | H49: =G49+H48 | I49: =H49+I48 | J49: =I49+J48 | ... S49: =R49+S48
A50: Caixa acumulado incl. investimento | B50: =B49-INVEST_TOTAL | C50: =C49-INVEST_TOTAL | D50: =D49-INVEST_TOTAL | E50: =E49-INVEST_TOTAL | F50: =F49-INVEST_TOTAL | G50: =G49-INVEST_TOTAL | H50: =H49-INVEST_TOTAL | I50: =I49-INVEST_TOTAL | ... S50: =S49-INVEST_TOTAL
A51: MARCOS | D51: =IF(AND(D48>0,COUNTIF($D48:D48,">0")=1),IF(AND(D50>=0,COUNTIF($D50:D50,">=0")=1),"BE + PAYBACK","BREAK-EVEN"),IF(AND(D50>=0,COUNTIF($D50:D50,">=0")=1),"PAYBACK","")) | E51: =IF(AND(E48>0,COUNTIF($D48:E48,">0")=1),IF(AND(E50>=0,COUNTIF($D50:E50,">=0")=1),"BE + PAYBACK","BREAK-EVEN"),IF(AND(E50>=0,COUNTIF($D50:E50,">=0")=1),"PAYBACK","")) | F51: =IF(AND(F48>0,COUNTIF($D48:F48,">0")=1),IF(AND(F50>=0,COUNTIF($D50:F50,">=0")=1),"BE + PAYBACK","BREAK-EVEN"),IF(AND(F50>=0,COUNTIF($D50:F50,">=0")=1),"PAYBACK","")) | G51: =IF(AND(G48>0,COUNTIF($D48:G48,">0")=1),IF(AND(G50>=0,COUNTIF($D50:G50,">=0")=1),"BE + PAYBACK","BREAK-EVEN"),IF(AND(G50>=0,COUNTIF($D50:G50,">=0")=1),"PAYBACK","")) | H51: =IF(AND(H48>0,COUNTIF($D48:H48,">0")=1),IF(AND(H50>=0,COUNTIF($D50:H50,">=0")=1),"BE + PAYBACK","BREAK-EVEN"),IF(AND(H50>=0,COUNTIF($D50:H50,">=0")=1),"PAYBACK","")) | I51: =IF(AND(I48>0,COUNTIF($D48:I48,">0")=1),IF(AND(I50>=0,COUNTIF($D50:I50,">=0")=1),"BE + PAYBACK","BREAK-EVEN"),IF(AND(I50>=0,COUNTIF($D50:I50,">=0")=1),"PAYBACK","")) | J51: =IF(AND(J48>0,COUNTIF($D48:J48,">0")=1),IF(AND(J50>=0,COUNTIF($D50:J50,">=0")=1),"BE + PAYBACK","BREAK-EVEN"),IF(AND(J50>=0,COUNTIF($D50:J50,">=0")=1),"PAYBACK","")) | K51: =IF(AND(K48>0,COUNTIF($D48:K48,">0")=1),IF(AND(K50>=0,COUNTIF($D50:K50,">=0")=1),"BE + PAYBACK","BREAK-EVEN"),IF(AND(K50>=0,COUNTIF($D50:K50,">=0")=1),"PAYBACK","")) | ... S51: =IF(AND(S48>0,COUNTIF($D48:S48,">0")=1),IF(AND(S50>=0,COUNTIF($D50:S50,">=0")=1),"BE + PAYBACK","BREAK-EVEN"),IF(AND(S50>=0,COUNTIF($D50:S50,">=0")=1),"PAYBACK",""))

Sheet Simulador
A1: Simulador | B1: Out (obras) | C1: Nov (obras) | D1: Dez (M1) | E1: Jan (M2) | F1: Fev (M3) | G1: Mar (M4) | H1: Abr (M5) | I1: Mai (M6) | J1: Jun (M7) | K1: Jul (M8) | L1: Ago (M9) | M1: Set (M10) | N1: Out (M11) | O1: Nov (M12) | P1: Dez (M13) | Q1: Jan (M14) | R1: Fev (M15) | S1: Mar (M16)
A2: Período (0 = out) | B2: 0 | C2: 1 | D2: 2 | E2: 3 | F2: 4 | G2: 5 | H2: 6 | I2: 7 | J2: 8 | K2: 9 | L2: 10 | M2: 11 | N2: 12 | O2: 13 | P2: 14 | Q2: 15 | R2: 16 | S2: 17
A3: Matrículas — entrada manual ✏️ editável | B3: 4 | C3: 35 | D3: 13 | E3: 30 | F3: 30 | G3: 20 | H3: 20 | I3: 20 | J3: 20 | K3: 30 | L3: 30 | M3: 20 | N3: 20 | O3: 30 | P3: 30 | Q3: 20 | R3: 30 | S3: 20 | U3: Break-even (alunos):
A4: Matrículas no período (vale para o cálculo) | B4: =IF(Premissas!$B$59=3,'Canais de aquisição'!C$9,IF(Premissas!$B$59=2,ROUND('Custos mês a mês'!B$11/MAX(Premissas!$B$60,1),0),B3)) | C4: =IF(Premissas!$B$59=3,'Canais de aquisição'!D$9,IF(Premissas!$B$59=2,ROUND('Custos mês a mês'!C$11/MAX(Premissas!$B$60,1),0),C3)) | D4: =IF(Premissas!$B$59=3,'Canais de aquisição'!E$9,IF(Premissas!$B$59=2,ROUND('Custos mês a mês'!D$11/MAX(Premissas!$B$60,1),0),D3)) | E4: =IF(Premissas!$B$59=3,'Canais de aquisição'!F$9,IF(Premissas!$B$59=2,ROUND('Custos mês a mês'!E$11/MAX(Premissas!$B$60,1),0),E3)) | F4: =IF(Premissas!$B$59=3,'Canais de aquisição'!G$9,IF(Premissas!$B$59=2,ROUND('Custos mês a mês'!F$11/MAX(Premissas!$B$60,1),0),F3)) | G4: =IF(Premissas!$B$59=3,'Canais de aquisição'!H$9,IF(Premissas!$B$59=2,ROUND('Custos mês a mês'!G$11/MAX(Premissas!$B$60,1),0),G3)) | H4: =IF(Premissas!$B$59=3,'Canais de aquisição'!I$9,IF(Premissas!$B$59=2,ROUND('Custos mês a mês'!H$11/MAX(Premissas!$B$60,1),0),H3)) | I4: =IF(Premissas!$B$59=3,'Canais de aquisição'!J$9,IF(Premissas!$B$59=2,ROUND('Custos mês a mês'!I$11/MAX(Premissas!$B$60,1),0),I3)) | ... S4: =IF(Premissas!$B$59=3,'Canais de aquisição'!T$9,IF(Premissas!$B$59=2,ROUND('Custos mês a mês'!S$11/MAX(Premissas!$B$60,1),0),S3)) | U4: =Premissas!$B$90
A5: CAC realizado (marketing + canais ÷ matrículas) | B5: =IF(B4=0,0,('Custos mês a mês'!B$11+'Canais de aquisição'!C$10)/B4) | C5: =IF(C4=0,0,('Custos mês a mês'!C$11+'Canais de aquisição'!D$10)/C4) | D5: =IF(D4=0,0,('Custos mês a mês'!D$11+'Canais de aquisição'!E$10)/D4) | E5: =IF(E4=0,0,('Custos mês a mês'!E$11+'Canais de aquisição'!F$10)/E4) | F5: =IF(F4=0,0,('Custos mês a mês'!F$11+'Canais de aquisição'!G$10)/F4) | G5: =IF(G4=0,0,('Custos mês a mês'!G$11+'Canais de aquisição'!H$10)/G4) | H5: =IF(H4=0,0,('Custos mês a mês'!H$11+'Canais de aquisição'!I$10)/H4) | I5: =IF(I4=0,0,('Custos mês a mês'!I$11+'Canais de aquisição'!J$10)/I4) | ... S5: =IF(S4=0,0,('Custos mês a mês'!S$11+'Canais de aquisição'!T$10)/S4)
A6: Desistências no mês | B6: 0 | C6: =B7*$B$53*Premissas!$B$55 | D6: =C7*$B$53*Premissas!$B$56 | E6: =D7*$B$53*Premissas!$B$45 | F6: =E7*$B$53*Premissas!$B$46 | G6: =F7*$B$53*Premissas!$B$47 | H6: =G7*$B$53*Premissas!$B$48 | I6: =H7*$B$53*Premissas!$B$49 | J6: =I7*$B$53*Premissas!$B$50 | K6: =J7*$B$53*Premissas!$B$51 | L6: =K7*$B$53*Premissas!$B$52 | M6: =L7*$B$53*Premissas!$B$53 | N6: =M7*$B$53*Premissas!$B$54 | O6: =N7*$B$53*Premissas!$B$55 | P6: =O7*$B$53*Premissas!$B$56 | Q6: =P7*$B$53*Premissas!$B$45 | R6: =Q7*$B$53*Premissas!$B$46 | S6: =R7*$B$53*Premissas!$B$47 | U6: 🟢 VERDE FORTE = mês do BREAK-EVEN
A7: Total de alunos | B7: =B4 | C7: =B7-C6+C4 | D7: =C7-D6+D4 | E7: =D7-E6+E4 | F7: =E7-F6+F4 | G7: =F7-G6+G4 | H7: =G7-H6+H4 | I7: =H7-I6+I4 | J7: =I7-J6+J4 | ... S7: =R7-S6+S4 | U7: 🟦 AZUL = mês do PAYBACK
A8: Professores necessários | B8: 0 | C8: 0 | D8: =CEILING(CEILING(D7*Premissas!$B$37/Premissas!$B$27,1)*Premissas!$B$28/Premissas!$B$34,1)+CEILING(CEILING(D7*Premissas!$B$38/Premissas!$B$30,1)*Premissas!$B$31/Premissas!$B$34,1) | E8: =CEILING(CEILING(E7*Premissas!$B$37/Premissas!$B$27,1)*Premissas!$B$28/Premissas!$B$34,1)+CEILING(CEILING(E7*Premissas!$B$38/Premissas!$B$30,1)*Premissas!$B$31/Premissas!$B$34,1) | F8: =CEILING(CEILING(F7*Premissas!$B$37/Premissas!$B$27,1)*Premissas!$B$28/Premissas!$B$34,1)+CEILING(CEILING(F7*Premissas!$B$38/Premissas!$B$30,1)*Premissas!$B$31/Premissas!$B$34,1) | G8: =CEILING(CEILING(G7*Premissas!$B$37/Premissas!$B$27,1)*Premissas!$B$28/Premissas!$B$34,1)+CEILING(CEILING(G7*Premissas!$B$38/Premissas!$B$30,1)*Premissas!$B$31/Premissas!$B$34,1) | H8: =CEILING(CEILING(H7*Premissas!$B$37/Premissas!$B$27,1)*Premissas!$B$28/Premissas!$B$34,1)+CEILING(CEILING(H7*Premissas!$B$38/Premissas!$B$30,1)*Premissas!$B$31/Premissas!$B$34,1) | I8: =CEILING(CEILING(I7*Premissas!$B$37/Premissas!$B$27,1)*Premissas!$B$28/Premissas!$B$34,1)+CEILING(CEILING(I7*Premissas!$B$38/Premissas!$B$30,1)*Premissas!$B$31/Premissas!$B$34,1) | J8: =CEILING(CEILING(J7*Premissas!$B$37/Premissas!$B$27,1)*Premissas!$B$28/Premissas!$B$34,1)+CEILING(CEILING(J7*Premissas!$B$38/Premissas!$B$30,1)*Premissas!$B$31/Premissas!$B$34,1) | K8: =CEILING(CEILING(K7*Premissas!$B$37/Premissas!$B$27,1)*Premissas!$B$28/Premissas!$B$34,1)+CEILING(CEILING(K7*Premissas!$B$38/Premissas!$B$30,1)*Premissas!$B$31/Premissas!$B$34,1) | ... S8: =CEILING(CEILING(S7*Premissas!$B$37/Premissas!$B$27,1)*Premissas!$B$28/Premissas!$B$34,1)+CEILING(CEILING(S7*Premissas!$B$38/Premissas!$B$30,1)*Premissas!$B$31/Premissas!$B$34,1) | U8: 🟩 verde claro = meses já positivos
A9: Ocupação das salas (100% = grade cheia) | B9: 0 | C9: 0 | D9: =MAX(CEILING(D7*Premissas!$B$37/Premissas!$B$27,1)*Premissas!$B$28/(Premissas!$B$26*Premissas!$B$32*Premissas!$B$33*Premissas!$B$25),CEILING(D7*Premissas!$B$38/Premissas!$B$30,1)*Premissas!$B$31/(Premissas!$B$29*Premissas!$B$32*Premissas!$B$33*Premissas!$B$25)) | E9: =MAX(CEILING(E7*Premissas!$B$37/Premissas!$B$27,1)*Premissas!$B$28/(Premissas!$B$26*Premissas!$B$32*Premissas!$B$33*Premissas!$B$25),CEILING(E7*Premissas!$B$38/Premissas!$B$30,1)*Premissas!$B$31/(Premissas!$B$29*Premissas!$B$32*Premissas!$B$33*Premissas!$B$25)) | F9: =MAX(CEILING(F7*Premissas!$B$37/Premissas!$B$27,1)*Premissas!$B$28/(Premissas!$B$26*Premissas!$B$32*Premissas!$B$33*Premissas!$B$25),CEILING(F7*Premissas!$B$38/Premissas!$B$30,1)*Premissas!$B$31/(Premissas!$B$29*Premissas!$B$32*Premissas!$B$33*Premissas!$B$25)) | G9: =MAX(CEILING(G7*Premissas!$B$37/Premissas!$B$27,1)*Premissas!$B$28/(Premissas!$B$26*Premissas!$B$32*Premissas!$B$33*Premissas!$B$25),CEILING(G7*Premissas!$B$38/Premissas!$B$30,1)*Premissas!$B$31/(Premissas!$B$29*Premissas!$B$32*Premissas!$B$33*Premissas!$B$25)) | H9: =MAX(CEILING(H7*Premissas!$B$37/Premissas!$B$27,1)*Premissas!$B$28/(Premissas!$B$26*Premissas!$B$32*Premissas!$B$33*Premissas!$B$25),CEILING(H7*Premissas!$B$38/Premissas!$B$30,1)*Premissas!$B$31/(Premissas!$B$29*Premissas!$B$32*Premissas!$B$33*Premissas!$B$25)) | I9: =MAX(CEILING(I7*Premissas!$B$37/Premissas!$B$27,1)*Premissas!$B$28/(Premissas!$B$26*Premissas!$B$32*Premissas!$B$33*Premissas!$B$25),CEILING(I7*Premissas!$B$38/Premissas!$B$30,1)*Premissas!$B$31/(Premissas!$B$29*Premissas!$B$32*Premissas!$B$33*Premissas!$B$25)) | J9: =MAX(CEILING(J7*Premissas!$B$37/Premissas!$B$27,1)*Premissas!$B$28/(Premissas!$B$26*Premissas!$B$32*Premissas!$B$33*Premissas!$B$25),CEILING(J7*Premissas!$B$38/Premissas!$B$30,1)*Premissas!$B$31/(Premissas!$B$29*Premissas!$B$32*Premissas!$B$33*Premissas!$B$25)) | K9: =MAX(CEILING(K7*Premissas!$B$37/Premissas!$B$27,1)*Premissas!$B$28/(Premissas!$B$26*Premissas!$B$32*Premissas!$B$33*Premissas!$B$25),CEILING(K7*Premissas!$B$38/Premissas!$B$30,1)*Premissas!$B$31/(Premissas!$B$29*Premissas!$B$32*Premissas!$B$33*Premissas!$B$25)) | ... S9: =MAX(CEILING(S7*Premissas!$B$37/Premissas!$B$27,1)*Premissas!$B$28/(Premissas!$B$26*Premissas!$B$32*Premissas!$B$33*Premissas!$B$25),CEILING(S7*Premissas!$B$38/Premissas!$B$30,1)*Premissas!$B$31/(Premissas!$B$29*Premissas!$B$32*Premissas!$B$33*Premissas!$B$25))
A11: RECEITA RECEBIDA (caixa)
A12: Matrícula | B12: =B4*Premissas!$B$3 | C12: =C4*Premissas!$B$3 | D12: =D4*Premissas!$B$3 | E12: =E4*Premissas!$B$3 | F12: =F4*Premissas!$B$3 | G12: =G4*Premissas!$B$3 | H12: =H4*Premissas!$B$3 | I12: =I4*Premissas!$B$3 | ... S12: =S4*Premissas!$B$3
A13: Mensalidade recebida (líq. de inadimplência) | B13: 0 | C13: 0 | D13: =C7*$B$55*(1-$B$54) | E13: =D7*$B$55*(1-$B$54) | F13: =E7*$B$55*(1-$B$54) | G13: =F7*$B$55*(1-$B$54) | H13: =G7*$B$55*(1-$B$54) | I13: =H7*$B$55*(1-$B$54) | J13: =I7*$B$55*(1-$B$54) | K13: =J7*$B$55*(1-$B$54) | ... S13: =R7*$B$55*(1-$B$54)
A14: Material antecipado no cartão | B14: =B4*Premissas!$B$5 | C14: =C4*Premissas!$B$5 | D14: =D4*Premissas!$B$5 | E14: =E4*Premissas!$B$5 | F14: =F4*Premissas!$B$5 | G14: =G4*Premissas!$B$5 | H14: =H4*Premissas!$B$5 | I14: =I4*Premissas!$B$5 | ... S14: =S4*Premissas!$B$5
A15: Receita recebida | B15: =SUM(B12:B14) | C15: =SUM(C12:C14) | D15: =SUM(D12:D14) | E15: =SUM(E12:E14) | F15: =SUM(F12:F14) | G15: =SUM(G12:G14) | H15: =SUM(H12:H14) | I15: =SUM(I12:I14) | ... S15: =SUM(S12:S14)
A17: BASE DO SIMPLES NACIONAL
A18: Faturamento do mês (nota emitida) | B18: =B4*Premissas!$B$3+B4*Premissas!$B$4 | C18: =C4*Premissas!$B$3+C4*Premissas!$B$4 | D18: =D4*Premissas!$B$3+C7*$B$55+D4*Premissas!$B$4 | E18: =E4*Premissas!$B$3+D7*$B$55+E4*Premissas!$B$4 | F18: =F4*Premissas!$B$3+E7*$B$55+F4*Premissas!$B$4 | G18: =G4*Premissas!$B$3+F7*$B$55+G4*Premissas!$B$4 | H18: =H4*Premissas!$B$3+G7*$B$55+H4*Premissas!$B$4 | I18: =I4*Premissas!$B$3+H7*$B$55+I4*Premissas!$B$4 | J18: =J4*Premissas!$B$3+I7*$B$55+J4*Premissas!$B$4 | K18: =K4*Premissas!$B$3+J7*$B$55+K4*Premissas!$B$4 | ... S18: =S4*Premissas!$B$3+R7*$B$55+S4*Premissas!$B$4
A19: RBT12 proporcionalizado | B19: =SUM($B$18:B18)/1*12 | C19: =SUM($B$18:C18)/2*12 | D19: =SUM($B$18:D18)/3*12 | E19: =SUM($B$18:E18)/4*12 | F19: =SUM($B$18:F18)/5*12 | G19: =SUM($B$18:G18)/6*12 | H19: =SUM($B$18:H18)/7*12 | I19: =SUM($B$18:I18)/8*12 | J19: =SUM($B$18:J18)/9*12 | K19: =SUM($B$18:K18)/10*12 | L19: =SUM($B$18:L18)/11*12 | M19: =SUM(B18:M18) | N19: =SUM(C18:N18) | O19: =SUM(D18:O18) | P19: =SUM(E18:P18) | Q19: =SUM(F18:Q18) | R19: =SUM(G18:R18) | S19: =SUM(H18:S18)
A20: Alíquota efetiva do Simples | B20: =IF(B19=0,Premissas!$C$66,IF(B19<=Premissas!$B$66,(B19*Premissas!$C$66-Premissas!$D$66)/B19,IF(B19<=Premissas!$B$67,(B19*Premissas!$C$67-Premissas!$D$67)/B19,IF(B19<=Premissas!$B$68,(B19*Premissas!$C$68-Premissas!$D$68)/B19,IF(B19<=Premissas!$B$69,(B19*Premissas!$C$69-Premissas!$D$69)/B19,IF(B19<=Premissas!$B$70,(B19*Premissas!$C$70-Premissas!$D$70)/B19,(B19*Premissas!$C$71-Premissas!$D$71)/B19)))))) | C20: =IF(C19=0,Premissas!$C$66,IF(C19<=Premissas!$B$66,(C19*Premissas!$C$66-Premissas!$D$66)/C19,IF(C19<=Premissas!$B$67,(C19*Premissas!$C$67-Premissas!$D$67)/C19,IF(C19<=Premissas!$B$68,(C19*Premissas!$C$68-Premissas!$D$68)/C19,IF(C19<=Premissas!$B$69,(C19*Premissas!$C$69-Premissas!$D$69)/C19,IF(C19<=Premissas!$B$70,(C19*Premissas!$C$70-Premissas!$D$70)/C19,(C19*Premissas!$C$71-Premissas!$D$71)/C19)))))) | D20: =IF(D19=0,Premissas!$C$66,IF(D19<=Premissas!$B$66,(D19*Premissas!$C$66-Premissas!$D$66)/D19,IF(D19<=Premissas!$B$67,(D19*Premissas!$C$67-Premissas!$D$67)/D19,IF(D19<=Premissas!$B$68,(D19*Premissas!$C$68-Premissas!$D$68)/D19,IF(D19<=Premissas!$B$69,(D19*Premissas!$C$69-Premissas!$D$69)/D19,IF(D19<=Premissas!$B$70,(D19*Premissas!$C$70-Premissas!$D$70)/D19,(D19*Premissas!$C$71-Premissas!$D$71)/D19)))))) | E20: =IF(E19=0,Premissas!$C$66,IF(E19<=Premissas!$B$66,(E19*Premissas!$C$66-Premissas!$D$66)/E19,IF(E19<=Premissas!$B$67,(E19*Premissas!$C$67-Premissas!$D$67)/E19,IF(E19<=Premissas!$B$68,(E19*Premissas!$C$68-Premissas!$D$68)/E19,IF(E19<=Premissas!$B$69,(E19*Premissas!$C$69-Premissas!$D$69)/E19,IF(E19<=Premissas!$B$70,(E19*Premissas!$C$70-Premissas!$D$70)/E19,(E19*Premissas!$C$71-Premissas!$D$71)/E19)))))) | F20: =IF(F19=0,Premissas!$C$66,IF(F19<=Premissas!$B$66,(F19*Premissas!$C$66-Premissas!$D$66)/F19,IF(F19<=Premissas!$B$67,(F19*Premissas!$C$67-Premissas!$D$67)/F19,IF(F19<=Premissas!$B$68,(F19*Premissas!$C$68-Premissas!$D$68)/F19,IF(F19<=Premissas!$B$69,(F19*Premissas!$C$69-Premissas!$D$69)/F19,IF(F19<=Premissas!$B$70,(F19*Premissas!$C$70-Premissas!$D$70)/F19,(F19*Premissas!$C$71-Premissas!$D$71)/F19)))))) | G20: =IF(G19=0,Premissas!$C$66,IF(G19<=Premissas!$B$66,(G19*Premissas!$C$66-Premissas!$D$66)/G19,IF(G19<=Premissas!$B$67,(G19*Premissas!$C$67-Premissas!$D$67)/G19,IF(G19<=Premissas!$B$68,(G19*Premissas!$C$68-Premissas!$D$68)/G19,IF(G19<=Premissas!$B$69,(G19*Premissas!$C$69-Premissas!$D$69)/G19,IF(G19<=Premissas!$B$70,(G19*Premissas!$C$70-Premissas!$D$70)/G19,(G19*Premissas!$C$71-Premissas!$D$71)/G19)))))) | H20: =IF(H19=0,Premissas!$C$66,IF(H19<=Premissas!$B$66,(H19*Premissas!$C$66-Premissas!$D$66)/H19,IF(H19<=Premissas!$B$67,(H19*Premissas!$C$67-Premissas!$D$67)/H19,IF(H19<=Premissas!$B$68,(H19*Premissas!$C$68-Premissas!$D$68)/H19,IF(H19<=Premissas!$B$69,(H19*Premissas!$C$69-Premissas!$D$69)/H19,IF(H19<=Premissas!$B$70,(H19*Premissas!$C$70-Premissas!$D$70)/H19,(H19*Premissas!$C$71-Premissas!$D$71)/H19)))))) | I20: =IF(I19=0,Premissas!$C$66,IF(I19<=Premissas!$B$66,(I19*Premissas!$C$66-Premissas!$D$66)/I19,IF(I19<=Premissas!$B$67,(I19*Premissas!$C$67-Premissas!$D$67)/I19,IF(I19<=Premissas!$B$68,(I19*Premissas!$C$68-Premissas!$D$68)/I19,IF(I19<=Premissas!$B$69,(I19*Premissas!$C$69-Premissas!$D$69)/I19,IF(I19<=Premissas!$B$70,(I19*Premissas!$C$70-Premissas!$D$70)/I19,(I19*Premissas!$C$71-Premissas!$D$71)/I19)))))) | ... S20: =IF(S19=0,Premissas!$C$66,IF(S19<=Premissas!$B$66,(S19*Premissas!$C$66-Premissas!$D$66)/S19,IF(S19<=Premissas!$B$67,(S19*Premissas!$C$67-Premissas!$D$67)/S19,IF(S19<=Premissas!$B$68,(S19*Premissas!$C$68-Premissas!$D$68)/S19,IF(S19<=Premissas!$B$69,(S19*Premissas!$C$69-Premissas!$D$69)/S19,IF(S19<=Premissas!$B$70,(S19*Premissas!$C$70-Premissas!$D$70)/S19,(S19*Premissas!$C$71-Premissas!$D$71)/S19))))))
A22: DESPESAS
A23: Impostos (Simples progressivo) | B23: =B18*B20 | C23: =C18*C20 | D23: =D18*D20 | E23: =E18*E20 | F23: =F18*F20 | G23: =G18*G20 | H23: =H18*H20 | I23: =I18*I20 | ... S23: =S18*S20
A24: Material — parcelas 12x | B24: 0 | C24: 0 | D24: =SUM($B$4:D4)*Premissas!$B$6/12 | E24: =SUM($B$4:E4)*Premissas!$B$6/12 | F24: =SUM($B$4:F4)*Premissas!$B$6/12 | G24: =SUM($B$4:G4)*Premissas!$B$6/12 | H24: =SUM($B$4:H4)*Premissas!$B$6/12 | I24: =SUM($B$4:I4)*Premissas!$B$6/12 | J24: =SUM($B$4:J4)*Premissas!$B$6/12 | K24: =SUM($B$4:K4)*Premissas!$B$6/12 | ... O24: =SUM($B$4:O4)*Premissas!$B$6/12 | P24: =SUM(E4:P4)*Premissas!$B$6/12 | Q24: =SUM(F4:Q4)*Premissas!$B$6/12 | R24: =SUM(G4:R4)*Premissas!$B$6/12 | S24: =SUM(H4:S4)*Premissas!$B$6/12
A25: Comissão do vendedor | B25: =IF(B2>=Premissas!$D$14,B4*Premissas!$B$10*(1+Premissas!$B$11),0) | C25: =IF(C2>=Premissas!$D$14,C4*Premissas!$B$10*(1+Premissas!$B$11),0) | D25: =IF(D2>=Premissas!$D$14,D4*Premissas!$B$10*(1+Premissas!$B$11),0) | E25: =IF(E2>=Premissas!$D$14,E4*Premissas!$B$10*(1+Premissas!$B$11),0) | F25: =IF(F2>=Premissas!$D$14,F4*Premissas!$B$10*(1+Premissas!$B$11),0) | G25: =IF(G2>=Premissas!$D$14,G4*Premissas!$B$10*(1+Premissas!$B$11),0) | H25: =IF(H2>=Premissas!$D$14,H4*Premissas!$B$10*(1+Premissas!$B$11),0) | I25: =IF(I2>=Premissas!$D$14,I4*Premissas!$B$10*(1+Premissas!$B$11),0) | ... S25: =IF(S2>=Premissas!$D$14,S4*Premissas!$B$10*(1+Premissas!$B$11),0)
A26: Aquisição de alunos (custo dos canais) | B26: ='Canais de aquisição'!C$10 | C26: ='Canais de aquisição'!D$10 | D26: ='Canais de aquisição'!E$10 | E26: ='Canais de aquisição'!F$10 | F26: ='Canais de aquisição'!G$10 | G26: ='Canais de aquisição'!H$10 | H26: ='Canais de aquisição'!I$10 | I26: ='Canais de aquisição'!J$10 | ... S26: ='Canais de aquisição'!T$10
A27: Folha + encargos mensais (só quem já entrou) | B27: =SUMPRODUCT((Premissas!$D$14:$D$20<=B2)*Premissas!$B$14:$B$20*(1+Premissas!$C$14:$C$20*Premissas!$B$11)) | C27: =SUMPRODUCT((Premissas!$D$14:$D$20<=C2)*Premissas!$B$14:$B$20*(1+Premissas!$C$14:$C$20*Premissas!$B$11)) | D27: =SUMPRODUCT((Premissas!$D$14:$D$20<=D2)*Premissas!$B$14:$B$20*(1+Premissas!$C$14:$C$20*Premissas!$B$11)) | E27: =SUMPRODUCT((Premissas!$D$14:$D$20<=E2)*Premissas!$B$14:$B$20*(1+Premissas!$C$14:$C$20*Premissas!$B$11)) | F27: =SUMPRODUCT((Premissas!$D$14:$D$20<=F2)*Premissas!$B$14:$B$20*(1+Premissas!$C$14:$C$20*Premissas!$B$11)) | G27: =SUMPRODUCT((Premissas!$D$14:$D$20<=G2)*Premissas!$B$14:$B$20*(1+Premissas!$C$14:$C$20*Premissas!$B$11)) | H27: =SUMPRODUCT((Premissas!$D$14:$D$20<=H2)*Premissas!$B$14:$B$20*(1+Premissas!$C$14:$C$20*Premissas!$B$11)) | I27: =SUMPRODUCT((Premissas!$D$14:$D$20<=I2)*Premissas!$B$14:$B$20*(1+Premissas!$C$14:$C$20*Premissas!$B$11)) | ... S27: =SUMPRODUCT((Premissas!$D$14:$D$20<=S2)*Premissas!$B$14:$B$20*(1+Premissas!$C$14:$C$20*Premissas!$B$11))
A28: Vale-transporte / benefícios | B28: =SUMPRODUCT((Premissas!$D$14:$D$20<=B2)*Premissas!$C$14:$C$20*(Premissas!$B$14:$B$20>0))*Premissas!$B$12 | C28: =SUMPRODUCT((Premissas!$D$14:$D$20<=C2)*Premissas!$C$14:$C$20*(Premissas!$B$14:$B$20>0))*Premissas!$B$12 | D28: =SUMPRODUCT((Premissas!$D$14:$D$20<=D2)*Premissas!$C$14:$C$20*(Premissas!$B$14:$B$20>0))*Premissas!$B$12 | E28: =SUMPRODUCT((Premissas!$D$14:$D$20<=E2)*Premissas!$C$14:$C$20*(Premissas!$B$14:$B$20>0))*Premissas!$B$12 | F28: =SUMPRODUCT((Premissas!$D$14:$D$20<=F2)*Premissas!$C$14:$C$20*(Premissas!$B$14:$B$20>0))*Premissas!$B$12 | G28: =SUMPRODUCT((Premissas!$D$14:$D$20<=G2)*Premissas!$C$14:$C$20*(Premissas!$B$14:$B$20>0))*Premissas!$B$12 | H28: =SUMPRODUCT((Premissas!$D$14:$D$20<=H2)*Premissas!$C$14:$C$20*(Premissas!$B$14:$B$20>0))*Premissas!$B$12 | I28: =SUMPRODUCT((Premissas!$D$14:$D$20<=I2)*Premissas!$C$14:$C$20*(Premissas!$B$14:$B$20>0))*Premissas!$B$12 | ... S28: =SUMPRODUCT((Premissas!$D$14:$D$20<=S2)*Premissas!$C$14:$C$20*(Premissas!$B$14:$B$20>0))*Premissas!$B$12
A29: 13º e férias (desembolso) | B29: 0 | C29: 0 | D29: =Premissas!$B$41*SUMPRODUCT((Premissas!$D$14:$D$20<=2)*Premissas!$C$14:$C$20*Premissas!$B$14:$B$20*(2-((Premissas!$D$14:$D$20>0)*Premissas!$D$14:$D$20+(Premissas!$D$14:$D$20<=0)*0)+1)/12)+0 | E29: 0 | F29: 0 | G29: 0 | H29: 0 | I29: 0 | J29: 0 | K29: 0 | L29: 0 | M29: 0 | N29: =0+Premissas!$B$42*SUMPRODUCT((Premissas!$D$14:$D$20=0)*Premissas!$C$14:$C$20*Premissas!$B$14:$B$20)*4/3 | O29: =0+Premissas!$B$42*SUMPRODUCT((Premissas!$D$14:$D$20=1)*Premissas!$C$14:$C$20*Premissas!$B$14:$B$20)*4/3 | P29: =Premissas!$B$41*SUMPRODUCT((Premissas!$D$14:$D$20<=14)*Premissas!$C$14:$C$20*Premissas!$B$14:$B$20*(14-((Premissas!$D$14:$D$20>3)*Premissas!$D$14:$D$20+(Premissas!$D$14:$D$20<=3)*3)+1)/12)+Premissas!$B$42*SUMPRODUCT((Premissas!$D$14:$D$20=2)*Premissas!$C$14:$C$20*Premissas!$B$14:$B$20)*4/3 | Q29: =0+Premissas!$B$42*SUMPRODUCT((Premissas!$D$14:$D$20=3)*Premissas!$C$14:$C$20*Premissas!$B$14:$B$20)*4/3 | R29: =0+Premissas!$B$42*SUMPRODUCT((Premissas!$D$14:$D$20=4)*Premissas!$C$14:$C$20*Premissas!$B$14:$B$20)*4/3 | S29: =0+Premissas!$B$42*SUMPRODUCT((Premissas!$D$14:$D$20=5)*Premissas!$C$14:$C$20*Premissas!$B$14:$B$20)*4/3
A30: Professores (salário + encargos) | B30: 0 | C30: 0 | D30: =D8*Premissas!$B$35 | E30: =E8*Premissas!$B$35 | F30: =F8*Premissas!$B$35 | G30: =G8*Premissas!$B$35 | H30: =H8*Premissas!$B$35 | I30: =I8*Premissas!$B$35 | J30: =J8*Premissas!$B$35 | K30: =K8*Premissas!$B$35 | ... S30: =S8*Premissas!$B$35
A31: Aluguel do espaço | B31: ='Custos mês a mês'!B2 | C31: ='Custos mês a mês'!C2 | D31: ='Custos mês a mês'!D2 | E31: ='Custos mês a mês'!E2 | F31: ='Custos mês a mês'!F2 | G31: ='Custos mês a mês'!G2 | H31: ='Custos mês a mês'!H2 | I31: ='Custos mês a mês'!I2 | ... S31: ='Custos mês a mês'!S2
A32: Água | B32: ='Custos mês a mês'!B3 | C32: ='Custos mês a mês'!C3 | D32: ='Custos mês a mês'!D3 | E32: ='Custos mês a mês'!E3 | F32: ='Custos mês a mês'!F3 | G32: ='Custos mês a mês'!G3 | H32: ='Custos mês a mês'!H3 | I32: ='Custos mês a mês'!I3 | ... S32: ='Custos mês a mês'!S3
A33: Luz | B33: ='Custos mês a mês'!B4 | C33: ='Custos mês a mês'!C4 | D33: ='Custos mês a mês'!D4 | E33: ='Custos mês a mês'!E4 | F33: ='Custos mês a mês'!F4 | G33: ='Custos mês a mês'!G4 | H33: ='Custos mês a mês'!H4 | I33: ='Custos mês a mês'!I4 | ... S33: ='Custos mês a mês'!S4
A34: Telefone | B34: ='Custos mês a mês'!B5 | C34: ='Custos mês a mês'!C5 | D34: ='Custos mês a mês'!D5 | E34: ='Custos mês a mês'!E5 | F34: ='Custos mês a mês'!F5 | G34: ='Custos mês a mês'!G5 | H34: ='Custos mês a mês'!H5 | I34: ='Custos mês a mês'!I5 | ... S34: ='Custos mês a mês'!S5
A35: Internet | B35: ='Custos mês a mês'!B6 | C35: ='Custos mês a mês'!C6 | D35: ='Custos mês a mês'!D6 | E35: ='Custos mês a mês'!E6 | F35: ='Custos mês a mês'!F6 | G35: ='Custos mês a mês'!G6 | H35: ='Custos mês a mês'!H6 | I35: ='Custos mês a mês'!I6 | ... S35: ='Custos mês a mês'!S6
A36: Sistema de gestão DiscoverON | B36: ='Custos mês a mês'!B7 | C36: ='Custos mês a mês'!C7 | D36: ='Custos mês a mês'!D7 | E36: ='Custos mês a mês'!E7 | F36: ='Custos mês a mês'!F7 | G36: ='Custos mês a mês'!G7 | H36: ='Custos mês a mês'!H7 | I36: ='Custos mês a mês'!I7 | ... S36: ='Custos mês a mês'!S7
A37: Itens para aula | B37: ='Custos mês a mês'!B8 | C37: ='Custos mês a mês'!C8 | D37: ='Custos mês a mês'!D8 | E37: ='Custos mês a mês'!E8 | F37: ='Custos mês a mês'!F8 | G37: ='Custos mês a mês'!G8 | H37: ='Custos mês a mês'!H8 | I37: ='Custos mês a mês'!I8 | ... S37: ='Custos mês a mês'!S8
A38: Materiais de limpeza + higiene | B38: ='Custos mês a mês'!B9 | C38: ='Custos mês a mês'!C9 | D38: ='Custos mês a mês'!D9 | E38: ='Custos mês a mês'!E9 | F38: ='Custos mês a mês'!F9 | G38: ='Custos mês a mês'!G9 | H38: ='Custos mês a mês'!H9 | I38: ='Custos mês a mês'!I9 | ... S38: ='Custos mês a mês'!S9
A39: Brindes | B39: ='Custos mês a mês'!B10 | C39: ='Custos mês a mês'!C10 | D39: ='Custos mês a mês'!D10 | E39: ='Custos mês a mês'!E10 | F39: ='Custos mês a mês'!F10 | G39: ='Custos mês a mês'!G10 | H39: ='Custos mês a mês'!H10 | I39: ='Custos mês a mês'!I10 | ... S39: ='Custos mês a mês'!S10
A40: Marketing | B40: ='Custos mês a mês'!B11 | C40: ='Custos mês a mês'!C11 | D40: ='Custos mês a mês'!D11 | E40: ='Custos mês a mês'!E11 | F40: ='Custos mês a mês'!F11 | G40: ='Custos mês a mês'!G11 | H40: ='Custos mês a mês'!H11 | I40: ='Custos mês a mês'!I11 | ... S40: ='Custos mês a mês'!S11
A41: Aluguel dos computadores | B41: ='Custos mês a mês'!B12 | C41: ='Custos mês a mês'!C12 | D41: ='Custos mês a mês'!D12 | E41: ='Custos mês a mês'!E12 | F41: ='Custos mês a mês'!F12 | G41: ='Custos mês a mês'!G12 | H41: ='Custos mês a mês'!H12 | I41: ='Custos mês a mês'!I12 | ... S41: ='Custos mês a mês'!S12
A42: Seguro empresarial | B42: ='Custos mês a mês'!B13 | C42: ='Custos mês a mês'!C13 | D42: ='Custos mês a mês'!D13 | E42: ='Custos mês a mês'!E13 | F42: ='Custos mês a mês'!F13 | G42: ='Custos mês a mês'!G13 | H42: ='Custos mês a mês'!H13 | I42: ='Custos mês a mês'!I13 | ... S42: ='Custos mês a mês'!S13
... A45: Pró-labore | B45: ='Custos mês a mês'!B16 | C45: ='Custos mês a mês'!C16 | D45: ='Custos mês a mês'!D16 | E45: ='Custos mês a mês'!E16 | F45: ='Custos mês a mês'!F16 | G45: ='Custos mês a mês'!G16 | H45: ='Custos mês a mês'!H16 | I45: ='Custos mês a mês'!I16 | ... S45: ='Custos mês a mês'!S16
A46: Total de despesas | B46: =SUM(B23:B45) | C46: =SUM(C23:C45) | D46: =SUM(D23:D45) | E46: =SUM(E23:E45) | F46: =SUM(F23:F45) | G46: =SUM(G23:G45) | H46: =SUM(H23:H45) | I46: =SUM(I23:I45) | ... S46: =SUM(S23:S45)
A48: Resultado do mês | B48: =B15-B46 | C48: =C15-C46 | D48: =D15-D46 | E48: =E15-E46 | F48: =F15-F46 | G48: =G15-G46 | H48: =H15-H46 | I48: =I15-I46 | ... S48: =S15-S46
A49: Caixa acumulado (operacional) | B49: =B48 | C49: =B49+C48 | D49: =C49+D48 | E49: =D49+E48 | F49: =E49+F48 | G49: =F49+G48 | H49: =G49+H48 | I49: =H49+I48 | J49: =I49+J48 | ... S49: =R49+S48
A50: Caixa acumulado incl. investimento | B50: =B49-INVEST_TOTAL | C50: =C49-INVEST_TOTAL | D50: =D49-INVEST_TOTAL | E50: =E49-INVEST_TOTAL | F50: =F49-INVEST_TOTAL | G50: =G49-INVEST_TOTAL | H50: =H49-INVEST_TOTAL | I50: =I49-INVEST_TOTAL | ... S50: =S49-INVEST_TOTAL
A51: MARCOS | D51: =IF(AND(D48>0,COUNTIF($D48:D48,">0")=1),IF(AND(D50>=0,COUNTIF($D50:D50,">=0")=1),"BE + PAYBACK","BREAK-EVEN"),IF(AND(D50>=0,COUNTIF($D50:D50,">=0")=1),"PAYBACK","")) | E51: =IF(AND(E48>0,COUNTIF($D48:E48,">0")=1),IF(AND(E50>=0,COUNTIF($D50:E50,">=0")=1),"BE + PAYBACK","BREAK-EVEN"),IF(AND(E50>=0,COUNTIF($D50:E50,">=0")=1),"PAYBACK","")) | F51: =IF(AND(F48>0,COUNTIF($D48:F48,">0")=1),IF(AND(F50>=0,COUNTIF($D50:F50,">=0")=1),"BE + PAYBACK","BREAK-EVEN"),IF(AND(F50>=0,COUNTIF($D50:F50,">=0")=1),"PAYBACK","")) | G51: =IF(AND(G48>0,COUNTIF($D48:G48,">0")=1),IF(AND(G50>=0,COUNTIF($D50:G50,">=0")=1),"BE + PAYBACK","BREAK-EVEN"),IF(AND(G50>=0,COUNTIF($D50:G50,">=0")=1),"PAYBACK","")) | H51: =IF(AND(H48>0,COUNTIF($D48:H48,">0")=1),IF(AND(H50>=0,COUNTIF($D50:H50,">=0")=1),"BE + PAYBACK","BREAK-EVEN"),IF(AND(H50>=0,COUNTIF($D50:H50,">=0")=1),"PAYBACK","")) | I51: =IF(AND(I48>0,COUNTIF($D48:I48,">0")=1),IF(AND(I50>=0,COUNTIF($D50:I50,">=0")=1),"BE + PAYBACK","BREAK-EVEN"),IF(AND(I50>=0,COUNTIF($D50:I50,">=0")=1),"PAYBACK","")) | J51: =IF(AND(J48>0,COUNTIF($D48:J48,">0")=1),IF(AND(J50>=0,COUNTIF($D50:J50,">=0")=1),"BE + PAYBACK","BREAK-EVEN"),IF(AND(J50>=0,COUNTIF($D50:J50,">=0")=1),"PAYBACK","")) | K51: =IF(AND(K48>0,COUNTIF($D48:K48,">0")=1),IF(AND(K50>=0,COUNTIF($D50:K50,">=0")=1),"BE + PAYBACK","BREAK-EVEN"),IF(AND(K50>=0,COUNTIF($D50:K50,">=0")=1),"PAYBACK","")) | ... S51: =IF(AND(S48>0,COUNTIF($D48:S48,">0")=1),IF(AND(S50>=0,COUNTIF($D50:S50,">=0")=1),"BE + PAYBACK","BREAK-EVEN"),IF(AND(S50>=0,COUNTIF($D50:S50,">=0")=1),"PAYBACK",""))
A53: AJUSTES RÁPIDOS — valem só nesta aba
A54: Churn mensal (%) | B54: 0.1 | D54: Teste hipóteses sem mexer nos 3 cenários oficiais.
A55: Inadimplência (%) | B55: 0.1
A56: Mensalidade (R$) | B56: 280
A58: SAÚDE DA EMPRESA
A59: Alunos no fim do horizonte (M16) | B59: =S7
A60: Alíquota efetiva do Simples no M16 | B60: =S20
A61: Resultado no M16 | B61: =S48
A62: Pior caixa operacional | B62: =MIN(B49:S49)
A63: Capital de giro necessário | B63: =MAX(0,-B62)
A64: 1º mês de operação com lucro | B64: =IFERROR(MATCH(TRUE,INDEX(D48:S48>0,0),0),"—")
A65: Payback incl. investimento (mês) | B65: =IFERROR(MATCH(TRUE,INDEX(D50:S50>=0,0),0),"não atinge")
A66: Caixa final incl. investimento | B66: =S50
A67: Necessidade total de capital | B67: =INVEST_TOTAL+B63
A69: VEREDITO | B69: =IF(NOT(ISNUMBER(B65)),"❌ NÃO SE PAGA em 16 meses",IF(B65<=12,"✅ SAUDÁVEL — payback no mês "&B65,"⚠️ NO LIMITE — payback no mês "&B65))

Sheet Realizado
A1: REALIZADO — lance o que de fato entrou e saiu | B1: Out (obras) | C1: Nov (obras) | D1: Dez (M1) | E1: Jan (M2) | F1: Fev (M3) | G1: Mar (M4) | H1: Abr (M5) | I1: Mai (M6) | J1: Jun (M7) | K1: Jul (M8) | L1: Ago (M9) | M1: Set (M10) | N1: Out (M11) | O1: Nov (M12) | P1: Dez (M13) | Q1: Jan (M14) | R1: Fev (M15) | S1: Mar (M16)
A2: Alunos ativos no fim do mês
A3: Matrículas feitas no mês
A4: Desistências no mês
A6: RECEITAS RECEBIDAS
A7: Matrículas
A8: Mensalidades
A9: Material didático
A10: Outras receitas
A11: Total recebido | B11: =SUM(B7:B10) | C11: =SUM(C7:C10) | D11: =SUM(D7:D10) | E11: =SUM(E7:E10) | F11: =SUM(F7:F10) | G11: =SUM(G7:G10) | H11: =SUM(H7:H10) | I11: =SUM(I7:I10) | ... S11: =SUM(S7:S10)
A13: DESPESAS PAGAS
A14: Impostos
A15: Material — parcelas
A16: Comissões
A17: Folha + encargos mensais
A18: Vale-transporte / benefícios
A19: 13º e férias
A20: Professores
A21: Aluguel do espaço
A22: Água
A23: Luz
A24: Telefone
... A36: Outras despesas
A37: Total pago | B37: =SUM(B14:B36) | C37: =SUM(C14:C36) | D37: =SUM(D14:D36) | E37: =SUM(E14:E36) | F37: =SUM(F14:F36) | G37: =SUM(G14:G36) | H37: =SUM(H14:H36) | I37: =SUM(I14:I36) | ... S37: =SUM(S14:S36)
A39: Resultado do mês | B39: =B11-B37 | C39: =C11-C37 | D39: =D11-D37 | E39: =E11-E37 | F39: =F11-F37 | G39: =G11-G37 | H39: =H11-H37 | I39: =I11-I37 | ... S39: =S11-S37
A40: Caixa acumulado | B40: =B39 | C40: =B40+C39 | D40: =C40+D39 | E40: =D40+E39 | F40: =E40+F39 | G40: =F40+G39 | H40: =G40+H39 | I40: =H40+I39 | J40: =I40+J39 | ... S40: =R40+S39
A42: Preencha só o que já aconteceu — meses futuros ficam zerados.

Sheet Plano × Real
A1: DESVIO (Realizado − Plano) · plano = Cenário Moderado | B1: Out (obras) | C1: Nov (obras) | D1: Dez (M1) | E1: Jan (M2) | F1: Fev (M3) | G1: Mar (M4) | H1: Abr (M5) | I1: Mai (M6) | J1: Jun (M7) | K1: Jul (M8) | L1: Ago (M9) | M1: Set (M10) | N1: Out (M11) | O1: Nov (M12) | P1: Dez (M13) | Q1: Jan (M14) | R1: Fev (M15) | S1: Mar (M16)
A2: Alunos ativos | B2: =Realizado!B2-'Cenário Moderado'!B7 | C2: =Realizado!C2-'Cenário Moderado'!C7 | D2: =Realizado!D2-'Cenário Moderado'!D7 | E2: =Realizado!E2-'Cenário Moderado'!E7 | F2: =Realizado!F2-'Cenário Moderado'!F7 | G2: =Realizado!G2-'Cenário Moderado'!G7 | H2: =Realizado!H2-'Cenário Moderado'!H7 | I2: =Realizado!I2-'Cenário Moderado'!I7 | ... S2: =Realizado!S2-'Cenário Moderado'!S7
A3: Matrículas no mês | B3: =Realizado!B3-'Cenário Moderado'!B4 | C3: =Realizado!C3-'Cenário Moderado'!C4 | D3: =Realizado!D3-'Cenário Moderado'!D4 | E3: =Realizado!E3-'Cenário Moderado'!E4 | F3: =Realizado!F3-'Cenário Moderado'!F4 | G3: =Realizado!G3-'Cenário Moderado'!G4 | H3: =Realizado!H3-'Cenário Moderado'!H4 | I3: =Realizado!I3-'Cenário Moderado'!I4 | ... S3: =Realizado!S3-'Cenário Moderado'!S4
A5: Receita recebida | B5: =Realizado!B11-'Cenário Moderado'!B15 | C5: =Realizado!C11-'Cenário Moderado'!C15 | D5: =Realizado!D11-'Cenário Moderado'!D15 | E5: =Realizado!E11-'Cenário Moderado'!E15 | F5: =Realizado!F11-'Cenário Moderado'!F15 | G5: =Realizado!G11-'Cenário Moderado'!G15 | H5: =Realizado!H11-'Cenário Moderado'!H15 | I5: =Realizado!I11-'Cenário Moderado'!I15 | ... S5: =Realizado!S11-'Cenário Moderado'!S15
A7: Impostos | B7: =Realizado!B14-'Cenário Moderado'!B23 | C7: =Realizado!C14-'Cenário Moderado'!C23 | D7: =Realizado!D14-'Cenário Moderado'!D23 | E7: =Realizado!E14-'Cenário Moderado'!E23 | F7: =Realizado!F14-'Cenário Moderado'!F23 | G7: =Realizado!G14-'Cenário Moderado'!G23 | H7: =Realizado!H14-'Cenário Moderado'!H23 | I7: =Realizado!I14-'Cenário Moderado'!I23 | ... S7: =Realizado!S14-'Cenário Moderado'!S23
A8: Material — parcelas | B8: =Realizado!B15-'Cenário Moderado'!B24 | C8: =Realizado!C15-'Cenário Moderado'!C24 | D8: =Realizado!D15-'Cenário Moderado'!D24 | E8: =Realizado!E15-'Cenário Moderado'!E24 | F8: =Realizado!F15-'Cenário Moderado'!F24 | G8: =Realizado!G15-'Cenário Moderado'!G24 | H8: =Realizado!H15-'Cenário Moderado'!H24 | I8: =Realizado!I15-'Cenário Moderado'!I24 | ... S8: =Realizado!S15-'Cenário Moderado'!S24
A9: Comissões | B9: =Realizado!B16-'Cenário Moderado'!B25 | C9: =Realizado!C16-'Cenário Moderado'!C25 | D9: =Realizado!D16-'Cenário Moderado'!D25 | E9: =Realizado!E16-'Cenário Moderado'!E25 | F9: =Realizado!F16-'Cenário Moderado'!F25 | G9: =Realizado!G16-'Cenário Moderado'!G25 | H9: =Realizado!H16-'Cenário Moderado'!H25 | I9: =Realizado!I16-'Cenário Moderado'!I25 | ... S9: =Realizado!S16-'Cenário Moderado'!S25
A10: Folha + encargos mensais | B10: =Realizado!B17-'Cenário Moderado'!B27 | C10: =Realizado!C17-'Cenário Moderado'!C27 | D10: =Realizado!D17-'Cenário Moderado'!D27 | E10: =Realizado!E17-'Cenário Moderado'!E27 | F10: =Realizado!F17-'Cenário Moderado'!F27 | G10: =Realizado!G17-'Cenário Moderado'!G27 | H10: =Realizado!H17-'Cenário Moderado'!H27 | I10: =Realizado!I17-'Cenário Moderado'!I27 | ... S10: =Realizado!S17-'Cenário Moderado'!S27
A11: Vale-transporte / benefícios | B11: =Realizado!B18-'Cenário Moderado'!B28 | C11: =Realizado!C18-'Cenário Moderado'!C28 | D11: =Realizado!D18-'Cenário Moderado'!D28 | E11: =Realizado!E18-'Cenário Moderado'!E28 | F11: =Realizado!F18-'Cenário Moderado'!F28 | G11: =Realizado!G18-'Cenário Moderado'!G28 | H11: =Realizado!H18-'Cenário Moderado'!H28 | I11: =Realizado!I18-'Cenário Moderado'!I28 | ... S11: =Realizado!S18-'Cenário Moderado'!S28
A12: 13º e férias | B12: =Realizado!B19-'Cenário Moderado'!B29 | C12: =Realizado!C19-'Cenário Moderado'!C29 | D12: =Realizado!D19-'Cenário Moderado'!D29 | E12: =Realizado!E19-'Cenário Moderado'!E29 | F12: =Realizado!F19-'Cenário Moderado'!F29 | G12: =Realizado!G19-'Cenário Moderado'!G29 | H12: =Realizado!H19-'Cenário Moderado'!H29 | I12: =Realizado!I19-'Cenário Moderado'!I29 | ... S12: =Realizado!S19-'Cenário Moderado'!S29
A13: Professores | B13: =Realizado!B20-'Cenário Moderado'!B30 | C13: =Realizado!C20-'Cenário Moderado'!C30 | D13: =Realizado!D20-'Cenário Moderado'!D30 | E13: =Realizado!E20-'Cenário Moderado'!E30 | F13: =Realizado!F20-'Cenário Moderado'!F30 | G13: =Realizado!G20-'Cenário Moderado'!G30 | H13: =Realizado!H20-'Cenário Moderado'!H30 | I13: =Realizado!I20-'Cenário Moderado'!I30 | ... S13: =Realizado!S20-'Cenário Moderado'!S30
A14: Aluguel do espaço | B14: =Realizado!B21-'Cenário Moderado'!B31 | C14: =Realizado!C21-'Cenário Moderado'!C31 | D14: =Realizado!D21-'Cenário Moderado'!D31 | E14: =Realizado!E21-'Cenário Moderado'!E31 | F14: =Realizado!F21-'Cenário Moderado'!F31 | G14: =Realizado!G21-'Cenário Moderado'!G31 | H14: =Realizado!H21-'Cenário Moderado'!H31 | I14: =Realizado!I21-'Cenário Moderado'!I31 | ... S14: =Realizado!S21-'Cenário Moderado'!S31
A15: Água | B15: =Realizado!B22-'Cenário Moderado'!B32 | C15: =Realizado!C22-'Cenário Moderado'!C32 | D15: =Realizado!D22-'Cenário Moderado'!D32 | E15: =Realizado!E22-'Cenário Moderado'!E32 | F15: =Realizado!F22-'Cenário Moderado'!F32 | G15: =Realizado!G22-'Cenário Moderado'!G32 | H15: =Realizado!H22-'Cenário Moderado'!H32 | I15: =Realizado!I22-'Cenário Moderado'!I32 | ... S15: =Realizado!S22-'Cenário Moderado'!S32
A16: Luz | B16: =Realizado!B23-'Cenário Moderado'!B33 | C16: =Realizado!C23-'Cenário Moderado'!C33 | D16: =Realizado!D23-'Cenário Moderado'!D33 | E16: =Realizado!E23-'Cenário Moderado'!E33 | F16: =Realizado!F23-'Cenário Moderado'!F33 | G16: =Realizado!G23-'Cenário Moderado'!G33 | H16: =Realizado!H23-'Cenário Moderado'!H33 | I16: =Realizado!I23-'Cenário Moderado'!I33 | ... S16: =Realizado!S23-'Cenário Moderado'!S33
A17: Telefone | B17: =Realizado!B24-'Cenário Moderado'!B34 | C17: =Realizado!C24-'Cenário Moderado'!C34 | D17: =Realizado!D24-'Cenário Moderado'!D34 | E17: =Realizado!E24-'Cenário Moderado'!E34 | F17: =Realizado!F24-'Cenário Moderado'!F34 | G17: =Realizado!G24-'Cenário Moderado'!G34 | H17: =Realizado!H24-'Cenário Moderado'!H34 | I17: =Realizado!I24-'Cenário Moderado'!I34 | ... S17: =Realizado!S24-'Cenário Moderado'!S34
A18: Internet | B18: =Realizado!B25-'Cenário Moderado'!B35 | C18: =Realizado!C25-'Cenário Moderado'!C35 | D18: =Realizado!D25-'Cenário Moderado'!D35 | E18: =Realizado!E25-'Cenário Moderado'!E35 | F18: =Realizado!F25-'Cenário Moderado'!F35 | G18: =Realizado!G25-'Cenário Moderado'!G35 | H18: =Realizado!H25-'Cenário Moderado'!H35 | I18: =Realizado!I25-'Cenário Moderado'!I35 | ... S18: =Realizado!S25-'Cenário Moderado'!S35
A19: Sistema de gestão DiscoverON | B19: =Realizado!B26-'Cenário Moderado'!B36 | C19: =Realizado!C26-'Cenário Moderado'!C36 | D19: =Realizado!D26-'Cenário Moderado'!D36 | E19: =Realizado!E26-'Cenário Moderado'!E36 | F19: =Realizado!F26-'Cenário Moderado'!F36 | G19: =Realizado!G26-'Cenário Moderado'!G36 | H19: =Realizado!H26-'Cenário Moderado'!H36 | I19: =Realizado!I26-'Cenário Moderado'!I36 | ... S19: =Realizado!S26-'Cenário Moderado'!S36
A20: Itens para aula | B20: =Realizado!B27-'Cenário Moderado'!B37 | C20: =Realizado!C27-'Cenário Moderado'!C37 | D20: =Realizado!D27-'Cenário Moderado'!D37 | E20: =Realizado!E27-'Cenário Moderado'!E37 | F20: =Realizado!F27-'Cenário Moderado'!F37 | G20: =Realizado!G27-'Cenário Moderado'!G37 | H20: =Realizado!H27-'Cenário Moderado'!H37 | I20: =Realizado!I27-'Cenário Moderado'!I37 | ... S20: =Realizado!S27-'Cenário Moderado'!S37
A21: Materiais de limpeza + higiene | B21: =Realizado!B28-'Cenário Moderado'!B38 | C21: =Realizado!C28-'Cenário Moderado'!C38 | D21: =Realizado!D28-'Cenário Moderado'!D38 | E21: =Realizado!E28-'Cenário Moderado'!E38 | F21: =Realizado!F28-'Cenário Moderado'!F38 | G21: =Realizado!G28-'Cenário Moderado'!G38 | H21: =Realizado!H28-'Cenário Moderado'!H38 | I21: =Realizado!I28-'Cenário Moderado'!I38 | ... S21: =Realizado!S28-'Cenário Moderado'!S38
... A28: Pró-labore | B28: =Realizado!B35-'Cenário Moderado'!B45 | C28: =Realizado!C35-'Cenário Moderado'!C45 | D28: =Realizado!D35-'Cenário Moderado'!D45 | E28: =Realizado!E35-'Cenário Moderado'!E45 | F28: =Realizado!F35-'Cenário Moderado'!F45 | G28: =Realizado!G35-'Cenário Moderado'!G45 | H28: =Realizado!H35-'Cenário Moderado'!H45 | I28: =Realizado!I35-'Cenário Moderado'!I45 | ... S28: =Realizado!S35-'Cenário Moderado'!S45
A29: Total de despesas | B29: =Realizado!B37-'Cenário Moderado'!B46 | C29: =Realizado!C37-'Cenário Moderado'!C46 | D29: =Realizado!D37-'Cenário Moderado'!D46 | E29: =Realizado!E37-'Cenário Moderado'!E46 | F29: =Realizado!F37-'Cenário Moderado'!F46 | G29: =Realizado!G37-'Cenário Moderado'!G46 | H29: =Realizado!H37-'Cenário Moderado'!H46 | I29: =Realizado!I37-'Cenário Moderado'!I46 | ... S29: =Realizado!S37-'Cenário Moderado'!S46
A31: Resultado do mês | B31: =Realizado!B39-'Cenário Moderado'!B48 | C31: =Realizado!C39-'Cenário Moderado'!C48 | D31: =Realizado!D39-'Cenário Moderado'!D48 | E31: =Realizado!E39-'Cenário Moderado'!E48 | F31: =Realizado!F39-'Cenário Moderado'!F48 | G31: =Realizado!G39-'Cenário Moderado'!G48 | H31: =Realizado!H39-'Cenário Moderado'!H48 | I31: =Realizado!I39-'Cenário Moderado'!I48 | ... S31: =Realizado!S39-'Cenário Moderado'!S48
A32: Caixa acumulado | B32: =Realizado!B40-'Cenário Moderado'!B49 | C32: =Realizado!C40-'Cenário Moderado'!C49 | D32: =Realizado!D40-'Cenário Moderado'!D49 | E32: =Realizado!E40-'Cenário Moderado'!E49 | F32: =Realizado!F40-'Cenário Moderado'!F49 | G32: =Realizado!G40-'Cenário Moderado'!G49 | H32: =Realizado!H40-'Cenário Moderado'!H49 | I32: =Realizado!I40-'Cenário Moderado'!I49 | ... S32: =Realizado!S40-'Cenário Moderado'!S49
A34: 🟩 verde = melhor que o plano · 🟥 vermelho = pior que o plano.

Sheet Custos de implantação
A1: CUSTOS DE IMPLANTAÇÃO — lance cada gasto com suas tags
A2: Total lançado | C2: Já pago | E2: Ainda previsto | G2: Nº de lançamentos
A3: =SUMIFS($F$5:$F$204,$G$5:$G$204,"<>Cancelado") | C3: =SUMIFS($F$5:$F$204,$G$5:$G$204,"Pago") | E3: =SUMIFS($F$5:$F$204,$G$5:$G$204,"Previsto") | G3: =COUNTIF($C$5:$C$204,"<>")
A4: Data | B4: Descrição | C4: Categoria | D4: Tipo | E4: Fornecedor | F4: Valor TOTAL (R$) | G4: Status | H4: Mês de início | I4: Parcelas | J4: Observação | K4: idx | M4: Categorias | N4: Tipos | O4: Status | P4: Meses
A5: 46275 | B5: Projeto arquitetônico | C5: Documentação/Legal | D5: Consultoria | E5: Arquiteta | F5: 8000 | G5: Previsto | H5: Set/26 | I5: 4 | J5: 8k em 4x a partir de setembro | K5: =IFERROR(MATCH(H5,$P$5:$P$23,0)-1,-1) | M5: Obra | N5: Material | O5: Pago | P5: Set/26
A6: 46300 | B6: Cimento, areia e argamassa dos banheiros | C6: Obra | D6: Material | E6: Depósito Silva | F6: 500 | G6: Pago | H6: Out/26 | I6: 1 | K6: =IFERROR(MATCH(H6,$P$5:$P$23,0)-1,-1) | M6: Documentação/Legal | N6: Mão de obra | O6: Previsto | P6: Out/26
A7: 46303 | B7: Pedreiro — reforma dos banheiros | C7: Obra | D7: Mão de obra | E7: José Pedreiro | F7: 1000 | G7: Pago | H7: Out/26 | I7: 1 | K7: =IFERROR(MATCH(H7,$P$5:$P$23,0)-1,-1) | M7: Equipamentos/TI | N7: Serviço | O7: Cancelado | P7: Nov/26
A8: 46305 | B8: Abertura de empresa e contrato social | C8: Documentação/Legal | D8: Licença/Taxa | E8: Contabilidade | F8: 1000 | G8: Pago | H8: Out/26 | I8: 1 | K8: =IFERROR(MATCH(H8,$P$5:$P$23,0)-1,-1) | M8: Mobiliário | N8: Compra | P8: Dez/26
A9: 46310 | B9: Alvará de funcionamento | C9: Documentação/Legal | D9: Licença/Taxa | E9: Prefeitura | F9: 2500 | G9: Previsto | H9: Nov/26 | I9: 1 | K9: =IFERROR(MATCH(H9,$P$5:$P$23,0)-1,-1) | M9: Marketing | N9: Licença/Taxa | P9: Jan/27
A10: 46315 | B10: Ar-condicionado (3 unidades) | C10: Equipamentos/TI | D10: Compra | E10: Loja X | F10: 12000 | G10: Previsto | H10: Nov/26 | I10: 3 | J10: parcelado em 3x | K10: =IFERROR(MATCH(H10,$P$5:$P$23,0)-1,-1) | M10: Material didático | N10: Consultoria | P10: Fev/27
I11: 1 | K11: =IFERROR(MATCH(H11,$P$5:$P$23,0)-1,-1) | M11: Instalações | N11: Software | P11: Mar/27
I12: 1 | K12: =IFERROR(MATCH(H12,$P$5:$P$23,0)-1,-1) | M12: Taxas/Franquia | N12: Outros | P12: Abr/27
I13: 1 | K13: =IFERROR(MATCH(H13,$P$5:$P$23,0)-1,-1) | M13: Aluguel/Caução | P13: Mai/27
I14: 1 | K14: =IFERROR(MATCH(H14,$P$5:$P$23,0)-1,-1) | M14: Outros | P14: Jun/27
I15: 1 | K15: =IFERROR(MATCH(H15,$P$5:$P$23,0)-1,-1) | P15: Jul/27
I16: 1 | K16: =IFERROR(MATCH(H16,$P$5:$P$23,0)-1,-1) | P16: Ago/27
I17: 1 | K17: =IFERROR(MATCH(H17,$P$5:$P$23,0)-1,-1) | P17: Set/27
I18: 1 | K18: =IFERROR(MATCH(H18,$P$5:$P$23,0)-1,-1) | P18: Out/27
I19: 1 | K19: =IFERROR(MATCH(H19,$P$5:$P$23,0)-1,-1) | P19: Nov/27
I20: 1 | K20: =IFERROR(MATCH(H20,$P$5:$P$23,0)-1,-1) | P20: Dez/27
I21: 1 | K21: =IFERROR(MATCH(H21,$P$5:$P$23,0)-1,-1) | P21: Jan/28
I22: 1 | K22: =IFERROR(MATCH(H22,$P$5:$P$23,0)-1,-1) | P22: Fev/28
I23: 1 | K23: =IFERROR(MATCH(H23,$P$5:$P$23,0)-1,-1) | P23: Mar/28
I24: 1 | K24: =IFERROR(MATCH(H24,$P$5:$P$23,0)-1,-1)
I25: 1 | K25: =IFERROR(MATCH(H25,$P$5:$P$23,0)-1,-1)
I26: 1 | K26: =IFERROR(MATCH(H26,$P$5:$P$23,0)-1,-1)
I27: 1 | K27: =IFERROR(MATCH(H27,$P$5:$P$23,0)-1,-1)
I28: 1 | K28: =IFERROR(MATCH(H28,$P$5:$P$23,0)-1,-1)
I29: 1 | K29: =IFERROR(MATCH(H29,$P$5:$P$23,0)-1,-1)
I30: 1 | K30: =IFERROR(MATCH(H30,$P$5:$P$23,0)-1,-1)
I31: 1 | K31: =IFERROR(MATCH(H31,$P$5:$P$23,0)-1,-1)
I32: 1 | K32: =IFERROR(MATCH(H32,$P$5:$P$23,0)-1,-1)
I33: 1 | K33: =IFERROR(MATCH(H33,$P$5:$P$23,0)-1,-1)
I34: 1 | K34: =IFERROR(MATCH(H34,$P$5:$P$23,0)-1,-1)
I35: 1 | K35: =IFERROR(MATCH(H35,$P$5:$P$23,0)-1,-1)
... I204: 1 | K204: =IFERROR(MATCH(H204,$P$5:$P$23,0)-1,-1)
A206: As colunas M, N, O e P guardam as listas dos menus — acrescente uma tag ali e ela aparece no dropdown e na análise.
A207: Valor TOTAL + mês de início + parcelas: o gasto é distribuído no fluxo mensal (ex.: projeto arquitetônico R$ 8.000 em 4x a partir de Set/26 = R$ 2.000/mês de set a dez).
A208: As primeiras linhas são exemplos: apague e comece a lançar os seus.

Sheet Análise de custos
A1: ANÁLISE — para onde o dinheiro foi
A2: Total lançado | B2: Orçado no CAPEX | C2: Desvio
A3: =SUMIFS('Custos de implantação'!$F$5:$F$204,'Custos de implantação'!$G$5:$G$204,"<>Cancelado") | B3: =INVEST_TOTAL | C3: =A3-B3
A5: POR CATEGORIA
A6: Categoria | B6: Total | C6: % do total | D6: Nº
A7: ='Custos de implantação'!$J$5 | B7: =SUMIFS('Custos de implantação'!$F$5:$F$204,'Custos de implantação'!$C$5:$C$204,$A7,'Custos de implantação'!$G$5:$G$204,"<>Cancelado") | C7: =IF($A$3=0,0,B7/$A$3) | D7: =COUNTIFS('Custos de implantação'!$C$5:$C$204,$A7)
A8: ='Custos de implantação'!$J$6 | B8: =SUMIFS('Custos de implantação'!$F$5:$F$204,'Custos de implantação'!$C$5:$C$204,$A8,'Custos de implantação'!$G$5:$G$204,"<>Cancelado") | C8: =IF($A$3=0,0,B8/$A$3) | D8: =COUNTIFS('Custos de implantação'!$C$5:$C$204,$A8)
A9: ='Custos de implantação'!$J$7 | B9: =SUMIFS('Custos de implantação'!$F$5:$F$204,'Custos de implantação'!$C$5:$C$204,$A9,'Custos de implantação'!$G$5:$G$204,"<>Cancelado") | C9: =IF($A$3=0,0,B9/$A$3) | D9: =COUNTIFS('Custos de implantação'!$C$5:$C$204,$A9)
A10: ='Custos de implantação'!$J$8 | B10: =SUMIFS('Custos de implantação'!$F$5:$F$204,'Custos de implantação'!$C$5:$C$204,$A10,'Custos de implantação'!$G$5:$G$204,"<>Cancelado") | C10: =IF($A$3=0,0,B10/$A$3) | D10: =COUNTIFS('Custos de implantação'!$C$5:$C$204,$A10)
A11: ='Custos de implantação'!$J$9 | B11: =SUMIFS('Custos de implantação'!$F$5:$F$204,'Custos de implantação'!$C$5:$C$204,$A11,'Custos de implantação'!$G$5:$G$204,"<>Cancelado") | C11: =IF($A$3=0,0,B11/$A$3) | D11: =COUNTIFS('Custos de implantação'!$C$5:$C$204,$A11)
A12: ='Custos de implantação'!$J$10 | B12: =SUMIFS('Custos de implantação'!$F$5:$F$204,'Custos de implantação'!$C$5:$C$204,$A12,'Custos de implantação'!$G$5:$G$204,"<>Cancelado") | C12: =IF($A$3=0,0,B12/$A$3) | D12: =COUNTIFS('Custos de implantação'!$C$5:$C$204,$A12)
A13: ='Custos de implantação'!$J$11 | B13: =SUMIFS('Custos de implantação'!$F$5:$F$204,'Custos de implantação'!$C$5:$C$204,$A13,'Custos de implantação'!$G$5:$G$204,"<>Cancelado") | C13: =IF($A$3=0,0,B13/$A$3) | D13: =COUNTIFS('Custos de implantação'!$C$5:$C$204,$A13)
A14: ='Custos de implantação'!$J$12 | B14: =SUMIFS('Custos de implantação'!$F$5:$F$204,'Custos de implantação'!$C$5:$C$204,$A14,'Custos de implantação'!$G$5:$G$204,"<>Cancelado") | C14: =IF($A$3=0,0,B14/$A$3) | D14: =COUNTIFS('Custos de implantação'!$C$5:$C$204,$A14)
A15: ='Custos de implantação'!$J$13 | B15: =SUMIFS('Custos de implantação'!$F$5:$F$204,'Custos de implantação'!$C$5:$C$204,$A15,'Custos de implantação'!$G$5:$G$204,"<>Cancelado") | C15: =IF($A$3=0,0,B15/$A$3) | D15: =COUNTIFS('Custos de implantação'!$C$5:$C$204,$A15)
A16: ='Custos de implantação'!$J$14 | B16: =SUMIFS('Custos de implantação'!$F$5:$F$204,'Custos de implantação'!$C$5:$C$204,$A16,'Custos de implantação'!$G$5:$G$204,"<>Cancelado") | C16: =IF($A$3=0,0,B16/$A$3) | D16: =COUNTIFS('Custos de implantação'!$C$5:$C$204,$A16)
A17: Total | B17: =SUM(B7:B16)
A18: POR TIPO DE GASTO
A19: Tipo | B19: Total | C19: % do total | D19: Nº
A20: ='Custos de implantação'!$K$5 | B20: =SUMIFS('Custos de implantação'!$F$5:$F$204,'Custos de implantação'!$D$5:$D$204,$A20,'Custos de implantação'!$G$5:$G$204,"<>Cancelado") | C20: =IF($A$3=0,0,B20/$A$3) | D20: =COUNTIFS('Custos de implantação'!$D$5:$D$204,$A20)
A21: ='Custos de implantação'!$K$6 | B21: =SUMIFS('Custos de implantação'!$F$5:$F$204,'Custos de implantação'!$D$5:$D$204,$A21,'Custos de implantação'!$G$5:$G$204,"<>Cancelado") | C21: =IF($A$3=0,0,B21/$A$3) | D21: =COUNTIFS('Custos de implantação'!$D$5:$D$204,$A21)
A22: ='Custos de implantação'!$K$7 | B22: =SUMIFS('Custos de implantação'!$F$5:$F$204,'Custos de implantação'!$D$5:$D$204,$A22,'Custos de implantação'!$G$5:$G$204,"<>Cancelado") | C22: =IF($A$3=0,0,B22/$A$3) | D22: =COUNTIFS('Custos de implantação'!$D$5:$D$204,$A22)
A23: ='Custos de implantação'!$K$8 | B23: =SUMIFS('Custos de implantação'!$F$5:$F$204,'Custos de implantação'!$D$5:$D$204,$A23,'Custos de implantação'!$G$5:$G$204,"<>Cancelado") | C23: =IF($A$3=0,0,B23/$A$3) | D23: =COUNTIFS('Custos de implantação'!$D$5:$D$204,$A23)
A24: ='Custos de implantação'!$K$9 | B24: =SUMIFS('Custos de implantação'!$F$5:$F$204,'Custos de implantação'!$D$5:$D$204,$A24,'Custos de implantação'!$G$5:$G$204,"<>Cancelado") | C24: =IF($A$3=0,0,B24/$A$3) | D24: =COUNTIFS('Custos de implantação'!$D$5:$D$204,$A24)
A25: ='Custos de implantação'!$K$10 | B25: =SUMIFS('Custos de implantação'!$F$5:$F$204,'Custos de implantação'!$D$5:$D$204,$A25,'Custos de implantação'!$G$5:$G$204,"<>Cancelado") | C25: =IF($A$3=0,0,B25/$A$3) | D25: =COUNTIFS('Custos de implantação'!$D$5:$D$204,$A25)
A26: ='Custos de implantação'!$K$11 | B26: =SUMIFS('Custos de implantação'!$F$5:$F$204,'Custos de implantação'!$D$5:$D$204,$A26,'Custos de implantação'!$G$5:$G$204,"<>Cancelado") | C26: =IF($A$3=0,0,B26/$A$3) | D26: =COUNTIFS('Custos de implantação'!$D$5:$D$204,$A26)
A27: ='Custos de implantação'!$K$12 | B27: =SUMIFS('Custos de implantação'!$F$5:$F$204,'Custos de implantação'!$D$5:$D$204,$A27,'Custos de implantação'!$G$5:$G$204,"<>Cancelado") | C27: =IF($A$3=0,0,B27/$A$3) | D27: =COUNTIFS('Custos de implantação'!$D$5:$D$204,$A27)
A29: CATEGORIA × TIPO
A30: Categoria \ Tipo | B30: Material | C30: Mão de obra | D30: Serviço | E30: Compra | F30: Licença/Taxa | G30: Consultoria | H30: Software | I30: Outros
A31: ='Custos de implantação'!$J$5 | B31: =SUMIFS('Custos de implantação'!$F$5:$F$204,'Custos de implantação'!$C$5:$C$204,$A31,'Custos de implantação'!$D$5:$D$204,B$30,'Custos de implantação'!$G$5:$G$204,"<>Cancelado") | C31: =SUMIFS('Custos de implantação'!$F$5:$F$204,'Custos de implantação'!$C$5:$C$204,$A31,'Custos de implantação'!$D$5:$D$204,C$30,'Custos de implantação'!$G$5:$G$204,"<>Cancelado") | D31: =SUMIFS('Custos de implantação'!$F$5:$F$204,'Custos de implantação'!$C$5:$C$204,$A31,'Custos de implantação'!$D$5:$D$204,D$30,'Custos de implantação'!$G$5:$G$204,"<>Cancelado") | E31: =SUMIFS('Custos de implantação'!$F$5:$F$204,'Custos de implantação'!$C$5:$C$204,$A31,'Custos de implantação'!$D$5:$D$204,E$30,'Custos de implantação'!$G$5:$G$204,"<>Cancelado") | F31: =SUMIFS('Custos de implantação'!$F$5:$F$204,'Custos de implantação'!$C$5:$C$204,$A31,'Custos de implantação'!$D$5:$D$204,F$30,'Custos de implantação'!$G$5:$G$204,"<>Cancelado") | G31: =SUMIFS('Custos de implantação'!$F$5:$F$204,'Custos de implantação'!$C$5:$C$204,$A31,'Custos de implantação'!$D$5:$D$204,G$30,'Custos de implantação'!$G$5:$G$204,"<>Cancelado") | H31: =SUMIFS('Custos de implantação'!$F$5:$F$204,'Custos de implantação'!$C$5:$C$204,$A31,'Custos de implantação'!$D$5:$D$204,H$30,'Custos de implantação'!$G$5:$G$204,"<>Cancelado") | I31: =SUMIFS('Custos de implantação'!$F$5:$F$204,'Custos de implantação'!$C$5:$C$204,$A31,'Custos de implantação'!$D$5:$D$204,I$30,'Custos de implantação'!$G$5:$G$204,"<>Cancelado")
A32: ='Custos de implantação'!$J$6 | B32: =SUMIFS('Custos de implantação'!$F$5:$F$204,'Custos de implantação'!$C$5:$C$204,$A32,'Custos de implantação'!$D$5:$D$204,B$30,'Custos de implantação'!$G$5:$G$204,"<>Cancelado") | C32: =SUMIFS('Custos de implantação'!$F$5:$F$204,'Custos de implantação'!$C$5:$C$204,$A32,'Custos de implantação'!$D$5:$D$204,C$30,'Custos de implantação'!$G$5:$G$204,"<>Cancelado") | D32: =SUMIFS('Custos de implantação'!$F$5:$F$204,'Custos de implantação'!$C$5:$C$204,$A32,'Custos de implantação'!$D$5:$D$204,D$30,'Custos de implantação'!$G$5:$G$204,"<>Cancelado") | E32: =SUMIFS('Custos de implantação'!$F$5:$F$204,'Custos de implantação'!$C$5:$C$204,$A32,'Custos de implantação'!$D$5:$D$204,E$30,'Custos de implantação'!$G$5:$G$204,"<>Cancelado") | F32: =SUMIFS('Custos de implantação'!$F$5:$F$204,'Custos de implantação'!$C$5:$C$204,$A32,'Custos de implantação'!$D$5:$D$204,F$30,'Custos de implantação'!$G$5:$G$204,"<>Cancelado") | G32: =SUMIFS('Custos de implantação'!$F$5:$F$204,'Custos de implantação'!$C$5:$C$204,$A32,'Custos de implantação'!$D$5:$D$204,G$30,'Custos de implantação'!$G$5:$G$204,"<>Cancelado") | H32: =SUMIFS('Custos de implantação'!$F$5:$F$204,'Custos de implantação'!$C$5:$C$204,$A32,'Custos de implantação'!$D$5:$D$204,H$30,'Custos de implantação'!$G$5:$G$204,"<>Cancelado") | I32: =SUMIFS('Custos de implantação'!$F$5:$F$204,'Custos de implantação'!$C$5:$C$204,$A32,'Custos de implantação'!$D$5:$D$204,I$30,'Custos de implantação'!$G$5:$G$204,"<>Cancelado")
A33: ='Custos de implantação'!$J$7 | B33: =SUMIFS('Custos de implantação'!$F$5:$F$204,'Custos de implantação'!$C$5:$C$204,$A33,'Custos de implantação'!$D$5:$D$204,B$30,'Custos de implantação'!$G$5:$G$204,"<>Cancelado") | C33: =SUMIFS('Custos de implantação'!$F$5:$F$204,'Custos de implantação'!$C$5:$C$204,$A33,'Custos de implantação'!$D$5:$D$204,C$30,'Custos de implantação'!$G$5:$G$204,"<>Cancelado") | D33: =SUMIFS('Custos de implantação'!$F$5:$F$204,'Custos de implantação'!$C$5:$C$204,$A33,'Custos de implantação'!$D$5:$D$204,D$30,'Custos de implantação'!$G$5:$G$204,"<>Cancelado") | E33: =SUMIFS('Custos de implantação'!$F$5:$F$204,'Custos de implantação'!$C$5:$C$204,$A33,'Custos de implantação'!$D$5:$D$204,E$30,'Custos de implantação'!$G$5:$G$204,"<>Cancelado") | F33: =SUMIFS('Custos de implantação'!$F$5:$F$204,'Custos de implantação'!$C$5:$C$204,$A33,'Custos de implantação'!$D$5:$D$204,F$30,'Custos de implantação'!$G$5:$G$204,"<>Cancelado") | G33: =SUMIFS('Custos de implantação'!$F$5:$F$204,'Custos de implantação'!$C$5:$C$204,$A33,'Custos de implantação'!$D$5:$D$204,G$30,'Custos de implantação'!$G$5:$G$204,"<>Cancelado") | H33: =SUMIFS('Custos de implantação'!$F$5:$F$204,'Custos de implantação'!$C$5:$C$204,$A33,'Custos de implantação'!$D$5:$D$204,H$30,'Custos de implantação'!$G$5:$G$204,"<>Cancelado") | I33: =SUMIFS('Custos de implantação'!$F$5:$F$204,'Custos de implantação'!$C$5:$C$204,$A33,'Custos de implantação'!$D$5:$D$204,I$30,'Custos de implantação'!$G$5:$G$204,"<>Cancelado")
A34: ='Custos de implantação'!$J$8 | B34: =SUMIFS('Custos de implantação'!$F$5:$F$204,'Custos de implantação'!$C$5:$C$204,$A34,'Custos de implantação'!$D$5:$D$204,B$30,'Custos de implantação'!$G$5:$G$204,"<>Cancelado") | C34: =SUMIFS('Custos de implantação'!$F$5:$F$204,'Custos de implantação'!$C$5:$C$204,$A34,'Custos de implantação'!$D$5:$D$204,C$30,'Custos de implantação'!$G$5:$G$204,"<>Cancelado") | D34: =SUMIFS('Custos de implantação'!$F$5:$F$204,'Custos de implantação'!$C$5:$C$204,$A34,'Custos de implantação'!$D$5:$D$204,D$30,'Custos de implantação'!$G$5:$G$204,"<>Cancelado") | E34: =SUMIFS('Custos de implantação'!$F$5:$F$204,'Custos de implantação'!$C$5:$C$204,$A34,'Custos de implantação'!$D$5:$D$204,E$30,'Custos de implantação'!$G$5:$G$204,"<>Cancelado") | F34: =SUMIFS('Custos de implantação'!$F$5:$F$204,'Custos de implantação'!$C$5:$C$204,$A34,'Custos de implantação'!$D$5:$D$204,F$30,'Custos de implantação'!$G$5:$G$204,"<>Cancelado") | G34: =SUMIFS('Custos de implantação'!$F$5:$F$204,'Custos de implantação'!$C$5:$C$204,$A34,'Custos de implantação'!$D$5:$D$204,G$30,'Custos de implantação'!$G$5:$G$204,"<>Cancelado") | H34: =SUMIFS('Custos de implantação'!$F$5:$F$204,'Custos de implantação'!$C$5:$C$204,$A34,'Custos de implantação'!$D$5:$D$204,H$30,'Custos de implantação'!$G$5:$G$204,"<>Cancelado") | I34: =SUMIFS('Custos de implantação'!$F$5:$F$204,'Custos de implantação'!$C$5:$C$204,$A34,'Custos de implantação'!$D$5:$D$204,I$30,'Custos de implantação'!$G$5:$G$204,"<>Cancelado")
A35: ='Custos de implantação'!$J$9 | B35: =SUMIFS('Custos de implantação'!$F$5:$F$204,'Custos de implantação'!$C$5:$C$204,$A35,'Custos de implantação'!$D$5:$D$204,B$30,'Custos de implantação'!$G$5:$G$204,"<>Cancelado") | C35: =SUMIFS('Custos de implantação'!$F$5:$F$204,'Custos de implantação'!$C$5:$C$204,$A35,'Custos de implantação'!$D$5:$D$204,C$30,'Custos de implantação'!$G$5:$G$204,"<>Cancelado") | D35: =SUMIFS('Custos de implantação'!$F$5:$F$204,'Custos de implantação'!$C$5:$C$204,$A35,'Custos de implantação'!$D$5:$D$204,D$30,'Custos de implantação'!$G$5:$G$204,"<>Cancelado") | E35: =SUMIFS('Custos de implantação'!$F$5:$F$204,'Custos de implantação'!$C$5:$C$204,$A35,'Custos de implantação'!$D$5:$D$204,E$30,'Custos de implantação'!$G$5:$G$204,"<>Cancelado") | F35: =SUMIFS('Custos de implantação'!$F$5:$F$204,'Custos de implantação'!$C$5:$C$204,$A35,'Custos de implantação'!$D$5:$D$204,F$30,'Custos de implantação'!$G$5:$G$204,"<>Cancelado") | G35: =SUMIFS('Custos de implantação'!$F$5:$F$204,'Custos de implantação'!$C$5:$C$204,$A35,'Custos de implantação'!$D$5:$D$204,G$30,'Custos de implantação'!$G$5:$G$204,"<>Cancelado") | H35: =SUMIFS('Custos de implantação'!$F$5:$F$204,'Custos de implantação'!$C$5:$C$204,$A35,'Custos de implantação'!$D$5:$D$204,H$30,'Custos de implantação'!$G$5:$G$204,"<>Cancelado") | I35: =SUMIFS('Custos de implantação'!$F$5:$F$204,'Custos de implantação'!$C$5:$C$204,$A35,'Custos de implantação'!$D$5:$D$204,I$30,'Custos de implantação'!$G$5:$G$204,"<>Cancelado")
A36: ='Custos de implantação'!$J$10 | B36: =SUMIFS('Custos de implantação'!$F$5:$F$204,'Custos de implantação'!$C$5:$C$204,$A36,'Custos de implantação'!$D$5:$D$204,B$30,'Custos de implantação'!$G$5:$G$204,"<>Cancelado") | C36: =SUMIFS('Custos de implantação'!$F$5:$F$204,'Custos de implantação'!$C$5:$C$204,$A36,'Custos de implantação'!$D$5:$D$204,C$30,'Custos de implantação'!$G$5:$G$204,"<>Cancelado") | D36: =SUMIFS('Custos de implantação'!$F$5:$F$204,'Custos de implantação'!$C$5:$C$204,$A36,'Custos de implantação'!$D$5:$D$204,D$30,'Custos de implantação'!$G$5:$G$204,"<>Cancelado") | E36: =SUMIFS('Custos de implantação'!$F$5:$F$204,'Custos de implantação'!$C$5:$C$204,$A36,'Custos de implantação'!$D$5:$D$204,E$30,'Custos de implantação'!$G$5:$G$204,"<>Cancelado") | F36: =SUMIFS('Custos de implantação'!$F$5:$F$204,'Custos de implantação'!$C$5:$C$204,$A36,'Custos de implantação'!$D$5:$D$204,F$30,'Custos de implantação'!$G$5:$G$204,"<>Cancelado") | G36: =SUMIFS('Custos de implantação'!$F$5:$F$204,'Custos de implantação'!$C$5:$C$204,$A36,'Custos de implantação'!$D$5:$D$204,G$30,'Custos de implantação'!$G$5:$G$204,"<>Cancelado") | H36: =SUMIFS('Custos de implantação'!$F$5:$F$204,'Custos de implantação'!$C$5:$C$204,$A36,'Custos de implantação'!$D$5:$D$204,H$30,'Custos de implantação'!$G$5:$G$204,"<>Cancelado") | I36: =SUMIFS('Custos de implantação'!$F$5:$F$204,'Custos de implantação'!$C$5:$C$204,$A36,'Custos de implantação'!$D$5:$D$204,I$30,'Custos de implantação'!$G$5:$G$204,"<>Cancelado")
A37: ='Custos de implantação'!$J$11 | B37: =SUMIFS('Custos de implantação'!$F$5:$F$204,'Custos de implantação'!$C$5:$C$204,$A37,'Custos de implantação'!$D$5:$D$204,B$30,'Custos de implantação'!$G$5:$G$204,"<>Cancelado") | C37: =SUMIFS('Custos de implantação'!$F$5:$F$204,'Custos de implantação'!$C$5:$C$204,$A37,'Custos de implantação'!$D$5:$D$204,C$30,'Custos de implantação'!$G$5:$G$204,"<>Cancelado") | D37: =SUMIFS('Custos de implantação'!$F$5:$F$204,'Custos de implantação'!$C$5:$C$204,$A37,'Custos de implantação'!$D$5:$D$204,D$30,'Custos de implantação'!$G$5:$G$204,"<>Cancelado") | E37: =SUMIFS('Custos de implantação'!$F$5:$F$204,'Custos de implantação'!$C$5:$C$204,$A37,'Custos de implantação'!$D$5:$D$204,E$30,'Custos de implantação'!$G$5:$G$204,"<>Cancelado") | F37: =SUMIFS('Custos de implantação'!$F$5:$F$204,'Custos de implantação'!$C$5:$C$204,$A37,'Custos de implantação'!$D$5:$D$204,F$30,'Custos de implantação'!$G$5:$G$204,"<>Cancelado") | G37: =SUMIFS('Custos de implantação'!$F$5:$F$204,'Custos de implantação'!$C$5:$C$204,$A37,'Custos de implantação'!$D$5:$D$204,G$30,'Custos de implantação'!$G$5:$G$204,"<>Cancelado") | H37: =SUMIFS('Custos de implantação'!$F$5:$F$204,'Custos de implantação'!$C$5:$C$204,$A37,'Custos de implantação'!$D$5:$D$204,H$30,'Custos de implantação'!$G$5:$G$204,"<>Cancelado") | I37: =SUMIFS('Custos de implantação'!$F$5:$F$204,'Custos de implantação'!$C$5:$C$204,$A37,'Custos de implantação'!$D$5:$D$204,I$30,'Custos de implantação'!$G$5:$G$204,"<>Cancelado")
A38: ='Custos de implantação'!$J$12 | B38: =SUMIFS('Custos de implantação'!$F$5:$F$204,'Custos de implantação'!$C$5:$C$204,$A38,'Custos de implantação'!$D$5:$D$204,B$30,'Custos de implantação'!$G$5:$G$204,"<>Cancelado") | C38: =SUMIFS('Custos de implantação'!$F$5:$F$204,'Custos de implantação'!$C$5:$C$204,$A38,'Custos de implantação'!$D$5:$D$204,C$30,'Custos de implantação'!$G$5:$G$204,"<>Cancelado") | D38: =SUMIFS('Custos de implantação'!$F$5:$F$204,'Custos de implantação'!$C$5:$C$204,$A38,'Custos de implantação'!$D$5:$D$204,D$30,'Custos de implantação'!$G$5:$G$204,"<>Cancelado") | E38: =SUMIFS('Custos de implantação'!$F$5:$F$204,'Custos de implantação'!$C$5:$C$204,$A38,'Custos de implantação'!$D$5:$D$204,E$30,'Custos de implantação'!$G$5:$G$204,"<>Cancelado") | F38: =SUMIFS('Custos de implantação'!$F$5:$F$204,'Custos de implantação'!$C$5:$C$204,$A38,'Custos de implantação'!$D$5:$D$204,F$30,'Custos de implantação'!$G$5:$G$204,"<>Cancelado") | G38: =SUMIFS('Custos de implantação'!$F$5:$F$204,'Custos de implantação'!$C$5:$C$204,$A38,'Custos de implantação'!$D$5:$D$204,G$30,'Custos de implantação'!$G$5:$G$204,"<>Cancelado") | H38: =SUMIFS('Custos de implantação'!$F$5:$F$204,'Custos de implantação'!$C$5:$C$204,$A38,'Custos de implantação'!$D$5:$D$204,H$30,'Custos de implantação'!$G$5:$G$204,"<>Cancelado") | I38: =SUMIFS('Custos de implantação'!$F$5:$F$204,'Custos de implantação'!$C$5:$C$204,$A38,'Custos de implantação'!$D$5:$D$204,I$30,'Custos de implantação'!$G$5:$G$204,"<>Cancelado")
A39: ='Custos de implantação'!$J$13 | B39: =SUMIFS('Custos de implantação'!$F$5:$F$204,'Custos de implantação'!$C$5:$C$204,$A39,'Custos de implantação'!$D$5:$D$204,B$30,'Custos de implantação'!$G$5:$G$204,"<>Cancelado") | C39: =SUMIFS('Custos de implantação'!$F$5:$F$204,'Custos de implantação'!$C$5:$C$204,$A39,'Custos de implantação'!$D$5:$D$204,C$30,'Custos de implantação'!$G$5:$G$204,"<>Cancelado") | D39: =SUMIFS('Custos de implantação'!$F$5:$F$204,'Custos de implantação'!$C$5:$C$204,$A39,'Custos de implantação'!$D$5:$D$204,D$30,'Custos de implantação'!$G$5:$G$204,"<>Cancelado") | E39: =SUMIFS('Custos de implantação'!$F$5:$F$204,'Custos de implantação'!$C$5:$C$204,$A39,'Custos de implantação'!$D$5:$D$204,E$30,'Custos de implantação'!$G$5:$G$204,"<>Cancelado") | F39: =SUMIFS('Custos de implantação'!$F$5:$F$204,'Custos de implantação'!$C$5:$C$204,$A39,'Custos de implantação'!$D$5:$D$204,F$30,'Custos de implantação'!$G$5:$G$204,"<>Cancelado") | G39: =SUMIFS('Custos de implantação'!$F$5:$F$204,'Custos de implantação'!$C$5:$C$204,$A39,'Custos de implantação'!$D$5:$D$204,G$30,'Custos de implantação'!$G$5:$G$204,"<>Cancelado") | H39: =SUMIFS('Custos de implantação'!$F$5:$F$204,'Custos de implantação'!$C$5:$C$204,$A39,'Custos de implantação'!$D$5:$D$204,H$30,'Custos de implantação'!$G$5:$G$204,"<>Cancelado") | I39: =SUMIFS('Custos de implantação'!$F$5:$F$204,'Custos de implantação'!$C$5:$C$204,$A39,'Custos de implantação'!$D$5:$D$204,I$30,'Custos de implantação'!$G$5:$G$204,"<>Cancelado")
A40: ='Custos de implantação'!$J$14 | B40: =SUMIFS('Custos de implantação'!$F$5:$F$204,'Custos de implantação'!$C$5:$C$204,$A40,'Custos de implantação'!$D$5:$D$204,B$30,'Custos de implantação'!$G$5:$G$204,"<>Cancelado") | C40: =SUMIFS('Custos de implantação'!$F$5:$F$204,'Custos de implantação'!$C$5:$C$204,$A40,'Custos de implantação'!$D$5:$D$204,C$30,'Custos de implantação'!$G$5:$G$204,"<>Cancelado") | D40: =SUMIFS('Custos de implantação'!$F$5:$F$204,'Custos de implantação'!$C$5:$C$204,$A40,'Custos de implantação'!$D$5:$D$204,D$30,'Custos de implantação'!$G$5:$G$204,"<>Cancelado") | E40: =SUMIFS('Custos de implantação'!$F$5:$F$204,'Custos de implantação'!$C$5:$C$204,$A40,'Custos de implantação'!$D$5:$D$204,E$30,'Custos de implantação'!$G$5:$G$204,"<>Cancelado") | F40: =SUMIFS('Custos de implantação'!$F$5:$F$204,'Custos de implantação'!$C$5:$C$204,$A40,'Custos de implantação'!$D$5:$D$204,F$30,'Custos de implantação'!$G$5:$G$204,"<>Cancelado") | G40: =SUMIFS('Custos de implantação'!$F$5:$F$204,'Custos de implantação'!$C$5:$C$204,$A40,'Custos de implantação'!$D$5:$D$204,G$30,'Custos de implantação'!$G$5:$G$204,"<>Cancelado") | H40: =SUMIFS('Custos de implantação'!$F$5:$F$204,'Custos de implantação'!$C$5:$C$204,$A40,'Custos de implantação'!$D$5:$D$204,H$30,'Custos de implantação'!$G$5:$G$204,"<>Cancelado") | I40: =SUMIFS('Custos de implantação'!$F$5:$F$204,'Custos de implantação'!$C$5:$C$204,$A40,'Custos de implantação'!$D$5:$D$204,I$30,'Custos de implantação'!$G$5:$G$204,"<>Cancelado")
A42: PAGO × PREVISTO
A43: Pago | B43: =SUMIFS('Custos de implantação'!$F$5:$F$204,'Custos de implantação'!$G$5:$G$204,$A43)
A44: Previsto | B44: =SUMIFS('Custos de implantação'!$F$5:$F$204,'Custos de implantação'!$G$5:$G$204,$A44)
A45: Cancelado | B45: =SUMIFS('Custos de implantação'!$F$5:$F$204,'Custos de implantação'!$G$5:$G$204,$A45)
A48: FLUXO MENSAL DA IMPLANTAÇÃO (com parcelamentos)
A49: Mês | B49: Desembolso | C49: Acumulado
A50: ='Custos de implantação'!$P$5 | B50: =SUMPRODUCT(('Custos de implantação'!$K$5:$K$204>=0)*('Custos de implantação'!$K$5:$K$204<=0)*('Custos de implantação'!$K$5:$K$204+'Custos de implantação'!$I$5:$I$204>0)*('Custos de implantação'!$G$5:$G$204<>"Cancelado")*'Custos de implantação'!$F$5:$F$204/('Custos de implantação'!$I$5:$I$204+('Custos de implantação'!$I$5:$I$204=0))) | C50: =B50
A51: ='Custos de implantação'!$P$6 | B51: =SUMPRODUCT(('Custos de implantação'!$K$5:$K$204>=0)*('Custos de implantação'!$K$5:$K$204<=1)*('Custos de implantação'!$K$5:$K$204+'Custos de implantação'!$I$5:$I$204>1)*('Custos de implantação'!$G$5:$G$204<>"Cancelado")*'Custos de implantação'!$F$5:$F$204/('Custos de implantação'!$I$5:$I$204+('Custos de implantação'!$I$5:$I$204=0))) | C51: =C50+B51
A52: ='Custos de implantação'!$P$7 | B52: =SUMPRODUCT(('Custos de implantação'!$K$5:$K$204>=0)*('Custos de implantação'!$K$5:$K$204<=2)*('Custos de implantação'!$K$5:$K$204+'Custos de implantação'!$I$5:$I$204>2)*('Custos de implantação'!$G$5:$G$204<>"Cancelado")*'Custos de implantação'!$F$5:$F$204/('Custos de implantação'!$I$5:$I$204+('Custos de implantação'!$I$5:$I$204=0))) | C52: =C51+B52
A53: ='Custos de implantação'!$P$8 | B53: =SUMPRODUCT(('Custos de implantação'!$K$5:$K$204>=0)*('Custos de implantação'!$K$5:$K$204<=3)*('Custos de implantação'!$K$5:$K$204+'Custos de implantação'!$I$5:$I$204>3)*('Custos de implantação'!$G$5:$G$204<>"Cancelado")*'Custos de implantação'!$F$5:$F$204/('Custos de implantação'!$I$5:$I$204+('Custos de implantação'!$I$5:$I$204=0))) | C53: =C52+B53
A54: ='Custos de implantação'!$P$9 | B54: =SUMPRODUCT(('Custos de implantação'!$K$5:$K$204>=0)*('Custos de implantação'!$K$5:$K$204<=4)*('Custos de implantação'!$K$5:$K$204+'Custos de implantação'!$I$5:$I$204>4)*('Custos de implantação'!$G$5:$G$204<>"Cancelado")*'Custos de implantação'!$F$5:$F$204/('Custos de implantação'!$I$5:$I$204+('Custos de implantação'!$I$5:$I$204=0))) | C54: =C53+B54
A55: ='Custos de implantação'!$P$10 | B55: =SUMPRODUCT(('Custos de implantação'!$K$5:$K$204>=0)*('Custos de implantação'!$K$5:$K$204<=5)*('Custos de implantação'!$K$5:$K$204+'Custos de implantação'!$I$5:$I$204>5)*('Custos de implantação'!$G$5:$G$204<>"Cancelado")*'Custos de implantação'!$F$5:$F$204/('Custos de implantação'!$I$5:$I$204+('Custos de implantação'!$I$5:$I$204=0))) | C55: =C54+B55
A56: ='Custos de implantação'!$P$11 | B56: =SUMPRODUCT(('Custos de implantação'!$K$5:$K$204>=0)*('Custos de implantação'!$K$5:$K$204<=6)*('Custos de implantação'!$K$5:$K$204+'Custos de implantação'!$I$5:$I$204>6)*('Custos de implantação'!$G$5:$G$204<>"Cancelado")*'Custos de implantação'!$F$5:$F$204/('Custos de implantação'!$I$5:$I$204+('Custos de implantação'!$I$5:$I$204=0))) | C56: =C55+B56
A57: ='Custos de implantação'!$P$12 | B57: =SUMPRODUCT(('Custos de implantação'!$K$5:$K$204>=0)*('Custos de implantação'!$K$5:$K$204<=7)*('Custos de implantação'!$K$5:$K$204+'Custos de implantação'!$I$5:$I$204>7)*('Custos de implantação'!$G$5:$G$204<>"Cancelado")*'Custos de implantação'!$F$5:$F$204/('Custos de implantação'!$I$5:$I$204+('Custos de implantação'!$I$5:$I$204=0))) | C57: =C56+B57
A58: ='Custos de implantação'!$P$13 | B58: =SUMPRODUCT(('Custos de implantação'!$K$5:$K$204>=0)*('Custos de implantação'!$K$5:$K$204<=8)*('Custos de implantação'!$K$5:$K$204+'Custos de implantação'!$I$5:$I$204>8)*('Custos de implantação'!$G$5:$G$204<>"Cancelado")*'Custos de implantação'!$F$5:$F$204/('Custos de implantação'!$I$5:$I$204+('Custos de implantação'!$I$5:$I$204=0))) | C58: =C57+B58
A59: ='Custos de implantação'!$P$14 | B59: =SUMPRODUCT(('Custos de implantação'!$K$5:$K$204>=0)*('Custos de implantação'!$K$5:$K$204<=9)*('Custos de implantação'!$K$5:$K$204+'Custos de implantação'!$I$5:$I$204>9)*('Custos de implantação'!$G$5:$G$204<>"Cancelado")*'Custos de implantação'!$F$5:$F$204/('Custos de implantação'!$I$5:$I$204+('Custos de implantação'!$I$5:$I$204=0))) | C59: =C58+B59
A60: ='Custos de implantação'!$P$15 | B60: =SUMPRODUCT(('Custos de implantação'!$K$5:$K$204>=0)*('Custos de implantação'!$K$5:$K$204<=10)*('Custos de implantação'!$K$5:$K$204+'Custos de implantação'!$I$5:$I$204>10)*('Custos de implantação'!$G$5:$G$204<>"Cancelado")*'Custos de implantação'!$F$5:$F$204/('Custos de implantação'!$I$5:$I$204+('Custos de implantação'!$I$5:$I$204=0))) | C60: =C59+B60
A61: ='Custos de implantação'!$P$16 | B61: =SUMPRODUCT(('Custos de implantação'!$K$5:$K$204>=0)*('Custos de implantação'!$K$5:$K$204<=11)*('Custos de implantação'!$K$5:$K$204+'Custos de implantação'!$I$5:$I$204>11)*('Custos de implantação'!$G$5:$G$204<>"Cancelado")*'Custos de implantação'!$F$5:$F$204/('Custos de implantação'!$I$5:$I$204+('Custos de implantação'!$I$5:$I$204=0))) | C61: =C60+B61
A62: ='Custos de implantação'!$P$17 | B62: =SUMPRODUCT(('Custos de implantação'!$K$5:$K$204>=0)*('Custos de implantação'!$K$5:$K$204<=12)*('Custos de implantação'!$K$5:$K$204+'Custos de implantação'!$I$5:$I$204>12)*('Custos de implantação'!$G$5:$G$204<>"Cancelado")*'Custos de implantação'!$F$5:$F$204/('Custos de implantação'!$I$5:$I$204+('Custos de implantação'!$I$5:$I$204=0))) | C62: =C61+B62
A63: ='Custos de implantação'!$P$18 | B63: =SUMPRODUCT(('Custos de implantação'!$K$5:$K$204>=0)*('Custos de implantação'!$K$5:$K$204<=13)*('Custos de implantação'!$K$5:$K$204+'Custos de implantação'!$I$5:$I$204>13)*('Custos de implantação'!$G$5:$G$204<>"Cancelado")*'Custos de implantação'!$F$5:$F$204/('Custos de implantação'!$I$5:$I$204+('Custos de implantação'!$I$5:$I$204=0))) | C63: =C62+B63
A64: ='Custos de implantação'!$P$19 | B64: =SUMPRODUCT(('Custos de implantação'!$K$5:$K$204>=0)*('Custos de implantação'!$K$5:$K$204<=14)*('Custos de implantação'!$K$5:$K$204+'Custos de implantação'!$I$5:$I$204>14)*('Custos de implantação'!$G$5:$G$204<>"Cancelado")*'Custos de implantação'!$F$5:$F$204/('Custos de implantação'!$I$5:$I$204+('Custos de implantação'!$I$5:$I$204=0))) | C64: =C63+B64
A65: ='Custos de implantação'!$P$20 | B65: =SUMPRODUCT(('Custos de implantação'!$K$5:$K$204>=0)*('Custos de implantação'!$K$5:$K$204<=15)*('Custos de implantação'!$K$5:$K$204+'Custos de implantação'!$I$5:$I$204>15)*('Custos de implantação'!$G$5:$G$204<>"Cancelado")*'Custos de implantação'!$F$5:$F$204/('Custos de implantação'!$I$5:$I$204+('Custos de implantação'!$I$5:$I$204=0))) | C65: =C64+B65
A66: ='Custos de implantação'!$P$21 | B66: =SUMPRODUCT(('Custos de implantação'!$K$5:$K$204>=0)*('Custos de implantação'!$K$5:$K$204<=16)*('Custos de implantação'!$K$5:$K$204+'Custos de implantação'!$I$5:$I$204>16)*('Custos de implantação'!$G$5:$G$204<>"Cancelado")*'Custos de implantação'!$F$5:$F$204/('Custos de implantação'!$I$5:$I$204+('Custos de implantação'!$I$5:$I$204=0))) | C66: =C65+B66
A67: ='Custos de implantação'!$P$22 | B67: =SUMPRODUCT(('Custos de implantação'!$K$5:$K$204>=0)*('Custos de implantação'!$K$5:$K$204<=17)*('Custos de implantação'!$K$5:$K$204+'Custos de implantação'!$I$5:$I$204>17)*('Custos de implantação'!$G$5:$G$204<>"Cancelado")*'Custos de implantação'!$F$5:$F$204/('Custos de implantação'!$I$5:$I$204+('Custos de implantação'!$I$5:$I$204=0))) | C67: =C66+B67
A68: ='Custos de implantação'!$P$23 | B68: =SUMPRODUCT(('Custos de implantação'!$K$5:$K$204>=0)*('Custos de implantação'!$K$5:$K$204<=18)*('Custos de implantação'!$K$5:$K$204+'Custos de implantação'!$I$5:$I$204>18)*('Custos de implantação'!$G$5:$G$204<>"Cancelado")*'Custos de implantação'!$F$5:$F$204/('Custos de implantação'!$I$5:$I$204+('Custos de implantação'!$I$5:$I$204=0))) | C68: =C67+B68
A69: Cada gasto entra do mês de início até o fim das parcelas — ex.: R$ 8.000 em 4x a partir de Set/26 = R$ 2.000/mês de set a dez.
A70: Tudo se atualiza sozinho conforme você lança na aba 'Custos de implantação'.

Sheet Painel do mês
A1: PAINEL DO MÊS — escolha o período e acompanhe
A2: Período (0 = out em obras … 2 = dez/M1 … 17 = mar/M16) | B2: 4 | C2: =INDEX({"Out (obras)","Nov (obras)","Dez (M1)","Jan (M2)","Fev (M3)","Mar (M4)","Abr (M5)","Mai (M6)","Jun (M7)","Jul (M8)","Ago (M9)","Set (M10)","Out (M11)","Nov (M12)","Dez (M13)","Jan (M14)","Fev (M15)","Mar (M16)"},$B$2+1)
A4: Indicador | B4: Plano | C4: Realizado | D4: Desvio
A5: Alunos ativos | B5: =INDEX('Cenário Moderado'!$B$7:$S$7,$B$2+1) | C5: =INDEX(Realizado!$B$2:$S$2,$B$2+1) | D5: =INDEX(Realizado!$B$2:$S$2,$B$2+1)-INDEX('Cenário Moderado'!$B$7:$S$7,$B$2+1)
A6: Matrículas no mês | B6: =INDEX('Cenário Moderado'!$B$4:$S$4,$B$2+1) | C6: =INDEX(Realizado!$B$3:$S$3,$B$2+1) | D6: =INDEX(Realizado!$B$3:$S$3,$B$2+1)-INDEX('Cenário Moderado'!$B$4:$S$4,$B$2+1)
A7: Receita recebida | B7: =INDEX('Cenário Moderado'!$B$15:$S$15,$B$2+1) | C7: =INDEX(Realizado!$B$11:$S$11,$B$2+1) | D7: =INDEX(Realizado!$B$11:$S$11,$B$2+1)-INDEX('Cenário Moderado'!$B$15:$S$15,$B$2+1)
A8: Impostos | B8: =INDEX('Cenário Moderado'!$B$23:$S$23,$B$2+1) | C8: =INDEX(Realizado!$B$14:$S$14,$B$2+1) | D8: =INDEX(Realizado!$B$14:$S$14,$B$2+1)-INDEX('Cenário Moderado'!$B$23:$S$23,$B$2+1)
A9: Folha + encargos mensais | B9: =INDEX('Cenário Moderado'!$B$27:$S$27,$B$2+1) | C9: =INDEX(Realizado!$B$17:$S$17,$B$2+1) | D9: =INDEX(Realizado!$B$17:$S$17,$B$2+1)-INDEX('Cenário Moderado'!$B$27:$S$27,$B$2+1)
A10: 13º e férias | B10: =INDEX('Cenário Moderado'!$B$29:$S$29,$B$2+1) | C10: =INDEX(Realizado!$B$19:$S$19,$B$2+1) | D10: =INDEX(Realizado!$B$19:$S$19,$B$2+1)-INDEX('Cenário Moderado'!$B$29:$S$29,$B$2+1)
A11: Professores | B11: =INDEX('Cenário Moderado'!$B$30:$S$30,$B$2+1) | C11: =INDEX(Realizado!$B$20:$S$20,$B$2+1) | D11: =INDEX(Realizado!$B$20:$S$20,$B$2+1)-INDEX('Cenário Moderado'!$B$30:$S$30,$B$2+1)
A12: Total de despesas | B12: =INDEX('Cenário Moderado'!$B$46:$S$46,$B$2+1) | C12: =INDEX(Realizado!$B$37:$S$37,$B$2+1) | D12: =INDEX(Realizado!$B$37:$S$37,$B$2+1)-INDEX('Cenário Moderado'!$B$46:$S$46,$B$2+1)
A13: Resultado do mês | B13: =INDEX('Cenário Moderado'!$B$48:$S$48,$B$2+1) | C13: =INDEX(Realizado!$B$39:$S$39,$B$2+1) | D13: =INDEX(Realizado!$B$39:$S$39,$B$2+1)-INDEX('Cenário Moderado'!$B$48:$S$48,$B$2+1)
A14: Caixa acumulado | B14: =INDEX('Cenário Moderado'!$B$49:$S$49,$B$2+1) | C14: =INDEX(Realizado!$B$40:$S$40,$B$2+1) | D14: =INDEX(Realizado!$B$40:$S$40,$B$2+1)-INDEX('Cenário Moderado'!$B$49:$S$49,$B$2+1)
A16: ALERTAS
A17: Ocupação das salas | B17: =INDEX('Cenário Moderado'!$B$9:$S$9,$B$2+1) | C17: =IF(INDEX('Cenário Moderado'!$B$9:$S$9,$B$2+1)>1,"🔴 A grade não cabe nas salas",IF(INDEX('Cenário Moderado'!$B$9:$S$9,$B$2+1)>0.85,"🟡 Grade quase cheia","🟢 Folga na grade"))
A18: Caixa acumulado do plano | B18: =INDEX('Cenário Moderado'!$B$49:$S$49,$B$2+1) | C18: =IF(INDEX('Cenário Moderado'!$B$49:$S$49,$B$2+1)<0,"🔴 Caixa negativo — precisa de capital de giro","🟢 Caixa positivo")
A19: Alunos vs break-even | B19: =INDEX('Cenário Moderado'!$B$7:$S$7,$B$2+1) | C19: =IF(INDEX('Cenário Moderado'!$B$7:$S$7,$B$2+1)>=Premissas!$B$90,"🟢 Acima do break-even","🔴 Abaixo do break-even de "&Premissas!$B$90&" alunos")
A20: Custos de implantação lançados | B20: ='Análise de custos'!A3 | C20: =IF('Análise de custos'!C3>0,"🔴 Estourou o orçado no CAPEX em "&TEXT('Análise de custos'!C3,"R$ #,##0"),"🟢 Dentro do orçado")
A22: Plano = Cenário Moderado. Realizado = o que você lançou. Meses não lançados aparecem com desvio negativo cheio.

Sheet Investimento (CAPEX)
A1: Categoria | B1: Item | C1: Qtd | D1: Preço | E1: Total | F1: Obs
A2: 1) Reforma dos banheiros
A3: Construção | B3: Blocos/tijolos | D3: 800 | E3: =IF(OR(C3="",D3=""),IF(D3="",0,D3),C3*D3) | F3: ⚠ ESTIMATIVA — trocar por orçamento
A4: Construção | B4: Cimento | D4: 600 | E4: =IF(OR(C4="",D4=""),IF(D4="",0,D4),C4*D4) | F4: ⚠ ESTIMATIVA — trocar por orçamento
A5: Construção | B5: Areia | D5: 400 | E5: =IF(OR(C5="",D5=""),IF(D5="",0,D5),C5*D5) | F5: ⚠ ESTIMATIVA — trocar por orçamento
A6: Construção | B6: Argamassa | D6: 500 | E6: =IF(OR(C6="",D6=""),IF(D6="",0,D6),C6*D6) | F6: ⚠ ESTIMATIVA — trocar por orçamento
A7: Construção | B7: Impermeabilizante | D7: 900 | E7: =IF(OR(C7="",D7=""),IF(D7="",0,D7),C7*D7) | F7: ⚠ ESTIMATIVA — trocar por orçamento
A8: Construção | B8: Rejunte | D8: 300 | E8: =IF(OR(C8="",D8=""),IF(D8="",0,D8),C8*D8) | F8: ⚠ ESTIMATIVA — trocar por orçamento
A9: Construção | B9: Portas | C9: 6 | D9: 900 | E9: =IF(OR(C9="",D9=""),IF(D9="",0,D9),C9*D9) | F9: 3 banheiros térreos, 2 mezanino, 1 interno
A10: Construção | B10: Batentes | D10: 1200 | E10: =IF(OR(C10="",D10=""),IF(D10="",0,D10),C10*D10) | F10: ⚠ ESTIMATIVA — trocar por orçamento
A11: Construção | B11: Fechaduras/trincos | C11: 6 | D11: 200 | E11: =IF(OR(C11="",D11=""),IF(D11="",0,D11),C11*D11)
A12: Demolição | B12: Demolição | D12: 2500 | E12: =IF(OR(C12="",D12=""),IF(D12="",0,D12),C12*D12) | F12: ⚠ ESTIMATIVA — trocar por orçamento
A13: Demolição | B13: Retirada de entulho | D13: 800 | E13: =IF(OR(C13="",D13=""),IF(D13="",0,D13),C13*D13) | F13: ⚠ ESTIMATIVA — trocar por orçamento
A14: Demolição | B14: Caçamba | C14: 1 | D14: 450 | E14: =IF(OR(C14="",D14=""),IF(D14="",0,D14),C14*D14)
A15: Hidráulica | B15: Tubos, conexões, registros, válvulas | D15: 2500 | E15: =IF(OR(C15="",D15=""),IF(D15="",0,D15),C15*D15) | F15: ⚠ ESTIMATIVA — trocar por orçamento
A16: Hidráulica | B16: Encanador | D16: 3500 | E16: =IF(OR(C16="",D16=""),IF(D16="",0,D16),C16*D16) | F16: ⚠ ESTIMATIVA — trocar por orçamento
A17: Louças | B17: Vasos sanitários | C17: 5 | D17: 700 | E17: =IF(OR(C17="",D17=""),IF(D17="",0,D17),C17*D17)
A18: Louças | B18: Assentos sanitários | C18: 6 | D18: 120 | E18: =IF(OR(C18="",D18=""),IF(D18="",0,D18),C18*D18)
A19: Louças | B19: Pias/cubas | C19: 3 | D19: 450 | E19: =IF(OR(C19="",D19=""),IF(D19="",0,D19),C19*D19)
A20: Louças | B20: Torneiras | C20: 3 | D20: 220 | E20: =IF(OR(C20="",D20=""),IF(D20="",0,D20),C20*D20)
A21: Louças | B21: Chuveiros | C21: 1 | D21: 120 | E21: =IF(OR(C21="",D21=""),IF(D21="",0,D21),C21*D21)
A22: Louças | B22: Espelhos | C22: 3 | D22: 350 | E22: =IF(OR(C22="",D22=""),IF(D22="",0,D22),C22*D22)
A23: Louças | B23: Instalação de louças | D23: 1800 | E23: =IF(OR(C23="",D23=""),IF(D23="",0,D23),C23*D23) | F23: ⚠ ESTIMATIVA — trocar por orçamento
A24: Acessibilidade | B24: Vaso sanitário acessível | C24: 1 | D24: 1000 | E24: =IF(OR(C24="",D24=""),IF(D24="",0,D24),C24*D24)
A25: Acessibilidade | B25: Pia acessível | C25: 1 | D25: 700 | E25: =IF(OR(C25="",D25=""),IF(D25="",0,D25),C25*D25)
A26: Acessibilidade | B26: Barras de apoio | C26: 1 | D26: 500 | E26: =IF(OR(C26="",D26=""),IF(D26="",0,D26),C26*D26)
A27: Acessibilidade | B27: Corrimão | C27: 1 | D27: 800 | E27: =IF(OR(C27="",D27=""),IF(D27="",0,D27),C27*D27) | F27: ⚠ ESTIMATIVA — trocar por orçamento
A28: Acessibilidade | B28: Espelho + torneira acessíveis | C28: 1 | D28: 600 | E28: =IF(OR(C28="",D28=""),IF(D28="",0,D28),C28*D28) | F28: ⚠ ESTIMATIVA — trocar por orçamento
A29: Revestimento | B29: Piso, azulejos, argamassa, rejunte, rodapé | D29: 6000 | E29: =IF(OR(C29="",D29=""),IF(D29="",0,D29),C29*D29) | F29: ⚠ ESTIMATIVA — trocar por orçamento
A30: Pintura | B30: Tinta, selador, massa | D30: 2500 | E30: =IF(OR(C30="",D30=""),IF(D30="",0,D30),C30*D30) | F30: ⚠ ESTIMATIVA — trocar por orçamento
A31: Elétrica | B31: Fiação, conduítes, tomadas, luminárias | D31: 4500 | E31: =IF(OR(C31="",D31=""),IF(D31="",0,D31),C31*D31) | F31: ⚠ ESTIMATIVA — trocar por orçamento
A32: Ventilação | B32: Exaustores e dutos | D32: 1500 | E32: =IF(OR(C32="",D32=""),IF(D32="",0,D32),C32*D32) | F32: ⚠ ESTIMATIVA — trocar por orçamento
A33: Acessórios | B33: Porta-papel higiênico | C33: 6 | D33: 50 | E33: =IF(OR(C33="",D33=""),IF(D33="",0,D33),C33*D33)
A34: Acessórios | B34: Suporte papel-toalha | C34: 6 | D34: 50 | E34: =IF(OR(C34="",D34=""),IF(D34="",0,D34),C34*D34)
A35: Acessórios | B35: Lixeiras | C35: 11 | D35: 50 | E35: =IF(OR(C35="",D35=""),IF(D35="",0,D35),C35*D35)
A36: Mão de obra | B36: Pedreiro, servente, encanador, eletricista, azulejista, pintor | D36: 12000 | E36: =IF(OR(C36="",D36=""),IF(D36="",0,D36),C36*D36) | F36: ⚠ ESTIMATIVA — trocar por orçamento
B37: Subtotal reforma | E37: =SUM(E3:E36)
A39: 2) Eletrônicos / móveis
B40: Impressora | C40: 1 | D40: 1000 | E40: =IF(D40="",0,C40*D40) | F40: Confirmar necessidade
B41: Impressora 3D | C41: 1 | D41: 3500 | E41: =IF(D41="",0,C41*D41)
B42: Roteadores | C42: 2 | D42: 300 | E42: =IF(D42="",0,C42*D42)
B43: Switch | C43: 1 | D43: 500 | E43: =IF(D43="",0,C43*D43)
B44: Cabos de rede | C44: 1 | D44: 500 | E44: =IF(D44="",0,C44*D44)
B45: Rack | C45: 1 | D45: 800 | E45: =IF(D45="",0,C45*D45)
B46: NoBreak | C46: 1 | D46: 1200 | E46: =IF(D46="",0,C46*D46) | F46: ⚠ ESTIMATIVA — trocar por orçamento
B47: Videogame | C47: 1 | D47: 3000 | E47: =IF(D47="",0,C47*D47)
B48: Ar condicionado | C48: 3 | D48: 4000 | E48: =IF(D48="",0,C48*D48)
B49: Ventiladores | C49: 4 | D49: 300 | E49: =IF(D49="",0,C49*D49)
B50: Mesas | C50: 10 | D50: 300 | E50: =IF(D50="",0,C50*D50)
B51: Cadeiras | C51: 30 | D51: 150 | E51: =IF(D51="",0,C51*D51)
B52: Armários | C52: 2 | D52: 800 | E52: =IF(D52="",0,C52*D52)
B53: Estantes | C53: 3 | D53: 400 | E53: =IF(D53="",0,C53*D53)
B54: Gaveteiros | C54: 3 | D54: 300 | E54: =IF(D54="",0,C54*D54)
B55: Prateleiras | C55: 5 | D55: 150 | E55: =IF(D55="",0,C55*D55)
B56: Cafeteira | C56: 1 | D56: 160 | E56: =IF(D56="",0,C56*D56)
B57: Geladeira | C57: 1 | D57: 1700 | E57: =IF(D57="",0,C57*D57)
B58: Micro-ondas | C58: 1 | D58: 600 | E58: =IF(D58="",0,C58*D58)
... B60: Uniformes | C60: 10 | D60: 70 | E60: =IF(D60="",0,C60*D60)
B61: EPI | C61: 1 | D61: 500 | E61: =IF(D61="",0,C61*D61) | F61: ⚠ ESTIMATIVA — trocar por orçamento
B62: TVs | C62: 5 | D62: 1400 | E62: =IF(D62="",0,C62*D62)
B63: Subtotal eletrônicos/móveis | E63: =SUM(E40:E62)
A65: 3) Abertura (projetos, licenças, fachada…)
B66: Projeto arquitetônico / adequação à franquia | D66: 4000 | E66: =IF(D66="",0,D66) | F66: Confirmar: havia dúvida se era R$ 6.000
B67: Projeto elétrico, hidráulico e acessibilidade | D67: 3500 | E67: =IF(D67="",0,D67) | F67: ⚠ ESTIMATIVA — trocar por orçamento
B68: Alvarás/licenças/taxas municipais | D68: 2500 | E68: =IF(D68="",0,D68)
B69: AVCB/regularização de incêndio | D69: 3500 | E69: =IF(D69="",0,D69)
B70: Comunicação visual/fachada | D70: 8000 | E70: =IF(D70="",0,D70)
B71: Computadores adicionais | D71: 3520 | E71: =IF(D71="",0,D71)
B72: Instalação de ar-condicionado | D72: 3000 | E72: =IF(D72="",0,D72)
B73: Câmeras/CFTV | D73: 3000 | E73: =IF(D73="",0,D73)
B74: Alarme/controle de acesso | D74: 1800 | E74: =IF(D74="",0,D74)
B75: Mobiliário recepção/secretaria | D75: 5000 | E75: =IF(D75="",0,D75)
B76: Adequação acústica | D76: 3000 | E76: =IF(D76="",0,D76)
B77: Placas de sinalização e emergência | D77: 1000 | E77: =IF(D77="",0,D77)
B78: Extintores e equipamentos de emergência | D78: 1500 | E78: =IF(D78="",0,D78)
B79: Kit primeiros socorros | D79: 400 | E79: =IF(D79="",0,D79) | F79: ⚠ ESTIMATIVA — trocar por orçamento
B80: Subtotal abertura | E80: =SUM(E66:E79)
B82: Reserva para imprevistos (% da reforma + abertura) | E82: =(E37+E80)*Premissas!$B$62 | F82: Obras estouram: 15% é o mínimo recomendado.
B83: Investimento em obra + equipamentos + abertura | E83: =E37+E63+E80+E82
B84: Caução do imóvel (recuperável) | E84: 30000
B85: INVESTIMENTO TOTAL (obra + caução) | E85: =E83+E84
B87: Capital de giro necessário (pior caixa do Moderado) | E87: =MAX(0,-MIN('Cenário Moderado'!B49:S49))
B88: NECESSIDADE TOTAL DE CAPITAL | E88: =E85+E87

Sheet Resumo
A1: RESUMO — comparação dos cenários | B1: Pessimista | C1: Moderado | D1: Otimista
A2: Alunos no M16 | B2: ='Cenário Pessimista'!S7 | C2: ='Cenário Moderado'!S7 | D2: ='Cenário Otimista'!S7
A3: Professores no M16 | B3: ='Cenário Pessimista'!S8 | C3: ='Cenário Moderado'!S8 | D3: ='Cenário Otimista'!S8
A4: Alíquota efetiva do Simples no M16 | B4: ='Cenário Pessimista'!S20 | C4: ='Cenário Moderado'!S20 | D4: ='Cenário Otimista'!S20
A5: Receita recebida no M16 | B5: ='Cenário Pessimista'!S15 | C5: ='Cenário Moderado'!S15 | D5: ='Cenário Otimista'!S15
A6: Resultado no M16 | B6: ='Cenário Pessimista'!S48 | C6: ='Cenário Moderado'!S48 | D6: ='Cenário Otimista'!S48
A7: 1º mês com lucro | B7: =IFERROR(MATCH(TRUE,INDEX('Cenário Pessimista'!D48:S48>0,0),0),"—") | C7: =IFERROR(MATCH(TRUE,INDEX('Cenário Moderado'!D48:S48>0,0),0),"—") | D7: =IFERROR(MATCH(TRUE,INDEX('Cenário Otimista'!D48:S48>0,0),0),"—")
A8: Pior caixa operacional | B8: =MIN('Cenário Pessimista'!B49:S49) | C8: =MIN('Cenário Moderado'!B49:S49) | D8: =MIN('Cenário Otimista'!B49:S49)
A9: Mês do payback | B9: =IFERROR(MATCH(TRUE,INDEX('Cenário Pessimista'!D50:S50>=0,0),0),"não atinge") | C9: =IFERROR(MATCH(TRUE,INDEX('Cenário Moderado'!D50:S50>=0,0),0),"não atinge") | D9: =IFERROR(MATCH(TRUE,INDEX('Cenário Otimista'!D50:S50>=0,0),0),"não atinge")
A10: Caixa no M16 incl. investimento | B10: ='Cenário Pessimista'!S50 | C10: ='Cenário Moderado'!S50 | D10: ='Cenário Otimista'!S50
A12: Break-even de alunos | B12: =Premissas!B90
A13: Necessidade total de capital | B13: ='Investimento (CAPEX)'!E88
A14: Investimento (obra + caução) | B14: =INVEST_TOTAL
A15: Custos de implantação já lançados | B15: ='Análise de custos'!A3
